Workbook

Sheet Read Me
A1: FRANCE MASTER'S SHORTLIST – Études en France catalogue (pulled 9 Oct 2026)
A2: Profile | B2: 4-year bachelor's (≈ Bac+4) with ~3 years' experience as an embedded systems engineer in biomedical devices
A3: What was searched | B3: ALL programs in the official Études en France catalogue of these degree types: Master (national), Master of Science (MSc), Mastère en sciences, Mastère spécialisé, Master recherche/professionnel, Diplôme d'ingénieur, PhD — 7,911 listings. Filtered by field/sub-field (electronics, signal & imaging, telecom, systems, industrial computing, engineering, medicine…) and by keywords → 999 relevant programs kept (arts/law/business/pharma/chemistry etc. removed).
A4: Data pulled per program | B4: Title, school, city, language, entry level, entry year, duration, tuition fee entered by the school, application window, whether a separate school application is required, website, requirements, direct catalogue link.
A5: Missing fees | B5: About half the listings have no fee in the catalogue (mostly public universities). These were filled with researched rules: the 2026-27 national fee decree, each university's exemption policy, and official school fee pages (sources in column "Fee basis" and the Sources sheet). "Fee confidence" tells you how sure the figure is.
A7: KEY FINDINGS
A8: 1. Cheapest route = public universities | B8: A national Master at a public university costs €3,950/yr for non-EU students in 2026-27 (official, service-public.gouv.fr). With an exemption it drops to ~€254-255/yr. Private schools and "MSc" programs cost €5,000-€18,000/yr.
A9: 2. BIG 2026 change: exemptions are now capped | B9: Decree n° 2026-385 (19 May 2026) caps fee exemptions at 30% of non-EU students per university in 2026-27, 25% in 2027-28 (your intake), 20% later. So budget €3,950/yr and treat €255 as a bonus. Apply for exemption at the same time as admission.
A10: 3. Most generous universities (2026-27) | B10: Sorbonne Université (says it can exempt all eligible applicants), Université de Toulouse (partial exemption for all), Université Grenoble Alpes / Grenoble INP (broad exemptions in 2026-27), Université de Lille (continues exemptions). See "University fee policies" sheet. Policies for Sept 2027 will be voted in spring/summer 2027 – re-check.
A11: 4. Your eligibility | B11: A 4-year bachelor's is usually treated as Bac+4 → you can enter Master year 1 (M1) almost everywhere, and many M2/MSc that accept Bac+4. Programs requiring Bac+5 (a Master) are marked red. Mastère Spécialisé (MS) accepts Bac+4 + 3 yrs experience — exactly your profile, but MS programs are expensive (€9k-€23k).
A12: 5. Grades | B12: Public French masters select on grades. If yours are average, compensate with: a strong SOP linking your embedded/biomedical work to the program, experience letters, a project portfolio (firmware, signal processing), a good IELTS (6.5+) and, for French-taught programs, a DELF/TCF B2. Apply widely (the EEF portal allows several choices).
A13: 6. "Reprise d'études" warning | B13: Some universities treat applicants who stopped studying 2+ years ago for work as "continuing education" with higher fees (e.g. Université de Pau states min €3,950+ for students resuming after a 2-yr break). Ask each university whether you will be enrolled under "formation initiale" before accepting.
A14: 7. Language | B14: Most cheap public masters are taught in FRENCH (B2 required). English-taught options are on the "English-taught" sheet. Learning French to B2 opens ~3x more low-fee options.
A15: 8. Apprenticeship programs | B15: Listings run by CFA/ITII (apprenticeship) are free to the student but need a French employer contract and residence permit — not realistic from abroad. Kept for completeness, marked in "Institution type".
A16: 9. PhD | B16: Only 1 relevant PhD listing appears in the catalogue. A French PhD needs a Master first; doctorate fee is €397/yr and PhDs are normally salaried (≈€2,100+/month gross). Plan: Master now → PhD later.
A17: 10. Deadlines | B17: Études en France applications for Sept 2027 are open in the catalogue from 1 Oct 2026 to 15 Mar 2027 (many schools close earlier, and "Extra school application" = Yes means you must ALSO apply on the school's own platform).
A19: SHEETS
A20: Top Picks (low fee) | B20: 261 programs: relevance ≥4, you are eligible, open, and could cost ≤ €6,000/yr. Start here.
A21: English-taught | B21: 192 open, eligible programs taught fully or partly in English.
A22: All Programs | B22: All 999 relevant programs, sorted by relevance → eligibility → lowest fee. Use the filter arrows.
A23: University fee policies | B23: 2026-27 exemption policy per university, with official sources.
A24: Summary | B24: Counts by field and fee band (live formulas on the All Programs sheet).
A25: Sources | B25: All official pages used.
A27: COLOUR LEGEND | B27: Fee: green ≤ €1,000 · yellow €1,001-6,000 · red > €6,000. Eligibility: green = eligible on level · red = needs a Master.
A28: Relevance | B28: ★★★★★ embedded / biomedical / health tech · ★★★★ electronics, signal, robotics, IoT, sensors · ★★★ AI, data, CS, cyber, energy · ★★ other engineering
A29: Est. total tuition | B29: Formula: Est. tuition per year × Years to finish (formula). Years are estimated from entry year (M1 entry = 2 yrs, M2 entry = 1 yr).
A30: Disclaimer | B30: Fees and policies change yearly; figures are 2026-27 (latest published). Always confirm on the school website before paying any deposit. Living costs (~€700-1,100/month, Campus France "proof of funds" ≈ €615/month) and CVEC (~€105) are extra.

Sheet Top Picks (low fee)
A1: # | B1: Relevance | C1: Relevance note | D1: Field (category) | E1: Program title (as in Études en France) | F1: Approx. English title (auto-translated) | G1: Degree type | H1: Institution / faculty | I1: University / group | J1: Campus / site | K1: City / postcode | L1: Institution type | M1: Teaching language | N1: Catalogue | O1: Entry level required | P1: Your eligibility (4-yr BS, 3 yrs exp.) | Q1: Entry year(s) | R1: Duration (months, per catalogue) | S1: Est. tuition / year non-EU (€) | T1: Lowest possible with exemption (€) | U1: Years to finish (est.) | V1: Est. total tuition (€) | W1: Fee basis & source | X1: Fee confidence | Y1: Fees found in catalogue (€) | Z1: Fee note from catalogue text | AA1: University exemption policy 2026-27 | AB1: Policy source | AC1: EEF status | AD1: Apply from | AE1: Apply until (EEF) | AF1: Extra school application required? | AG1: Program website | AH1: Requirements (excerpt) | AI1: Catalogue link
A2: 1 | B2: ★★★★★ | C2: 5 – Core fit (embedded/biomedical/health tech) | D2: IoT / Telecom / Networks | E2: Master indifférencié (recherche et professionnel) Master Computer Networks and IoT Systems | F2: Master Computer Networks and IoT Systems | G2: Master indifférencié (recherche et professionnel) | H2: Conservatoire national des arts et métiers - CNAM | J2: Cnam Etablissement Public - EPN5 Computer Science | K2: 75003 Paris | L2: Public school / institute | M2: English | N2: Taught in English | O2: Bac +4 / Bac +5 | P2: Eligible on level (4-yr BS ≈ Bac+4) | Q2: 1/2 | R2: 12 | S2: 3950 | T2: 255 | U2: 2 | V2: =IF(S2="","",S2*U2) | W2: Catalogue: €3,770. = national differentiated master fee (2026-27: €3,950). Exemption to ~€255 possible (university quota). | X2: High | Y2: 3770 | AC2: Open | AD2: 2026-10-01 | AE2: 2027-03-15 | AF2: Yes | AG2: https://master.roc.cnam.fr | AH2: International, European and French students willing to pursue a master degree in English, and possessing a Bachelor-level degree in one of these fields: Computer Science, Electronics, Computer Engineering, Electrical Eng | AI2: Open in EEF
A3: 2 | B3: ★★★★★ | C3: 5 – Core fit (embedded/biomedical/health tech) | D3: Biomedical / Health tech | E3: Master indifférencié (recherche et professionnel) mention Biomedical Engineering (BME) | F3: major: Biomedical Engineering (BME) | G3: Master indifférencié (recherche et professionnel) | H3: UFR des Sciences pharmaceutiques et biologiques | I3: Université de Montpellier | J3: Site de Montpellier | K3: 34090 Montpellier | L3: Public university | M3: English | N3: Taught in English | O3: Bac +4 | P3: Eligible on level (4-yr BS ≈ Bac+4) | Q3: 1 | R3: 12 | S3: 3950 | T3: 255 | U3: 2 | V3: =IF(S3="","",S3*U3) | W3: Not in catalogue. Public national master → 2026-27 differentiated fee €3,950; exemption to ~€254-255 depends on university quota (25% cap in 2027-28). | X3: Medium | AA3: Montpellier 2026-27: new non-EU entrants pay the differentiated fee unless individual exemption (limited). | AB3: https://www.umontpellier.fr/en/international/etudier-a-letranger/etudiants-internationaux-annee-universitaire-2026-2027/ | AC3: Open | AD3: 2026-10-01 | AE3: 2027-03-15 | AF3: No | AG3: https://idil.edu.umontpellier.fr/master-idil/les-parcours/ | AH3: Conditions d’accès Diplôme de licence dans la discipline choisie IDIL Niveau d’anglais B2 minimum CV et lettre de motivation 2 lettres de soutien d’un chercheur et/ou professeur (recommandé, mais non obligatoire) Estimat | AI3: Open in EEF
A4: 3 | B4: ★★★★★ | C4: 5 – Core fit (embedded/biomedical/health tech) | D4: Embedded systems / Electronics | E4: Master indifférencié (recherche et professionnel) mention Electronique, énergies électriques et automatique* parcours Electronique, Outils Libres pour l'instrumentation et les Systèmes Embarqués (ELISE) * | F4: major: Electronics, Energies Electrical & Automation* – track: Electronics, Outils Libres for Instrumentation & the Embedded Systems (ELISE) * | G4: Master indifférencié (recherche et professionnel) | H4: UFR Sciences et Techniques | I4: Université Marie et Louis Pasteur | J4: Site de Besançon | K4: 25030 BESANCON CEDEX | L4: Public university | M4: English | N4: Taught in English | O4: Bac +4 | P4: Eligible on level (4-yr BS ≈ Bac+4) | Q4: 1 | S4: 3950 | T4: 255 | U4: 2 | V4: =IF(S4="","",S4*U4) | W4: Not in catalogue. Public national master → 2026-27 differentiated fee €3,950; exemption to ~€254-255 depends on university quota (25% cap in 2027-28). | X4: Medium | AA4: UMLP: individual exemption requests assessed on personal resources. | AB4: https://www.umlp.fr/sites/default/files/2026-07-02-page-droits-differencies-vf.pdf | AC4: Open | AD4: 2026-10-01 | AE4: 2027-03-15 | AF4: No | AG4: https://formations.univ-fcomte.fr/fr/formations/feuilleter-le-catalogue/master-lmd-XB/master-electronique-energie-electrique-automatique-M4QUAZ0D.html | AH4: C langage programming, digital electronics, microcontroller programming, analog electronics, instrumentation, Python programming, signal processing, mathematics (basic algebra and analysis), Linux operating system Langue | AI4: Open in EEF
A5: 4 | B5: ★★★★★ | C5: 5 – Core fit (embedded/biomedical/health tech) | D5: Biomedical / Health tech | E5: Master indifférencié (recherche et professionnel) Sciences, Technologies, Santé mention Biologie Santé parcours Bioingénierie Moléculaire et Cellulaire | F5: Science, Technology, Health (STS) – major: Biology-Health – track: Bioengineering Molecular & Cellular | G5: Master indifférencié (recherche et professionnel) | H5: UFR de Chimie et Biologie | I5: Université de Grenoble Alpes | J5: Site de Grenoble - Campus de Saint Martin d'Hères | L5: Public university | M5: English | N5: Taught in English | O5: Bac +4 | P5: Eligible on level (4-yr BS ≈ Bac+4) | Q5: 1 | S5: 3950 | T5: 255 | U5: 2 | V5: =IF(S5="","",S5*U5) | W5: Not in catalogue. Public national master → 2026-27 differentiated fee €3,950; exemption to ~€254-255 depends on university quota (25% cap in 2027-28). | X5: Medium | AA5: UGA (incl. Grenoble INP masters): 2026-27 broad exemptions on request (pay national €254). From 2027-28 the decree caps apply; exemptions based on resources. | AB5: https://www.univ-grenoble-alpes.fr/actualites/a-la-une/actualites-universite/etudiants-internationaux-ce-que-change-le-nouveau-decret-sur-les-droits-d-inscription-a-l-uga-1775870.kjsp | AC5: Open | AD5: 2026-10-01 | AE5: 2027-03-15 | AF5: No | AG5: https://formations.univ-grenoble-alpes.fr/fr/offre-de-formation/master-XB/master-biologie-sante-IAQKB0GE/parcours-molecular-and-cellular-biology-1re-annee-IK43J2QV.html | AH5: The "Bioingénierie Moléculaire et Cellulaire" M1 program is open to students having completed a bachelor’s degree in Sciences or are enrolled in the ﬁnal semester of a bachelor’s program in Sciences with a solid backgrou | AI5: Open in EEF
A6: 5 | B6: ★★★★★ | C6: 5 – Core fit (embedded/biomedical/health tech) | D6: Biomedical / Health tech | E6: Master indifférencié (recherche et professionnel) Sciences, Technologies, Santé mention Ingénierie de la santé parcours Bio Health Engineering | F6: Science, Technology, Health (STS) – major: Health Engineering – track: Bio Health Engineering | G6: Master indifférencié (recherche et professionnel) | H6: UFR Médecine - Pharmacie | I6: Université de Grenoble Alpes | J6: Site de Grenoble - Campus de La Merci - La Tronche | L6: Public university | M6: English | N6: Taught in English | O6: Bac +4 / Bac +5 | P6: Eligible on level (4-yr BS ≈ Bac+4) | Q6: 1/2 | S6: 3950 | T6: 255 | U6: 2 | V6: =IF(S6="","",S6*U6) | W6: Not in catalogue. Public national master → 2026-27 differentiated fee €3,950; exemption to ~€254-255 depends on university quota (25% cap in 2027-28). | X6: Medium | AA6: UGA (incl. Grenoble INP masters): 2026-27 broad exemptions on request (pay national €254). From 2027-28 the decree caps apply; exemptions based on resources. | AB6: https://www.univ-grenoble-alpes.fr/actualites/a-la-une/actualites-universite/etudiants-internationaux-ce-que-change-le-nouveau-decret-sur-les-droits-d-inscription-a-l-uga-1775870.kjsp | AC6: Open | AD6: 2026-10-01 | AE6: 2027-03-15 | AF6: No | AG6: https://formations.univ-grenoble-alpes.fr/fr/catalogue-2021/master-XB/master-ingenierie-de-la-sante-IAQKSXOB.html | AH6: Requirement M1: - Strong theoritical and practical skills in biology or biochemistry or pharmaceutical sciences or biotechnologies. - B2 level in english mandatory. Requirement M2: - Strong theoritical and practical skil | AI6: Open in EEF
A7: 6 | B7: ★★★★★ | C7: 5 – Core fit (embedded/biomedical/health tech) | D7: Biomedical / Health tech | E7: Master indifférencié (recherche et professionnel) Sciences, technologies, santé mention sciences du vivant parcours Biomedical and Computational Sciences in Ageing (imAGEin) | F7: Science, Technology, Health (STS) – major: Sciences of Life – track: Biomedical and Computational Sciences in Ageing (imAGEin) | G7: Master indifférencié (recherche et professionnel) | H7: Sciences | I7: Université Côte d'Azur | J7: Site de Nice | L7: Public university | M7: English | N7: General | O7: Bac +3 | P7: Eligible on level (4-yr BS ≈ Bac+4) | Q7: 1 | S7: 3950 | T7: 255 | U7: 2 | V7: =IF(S7="","",S7*U7) | W7: Not in catalogue. Public national master → 2026-27 differentiated fee €3,950; exemption to ~€254-255 depends on university quota (25% cap in 2027-28). | X7: Medium | AC7: Open | AD7: 2026-10-01 | AE7: 2027-03-15 | AF7: Yes | AG7: https://life.univ-cotedazur.fr/international/imagein | AH7: Consulter le site web | AI7: Open in EEF
A8: 7 | B8: ★★★★★ | C8: 5 – Core fit (embedded/biomedical/health tech) | D8: IoT / Telecom / Networks | E8: Master Sciences, technologies, santé mention informatique parcours Internet of Things | F8: Master Science, Technology, Health (STS) – major: Computer Science – track: Internet of Things | G8: Master indifférencié (recherche et professionnel) | H8: UFR Sciences, Techniques et Gestion de l'Industrie | I8: Université Marie et Louis Pasteur | J8: Site de Montbéliard | K8: 25211 MONTBELIARD CEDEX | L8: Public university | M8: English | N8: General | O8: Bac +4 / Bac +5 | P8: Eligible on level (4-yr BS ≈ Bac+4) | Q8: 1/2 | R8: 12 | S8: 3950 | T8: 255 | U8: 2 | V8: =IF(S8="","",S8*U8) | W8: Not in catalogue. Public national master → 2026-27 differentiated fee €3,950; exemption to ~€254-255 depends on university quota (25% cap in 2027-28). | X8: Medium | Z8: (Pour information, le montant de la CVEC, pour la rentrée 2026-2027, était de 105€) … (Pour information, le montant de la CVEC, pour la rentrée 2025-2026, était de 105€) | AA8: UMLP: individual exemption requests assessed on personal resources. | AB8: https://www.umlp.fr/sites/default/files/2026-07-02-page-droits-differencies-vf.pdf | AC8: Open | AD8: 2026-10-01 | AE8: 2027-03-15 | AF8: No | AG8: https://stgi.umlp.fr/ | AH8: Le Master Internet of Things (IOT) est un Master en Informatique spécialisé dans le développement des objets communiquants. Il est attendu des candidats en M1 : Licence Informatique avec de bonnes connaissances en algori | AI8: Open in EEF
A9: 8 | B9: ★★★★★ | C9: 5 – Core fit (embedded/biomedical/health tech) | D9: Biomedical / Health tech | E9: Master indifférencié (recherche et professionnel) Sciences, technologies, santé mention Biotechnologies parcours Biomédicaments : conception et production | F9: Science, Technology, Health (STS) – major: Biotechnologies – track: Biodrugs : Design & Production | G9: Master indifférencié (recherche et professionnel) | H9: Faculté de pharmacie | I9: Université de Strasbourg | J9: Site de Illkirch-Graffenstaden | L9: Public university | M9: French & English | N9: General | O9: Bac +4 | P9: Eligible on level (4-yr BS ≈ Bac+4) | Q9: 1 | S9: 3950 | T9: 255 | U9: 2 | V9: =IF(S9="","",S9*U9) | W9: Catalogue: €3,950. = national differentiated master fee (2026-27: €3,950). Exemption to ~€255 possible (university quota). | X9: High | Y9: 3950 | AA9: Unistra: master entrants who did not do their licence at Unistra pay the differentiated fee (€3,950). | AB9: https://www.unistra.fr/fr/node/8168 | AC9: Open | AD9: 2026-10-01 | AE9: 2027-03-15 | AF9: No | AG9: https://pharmacie.unistra.fr | AH9: Entrée en M1 avoir effectué un curus en : - biologie cellulaire et moléculaire, biochimie, - avoir des bases en chimie Entrée en M2 avoir effectué un cursus en - biologie moléculaire et cellulaire avancée, - avoir des ba | AI9: Open in EEF
A10: 9 | B10: ★★★★★ | C10: 5 – Core fit (embedded/biomedical/health tech) | D10: Biomedical / Health tech | E10: Master indifférencié (recherche et professionnel) Sciences, technologies, santé mention sciences du vivant parcours Bioinformatique et Bioimagerie Structurale | F10: Science, Technology, Health (STS) – major: Sciences of Life – track: Bioinformatics & Bioimagerie Structural | G10: Master indifférencié (recherche et professionnel) | H10: Faculté des sciences de la vie | I10: Université de Strasbourg | J10: Site de Strasbourg | K10: 67000 Strasbourg | L10: Public university | M10: French & English | N10: General | O10: Bac +4 / Bac +5 | P10: Eligible on level (4-yr BS ≈ Bac+4) | Q10: 1/2 | S10: 3950 | T10: 255 | U10: 2 | V10: =IF(S10="","",S10*U10) | W10: Catalogue: €3,950. = national differentiated master fee (2026-27: €3,950). Exemption to ~€255 possible (university quota). | X10: High | Y10: 3950 | AA10: Unistra: master entrants who did not do their licence at Unistra pay the differentiated fee (€3,950). | AB10: https://www.unistra.fr/fr/node/8168 | AC10: Open | AD10: 2026-10-01 | AE10: 2027-03-15 | AF10: No | AG10: http://sciencesvie.unistra.fr/ | AH10: M1 : Cette formation s’adresse aux étudiants désirant acquérir une formation pluridisciplinaire alliant une culture biologique à une maîtrise ou une expertise de plusieurs outils et méthodes informatiques, bioinformatiqu | AI10: Open in EEF
A11: 10 | B11: ★★★★★ | C11: 5 – Core fit (embedded/biomedical/health tech) | D11: IoT / Telecom / Networks | E11: Master indifférencié (recherche et professionnel) Sciences, technologies, santé mention Traitement du signal et des images parcours EUR Smart IoT | F11: Science, Technology, Health (STS) – major: Signal & Image Processing – track: EUR Smart IoT | G11: Master indifférencié (recherche et professionnel) | H11: UFR de sciences fondamentales et appliquées - Université de Poitiers | I11: Université de Poitiers | J11: Site de Poitiers | L11: Public university | M11: French & English | N11: Taught in English | O11: Bac +4 / Bac +5 | P11: Eligible on level (4-yr BS ≈ Bac+4) | Q11: 1/2 | S11: 3950 | T11: 255 | U11: 2 | V11: =IF(S11="","",S11*U11) | W11: Catalogue: €3,950. = national differentiated master fee (2026-27: €3,950). Exemption to ~€255 possible (university quota). | X11: High | Y11: 3950 | AC11: Open | AD11: 2026-10-01 | AE11: 2027-03-15 | AF11: No | AG11: https://www.unilim.fr/gradschool-ceramics-ict/formation/smart-iot/ | AH11: Year 1 The admissions committee will focus in particular on the candidate’s grades in subjects related to the intended field of study and on the candidate’s ability to articulate their motivations and career goals. Minim | AI11: Open in EEF
A12: 11 | B12: ★★★★★ | C12: 5 – Core fit (embedded/biomedical/health tech) | D12: Biomedical / Health tech | E12: Master Sciences, technologies, santé, mention Ingéniérie de la santé parcours Biomatériaux et bio ingénierie pour la santé | F12: Master Science, Technology, Health (STS), – major: Engineering of the Health – track: Biomaterials & bio Engineering for Health | G12: Master indifférencié (recherche et professionnel) | H12: Faculté de chirurgie dentaire | I12: Université de Strasbourg | J12: Site de Strasbourg | L12: Public university | M12: French & English | N12: General | O12: Bac +4 / Bac +5 | P12: Eligible on level (4-yr BS ≈ Bac+4) | Q12: 1/2 | S12: 3950 | T12: 255 | U12: 2 | V12: =IF(S12="","",S12*U12) | W12: Catalogue: €3,950. = national differentiated master fee (2026-27: €3,950). Exemption to ~€255 possible (university quota). | X12: High | Y12: 3950 | AA12: Unistra: master entrants who did not do their licence at Unistra pay the differentiated fee (€3,950). | AB12: https://www.unistra.fr/fr/node/8168 | AC12: Open | AD12: 2026-10-01 | AE12: 2027-03-15 | AF12: No | AG12: https://chirurgie-dentaire.unistra.fr/ | AH12: Formation à enseignement mixte : français/anglais. Niveau de langue (anglais B1, français C1) | AI12: Open in EEF
A13: 12 | B13: ★★★★★ | C13: 5 – Core fit (embedded/biomedical/health tech) | D13: Biomedical / Health tech | E13: Master Sciences, technologies, santé, mention Ingénierie de la santé parcours Jumeaux numériques pour la santé | F13: Master Science, Technology, Health (STS), – major: Health Engineering – track: Jumeaux Digital for the Health | G13: Master indifférencié (recherche et professionnel) | H13: Université de technologie de Compiègne | J13: Site de Compiègne | L13: Public university | M13: French & English | N13: General | O13: Bac +4 / Bac +5 | P13: Eligible on level (4-yr BS ≈ Bac+4) | Q13: 1/2 | S13: 3950 | T13: 255 | U13: 2 | V13: =IF(S13="","",S13*U13) | W13: Catalogue: €3,950. = national differentiated master fee (2026-27: €3,950). Exemption to ~€255 possible (university quota). | X13: High | Y13: 3950 | AC13: Open | AD13: 2026-10-01 | AE13: 2027-03-15 | AF13: No | AH13: Parcours DTH Mentions de licences conseillées : Informatique Mathématiques Physique Mécanique Sciences et technologies Sciences pour l'ingénieur Attendus : Avoir des compétences en mathématiques appliquées, en mécanique | AI13: Open in EEF
A14: 13 | B14: ★★★★★ | C14: 5 – Core fit (embedded/biomedical/health tech) | D14: Biomedical / Health tech | E14: Master indifférencié (recherche et professionnel) Sciences, technologies, santé mention Electronique, énergie électrique, automatique parcours Ingénierie pour la santé | F14: Science, Technology, Health (STS) – major: Electronics, Electrical Energy & Automation (EEA) – track: Engineering for Health | G14: Master indifférencié (recherche et professionnel) | H14: Sciences et Ingénierie | I14: Sorbonne Université | J14: Site de Paris | L14: Public university | M14: French & English | N14: General | O14: Bac +4 / Bac +5 | P14: Eligible on level (4-yr BS ≈ Bac+4) | Q14: 1/2 | S14: 3950 | T14: 255 | U14: 2 | V14: =IF(S14="","",S14*U14) | W14: Not in catalogue. Public national master → 2026-27 differentiated fee €3,950; exemption to ~€254-255 depends on university quota (25% cap in 2027-28). | X14: Medium | AA14: Board vote 7 Jul 2026: Sorbonne Université says it can exempt all eligible non-EU applicants (pay same as EU, ~€254) for 2026-27. | AB14: https://www.sorbonne-universite.fr/actualites/le-conseil-dadministration-de-sorbonne-universite-vote-lunanimite-le-7-juillet-2026-sa | AC14: Open | AD14: 2026-10-01 | AE14: 2027-03-15 | AF14: No | AG14: https://masters-sdi.sorbonne-universite.fr/electronique-energie-electrique-automatique | AI14: Open in EEF
A15: 14 | B15: ★★★★★ | C15: 5 – Core fit (embedded/biomedical/health tech) | D15: Embedded systems / Electronics | E15: Master indifférencié (recherche et professionnel) Sciences, technologies, santé mention Electronique, énergie électrique, automatique parcours Microélectronique Intégration des Systèmes Temps Réels et Embarqués (EEA MISTRE) | F15: Science, Technology, Health (STS) – major: Electronics, Electrical Energy & Automation (EEA) – track: Microelectronics Integration of Systems Real-Times & Embedded (EEA MISTRE) | G15: Master indifférencié (recherche et professionnel) | H15: UFR de Physique, ingénierie, terre, environnement, mécanique | I15: Université de Grenoble Alpes | J15: Site de Grenoble - Polygone scientifique - GreEn-ER | L15: Public university | M15: French & English | N15: General | O15: Bac +4 / Bac +5 | P15: Eligible on level (4-yr BS ≈ Bac+4) | Q15: 1/2 | S15: 3950 | T15: 255 | U15: 2 | V15: =IF(S15="","",S15*U15) | W15: Not in catalogue. Public national master → 2026-27 differentiated fee €3,950; exemption to ~€254-255 depends on university quota (25% cap in 2027-28). | X15: Medium | AA15: UGA (incl. Grenoble INP masters): 2026-27 broad exemptions on request (pay national €254). From 2027-28 the decree caps apply; exemptions based on resources. | AB15: https://www.univ-grenoble-alpes.fr/actualites/a-la-une/actualites-universite/etudiants-internationaux-ce-que-change-le-nouveau-decret-sur-les-droits-d-inscription-a-l-uga-1775870.kjsp | AC15: Open | AD15: 2026-10-01 | AE15: 2027-03-15 | AF15: No | AG15: https://formations.univ-grenoble-alpes.fr/fr/catalogue-2021/master-XB/master-electronique-energie-electrique-automatique-IFZ3DRB9/parcours-microelectronique-integration-des-systemes-temps-reels-embarques-mistre-1re-et-2e-annees-IFZ5TP7C.html | AH15: Master 1 : - Les candidats titulaires d'un diplôme de BAC+5 au moment de la candidature ne seront pas admis en master 1. Seules les candidatures de BAC+3 ou BAC+4 seront considérées. - Prérequis : Electronique, automatiq | AI15: Open in EEF
A16: 15 | B16: ★★★★★ | C16: 5 – Core fit (embedded/biomedical/health tech) | D16: Embedded systems / Electronics | E16: Master indifférencié (recherche et professionnel) Sciences, technologies, santé mention Electronique, énergie électrique, automatique parcours Systèmes Communicants | F16: Science, Technology, Health (STS) – major: Electronics, Electrical Energy & Automation (EEA) – track: Systems Communicating | G16: Master indifférencié (recherche et professionnel) | H16: Sciences et Ingénierie | I16: Sorbonne Université | J16: Site de Paris | L16: Public university | M16: French & English | N16: General | O16: Bac +4 / Bac +5 | P16: Eligible on level (4-yr BS ≈ Bac+4) | Q16: 1/2 | S16: 3950 | T16: 255 | U16: 2 | V16: =IF(S16="","",S16*U16) | W16: Not in catalogue. Public national master → 2026-27 differentiated fee €3,950; exemption to ~€254-255 depends on university quota (25% cap in 2027-28). | X16: Medium | AA16: Board vote 7 Jul 2026: Sorbonne Université says it can exempt all eligible non-EU applicants (pay same as EU, ~€254) for 2026-27. | AB16: https://www.sorbonne-universite.fr/actualites/le-conseil-dadministration-de-sorbonne-universite-vote-lunanimite-le-7-juillet-2026-sa | AC16: Open | AD16: 2026-10-01 | AE16: 2027-03-15 | AF16: No | AG16: https://masters-sdi.sorbonne-universite.fr/electronique-energie-electrique-automatique | AI16: Open in EEF
A17: 16 | B17: ★★★★★ | C17: 5 – Core fit (embedded/biomedical/health tech) | D17: Biomedical / Health tech | E17: Master Sciences de la santé mention Ingénierie de la santé | F17: Master Sciences of the Health – major: Health Engineering | G17: Master indifférencié (recherche et professionnel) | H17: UFR des Sciences Fondamentales et Biomédicales | I17: Université Paris Cité | J17: Site de Paris | K17: 75006 Paris | L17: Public university | M17: French & English | N17: General | O17: Bac +4 | P17: Eligible on level (4-yr BS ≈ Bac+4) | Q17: 1 | S17: 3950 | T17: 255 | U17: 2 | V17: =IF(S17="","",S17*U17) | W17: Not in catalogue. Public national master → 2026-27 differentiated fee €3,950; exemption to ~€254-255 depends on university quota (25% cap in 2027-28). | X17: Medium | AA17: Paris Cité historically exempted non-EU master students (paid EU rate). 2026-27/2027-28 policy not yet published – confirm. | AB17: https://u-paris.fr/droits-dinscription-tarifs-exonerations/ | AC17: Open | AD17: 2026-10-01 | AE17: 2027-03-15 | AF17: Yes | AG17: https://odf.u-paris.fr/fr/offre-de-formation/master-XB/sciences-technologies-sante-STS/ingenierie-de-la-sante-K2NDJ7KW.html | AH17: All courses are taught in English, so candidates must demonstrate a perfect command of English (C1 level certificate required) with no French prerequisites for non-French speaking students. Candidates must: - excel in th | AI17: Open in EEF
A18: 17 | B18: ★★★★★ | C18: 5 – Core fit (embedded/biomedical/health tech) | D18: Embedded systems / Electronics | E18: Master indifférencié (recherche et professionnel) Sciences et technologies mention Electronique, énergie électrique, automatique parcours Systèmes Embarqués (SE) | F18: Science & Technology – major: Electronics, Electrical Energy & Automation (EEA) – track: Embedded Systems (SE) | G18: Master indifférencié (recherche et professionnel) | H18: Campus scientifique de BEAULIEU | I18: Université de Rennes | J18: Site de Rennes - ISTIC | K18: 35042 RENNES Cedex | L18: Public university | M18: French | N18: General | O18: Bac +4 | P18: Eligible on level (4-yr BS ≈ Bac+4) | Q18: 1 | R18: 12 | S18: 3950 | T18: 255 | U18: 2 | V18: =IF(S18="","",S18*U18) | W18: Catalogue: €3,950. = national differentiated master fee (2026-27: €3,950). Exemption to ~€255 possible (university quota). | X18: High | Y18: 3950 | Z18: ue, il faudra vous acquitter obligatoirement des frais d'inscription d'un montant de 3950 euros pour vous inscrire dans la formation | AC18: Open | AD18: 2026-10-01 | AE18: 2027-03-15 | AF18: No | AG18: https://istic.univ-rennes.fr/master-eeea-electronique-energie-electrique-automatique | AH18: Prérequis :Les candidats doivent disposer de bases solides en électronique analogique et numérique, en outils mathématiques pour le traitement du signal ainsi qu'en programmation. Profil attendu : Etudiant.e de niveau Ba | AI18: Open in EEF
A19: 18 | B19: ★★★★★ | C19: 5 – Core fit (embedded/biomedical/health tech) | D19: Embedded systems / Electronics | E19: Master indifférencié (recherche et professionnel) Sciences, technologies, santé mention génie industriel parcours Systèmes Embarqués et Technologies d'Intelligence Artificielle | F19: Science, Technology, Health (STS) – major: Industrial Engineering – track: Embedded Systems & Technologies d'Artificial Intelligence | G19: Master indifférencié (recherche et professionnel) | H19: Institut supérieur des sciences et techniques | I19: Université Picardie Jules Verne Amiens | J19: Site de Saint-Quentin | K19: 02315 Saint Quentin cedex | L19: Public school / institute | M19: French | N19: General | O19: Bac +4 | P19: Eligible on level (4-yr BS ≈ Bac+4) | Q19: 1 | R19: 12 | S19: 3950 | T19: 255 | U19: 2 | V19: =IF(S19="","",S19*U19) | W19: Catalogue: €3,950. = national differentiated master fee (2026-27: €3,950). Exemption to ~€255 possible (university quota). | X19: High | Y19: 3950 | AC19: Open | AD19: 2026-10-01 | AE19: 2027-03-15 | AF19: No | AG19: https://www.insset.u-picardie.fr/ | AH19: Niveau de test de compétence en Francais requis B2 Le tarif indiqué est celui de l'année universitaire 2026/2027 et, est susceptible d'etre modifié pour la rentrée 2027/2028 Pré-requis nécessaires en programmation inform | AI19: Open in EEF
A20: 19 | B20: ★★★★★ | C20: 5 – Core fit (embedded/biomedical/health tech) | D20: Embedded systems / Electronics | E20: Master indifférencié (recherche et professionnel) Sciences, technologies, santé mention informatique parcours LSE : logiciel pour systèmes embarqués | F20: Science, Technology, Health (STS) – major: Computer Science – track: LSE : Software for Embedded Systems | G20: Master indifférencié (recherche et professionnel) | H20: UFR sciences et techniques | I20: Université de Bretagne Occidentale | J20: Site de Brest | L20: Public university | M20: French | N20: General | O20: Bac +4 / Bac +5 | P20: Eligible on level (4-yr BS ≈ Bac+4) | Q20: 1/2 | R20: 12 | S20: 3950 | T20: 255 | U20: 2 | V20: =IF(S20="","",S20*U20) | W20: Catalogue: €3,950. = national differentiated master fee (2026-27: €3,950). Exemption to ~€255 possible (university quota). | X20: High | Y20: 3950 | AC20: Open | AD20: 2026-10-01 | AE20: 2027-03-15 | AF20: No | AG20: http://www.univ-brest.fr/ufr-sciences | AH20: L'université de Bretagne occidentale demande de présenter un Test de connaissance en français pour tous les candidats dont une des langues officielles n'est pas le français. Pour les pays où le français n'est pas la seul | AI20: Open in EEF
A21: 20 | B21: ★★★★★ | C21: 5 – Core fit (embedded/biomedical/health tech) | D21: Biomedical / Health tech | E21: Master indifférencié (recherche et professionnel) Sciences, technologies, santé mention Ingénierie de la santé parcours Technologies biomédicales et territoires de santé | F21: Science, Technology, Health (STS) – major: Health Engineering – track: Technologies biomédicales & Territories of Health | G21: Master indifférencié (recherche et professionnel) | H21: Université de technologie de Compiègne | J21: Site de Compiègne | L21: Public university | M21: French | N21: General | O21: Bac +4 / Bac +5 | P21: Eligible on level (4-yr BS ≈ Bac+4) | Q21: 1/2 | S21: 3950 | T21: 255 | U21: 2 | V21: =IF(S21="","",S21*U21) | W21: Catalogue: €3,950. = national differentiated master fee (2026-27: €3,950). Exemption to ~€255 possible (university quota). | X21: High | Y21: 3950 | AC21: Open | AD21: 2026-10-01 | AE21: 2027-03-15 | AF21: No | AG21: https://www.utc.fr/formations/diplome-de-master/mention-ingenierie-de-la-sante-ids/parcours-technologies-biomedicales-et-territoires-de-sante-tbts/ | AH21: Pour les parcours DMAR et TBTS Attention, le recrutement en M1 est commun. Ainsi, en candidatant sur l’un vous candidatez également sur l’autre, pas besoin de déposer votre dossier de candidature deux fois. Mentions de l | AI21: Open in EEF
A22: 21 | B22: ★★★★★ | C22: 5 – Core fit (embedded/biomedical/health tech) | D22: Embedded systems / Electronics | E22: Master indifférencié (recherche et professionnel) Sciences, technologies, santé mention Ingénierie des systèmes complexes parcours Robotique, Intelligence artificielle et Systèmes Embarqués (RISE) | F22: Science, Technology, Health (STS) – major: Complex Systems Engineering – track: Robotics, Artificial Intelligence & Embedded Systems (RISE) | G22: Master indifférencié (recherche et professionnel) | H22: UFR de sciences et techniques | I22: Université de Toulon | J22: Site de La Garde | K22: 83130 La Garde UFR SCIENCES ET TECH | L22: Public university | M22: French | N22: General | O22: Bac +4 | P22: Eligible on level (4-yr BS ≈ Bac+4) | Q22: 1 | R22: 12 | S22: 3950 | T22: 255 | U22: 2 | V22: =IF(S22="","",S22*U22) | W22: Catalogue: €3,950. = national differentiated master fee (2026-27: €3,950). Exemption to ~€255 possible (university quota). | X22: High | Y22: 3950 | AC22: Open | AD22: 2026-10-01 | AE22: 2027-03-15 | AF22: No | AG22: https://formations.univ-tln.fr/fr/offre-de-formation/master-XB/master-ingenierie-des-systemes-complexes-LO8RGPP1/master-ingenierie-des-systemes-complexes-parcours-robotique-intelligente-et-systemes-embarques-LPZRY65U.html | AH22: Attendus administratifs : Niveau B2 de langue française exigé Attendus pédagogiques : solides connaissances en maths-physiques, notions de programmation, sens physique. Un nombre limité de cours magistraux sont susceptib | AI22: Open in EEF
A23: 22 | B23: ★★★★★ | C23: 5 – Core fit (embedded/biomedical/health tech) | D23: Biomedical / Health tech | E23: Master indifférencié (recherche et professionnel) Sciences, technologies, santé mention Physique fondamentale et applications parcours Physique médicale | F23: Science, Technology, Health (STS) – major: Physics Fundamental & Applications – track: Medical Physics | G23: Master indifférencié (recherche et professionnel) | H23: Campus scientifique de BEAULIEU | I23: Université de Rennes | J23: Site de Rennes - FDS Faculté des sciences | L23: Public university | M23: French | N23: General | O23: Bac +4 | P23: Eligible on level (4-yr BS ≈ Bac+4) | Q23: 1 | R23: 12 | S23: 3950 | T23: 255 | U23: 2 | V23: =IF(S23="","",S23*U23) | W23: Catalogue: €3,950. = national differentiated master fee (2026-27: €3,950). Exemption to ~€255 possible (university quota). | X23: High | Y23: 3950 | Z23: ption, il faudra vous acquitter obligatoirement des frais d'inscription s’élevant à 3 950 Euros | AC23: Open | AD23: 2026-10-01 | AE23: 2027-03-15 | AF23: No | AG23: https://formations.univ-rennes.fr/ | AH23: Formations ou matières qu'il faut avoir déjà suivi au cours de son cursus antérieur : Licence de physique ou physique chimie, sciences des matériaux, master 1 en physique, bon socle en mathématiques. Niveau spécifique at | AI23: Open in EEF
A24: 23 | B24: ★★★★★ | C24: 5 – Core fit (embedded/biomedical/health tech) | D24: Biomedical / Health tech | E24: Master indifférencié (recherche et professionnel) Sciences, technologies, santé mention Sciences et génie des matériaux parcours Ingénierie Biomédicale, Biomatériaux, Biomolécules | F24: Science, Technology, Health (STS) – major: Sciences & Engineering of Materials – track: Biomedical Engineering, Biomaterials, Biomolecules | G24: Master indifférencié (recherche et professionnel) | H24: Institut Galilée | I24: Université Sorbonne Paris Nord | J24: Site de Villetaneuse | L24: Public school / institute | M24: French | N24: General | O24: Bac +4 / Bac +5 | P24: Eligible on level (4-yr BS ≈ Bac+4) | Q24: 1/2 | R24: 12 | S24: 3950 | T24: 255 | U24: 2 | V24: =IF(S24="","",S24*U24) | W24: Catalogue: €3,770. = national differentiated master fee (2026-27: €3,950). Exemption to ~€255 possible (university quota). | X24: High | Y24: 3950/3770 | Z24: sitaire 2024-2025 et devront s'acquitter des mêmes frais que les étudiants nationaux (250 euros + CVEC) L'information concernant une exonération | AC24: Open | AD24: 2026-10-01 | AE24: 2027-03-15 | AF24: No | AG24: http://www-galilee.univ-paris13.fr/ | AH24: Niveau TCF Minimun C1 bon niveau d'anglais Diplome scientifique chimie, physique-chimie, biologie ou science technologique et santé ou diplôme équivalent. Etudiant en filières médicales et odontologiques ou filières équi | AI24: Open in EEF
A25: 24 | B25: ★★★★★ | C25: 5 – Core fit (embedded/biomedical/health tech) | D25: Biomedical / Health tech | E25: Master Ingénierie de la santé BioTesting et Biomédicaments | F25: Master Health Engineering BioTesting & Biodrugs | G25: Master indifférencié (recherche et professionnel) | H25: UFR Sciences et Techniques | I25: Université de Rouen | J25: Site de Mont-Saint-Aignan | L25: Public university | M25: French | N25: General | O25: Bac +4 | P25: Eligible on level (4-yr BS ≈ Bac+4) | Q25: 1 | R25: 10 | S25: 3950 | T25: 255 | U25: 2 | V25: =IF(S25="","",S25*U25) | W25: Catalogue: €3,950. = national differentiated master fee (2026-27: €3,950). Exemption to ~€255 possible (university quota). | X25: High | Y25: 3950 | AA25: Rouen: individual exemptions up to 30% quota, priority to social/economic hardship. | AB25: https://www.univ-rouen.fr/actualites/application-des-droits-dinscription-differencies-a-luniversite-de-rouen-normandie-a-compter-de-la-rentree-universitaire-2026-2027/ | AC25: Open | AD25: 2026-10-01 | AE25: 2027-03-15 | AF25: No | AG25: https://sciences-techniques.univ-rouen.fr/offre-de-formation-les-masters--332182.kjsp?RH=1392301431998&RF=1378324428882 | AH25: B2 en français exigé. Bac +3 dans du domaine requis (licence sciences de la vie ou équivalent) | AI25: Open in EEF
A26: 25 | B26: ★★★★★ | C26: 5 – Core fit (embedded/biomedical/health tech) | D26: Biomedical / Health tech | E26: Master Ingénierie de la santé parcours Analyses et Qualité en Bio-Industries (AQBIO) | F26: Master Health Engineering – track: Analyses & Quality in Bio-Industries (AQBIO) | G26: Master indifférencié (recherche et professionnel) | H26: UFR Sciences et Techniques | I26: Université de Rouen | J26: Site de Mont-Saint-Aignan | L26: Public university | M26: French | N26: General | O26: Bac +4 | P26: Eligible on level (4-yr BS ≈ Bac+4) | Q26: 1 | R26: 10 | S26: 3950 | T26: 255 | U26: 2 | V26: =IF(S26="","",S26*U26) | W26: Catalogue: €3,950. = national differentiated master fee (2026-27: €3,950). Exemption to ~€255 possible (university quota). | X26: High | Y26: 3950 | AA26: Rouen: individual exemptions up to 30% quota, priority to social/economic hardship. | AB26: https://www.univ-rouen.fr/actualites/application-des-droits-dinscription-differencies-a-luniversite-de-rouen-normandie-a-compter-de-la-rentree-universitaire-2026-2027/ | AC26: Open | AD26: 2026-10-01 | AE26: 2027-03-15 | AF26: No | AG26: https://sciences-techniques.univ-rouen.fr/ | AH26: B2 en français exigé et Bac+3 du domaine requis. Rentrée début septembre | AI26: Open in EEF
A27: 26 | B27: ★★★★★ | C27: 5 – Core fit (embedded/biomedical/health tech) | D27: Biomedical / Health tech | E27: Master Ingénierie de la santé parcours Imagerie Cellulaire (IMAC) | F27: Master Health Engineering – track: Imaging Cellular (IMAC) | G27: Master indifférencié (recherche et professionnel) | H27: UFR Sciences et Techniques | I27: Université de Rouen | J27: Site de Mont-Saint-Aignan | L27: Public university | M27: French | N27: General | O27: Bac +4 / Bac +5 | P27: Eligible on level (4-yr BS ≈ Bac+4) | Q27: 1/2 | R27: 10 | S27: 3950 | T27: 255 | U27: 2 | V27: =IF(S27="","",S27*U27) | W27: Catalogue: €3,950. = national differentiated master fee (2026-27: €3,950). Exemption to ~€255 possible (university quota). | X27: High | Y27: 3950 | AA27: Rouen: individual exemptions up to 30% quota, priority to social/economic hardship. | AB27: https://www.univ-rouen.fr/actualites/application-des-droits-dinscription-differencies-a-luniversite-de-rouen-normandie-a-compter-de-la-rentree-universitaire-2026-2027/ | AC27: Open | AD27: 2026-10-01 | AE27: 2027-03-15 | AF27: No | AG27: https://sciences-techniques.univ-rouen.fr/ | AH27: B2 en français exigé. Rentrée début septembre. Pour une entrée en master 1 niveau Bac + 3 dans le domaine requis. Pour une entrée en Master 2, Bac + 4 dans le domaine requis. Ce master est un master spécialisé sur deux a | AI27: Open in EEF
A28: 27 | B28: ★★★★★ | C28: 5 – Core fit (embedded/biomedical/health tech) | D28: Biomedical / Health tech | E28: Master Ingénierie de la santé parcours Ingénierie pour le Bio-Médical | F28: Master Health Engineering – track: Engineering for the Bio-Médical | G28: Master indifférencié (recherche et professionnel) | H28: UFR Sciences et Techniques | I28: Université de Rouen | J28: Saint-Etienne-du-Rouvray | L28: Public university | M28: French | N28: General | O28: Bac +4 / Bac +5 | P28: Eligible on level (4-yr BS ≈ Bac+4) | Q28: 1/2 | R28: 10 | S28: 3950 | T28: 255 | U28: 2 | V28: =IF(S28="","",S28*U28) | W28: Catalogue: €3,950. = national differentiated master fee (2026-27: €3,950). Exemption to ~€255 possible (university quota). | X28: High | Y28: 3950 | AA28: Rouen: individual exemptions up to 30% quota, priority to social/economic hardship. | AB28: https://www.univ-rouen.fr/actualites/application-des-droits-dinscription-differencies-a-luniversite-de-rouen-normandie-a-compter-de-la-rentree-universitaire-2026-2027/ | AC28: Open | AD28: 2026-10-01 | AE28: 2027-03-15 | AF28: No | AG28: http://sciences-techniques.univ-rouen.fr/ | AH28: B2 en français exigé. Rentrée début septembre. | AI28: Open in EEF
A29: 28 | B29: ★★★★★ | C29: 5 – Core fit (embedded/biomedical/health tech) | D29: Embedded systems / Electronics | E29: Master mention Génie industriel [Electronique embarquée et systèmes de communication] | F29: Master – major: Industrial Engineering [Embedded Electronics & Systems of Communication] | G29: Master indifférencié (recherche et professionnel) | H29: UFR Systèmes industriels et techniques de communication (Ville d'Avray) | I29: Université Paris Nanterre | J29: Site de Ville-d'Avray | L29: Public university | M29: French | N29: General | O29: Bac +4 | P29: Eligible on level (4-yr BS ≈ Bac+4) | Q29: 1 | S29: 3950 | T29: 255 | U29: 2 | V29: =IF(S29="","",S29*U29) | W29: Catalogue: €3,950. = national differentiated master fee (2026-27: €3,950). Exemption to ~€255 possible (university quota). | X29: High | Y29: 3950 | AC29: Open | AD29: 2026-10-01 | AE29: 2027-03-15 | AF29: No | AG29: https://ufr-sitec.parisnanterre.fr/ | AH29: Les candidats non francophones ou ressortissant d'un pays ou le français n'est pas langue officielle doivent impérativement justifier de leur niveau de français en produisant dans leur dossier le TCF niveau C1 ou le DALF | AI29: Open in EEF
A30: 29 | B30: ★★★★★ | C30: 5 – Core fit (embedded/biomedical/health tech) | D30: Embedded systems / Electronics | E30: Master Sciences, technologies, santé, mention Electronique, énergie électrique, automatique Orientations CIM (Capteurs intelligents et micro-nano-technologies) et EMB (Électronique Embarquée) | F30: Master Science, Technology, Health (STS), – major: Electronics, Electrical Energy & Automation (EEA) Orientations CIM (Sensors Intelligent & micro-nano-technologies) & EMB (Embedded Electronics) | G30: Master indifférencié (recherche et professionnel) | H30: Faculté des Sciences et Technologies | I30: Université de Lorraine | J30: Site de Vandoeuvre-lès-Nancy | L30: Public university | M30: French | N30: General | O30: Bac +4 | P30: Eligible on level (4-yr BS ≈ Bac+4) | Q30: 1 | S30: 3950 | T30: 255 | U30: 2 | V30: =IF(S30="","",S30*U30) | W30: Catalogue: €3,950. = national differentiated master fee (2026-27: €3,950). Exemption to ~€255 possible (university quota). | X30: High | Y30: 3950 | AC30: Open | AD30: 2026-10-01 | AE30: 2027-03-15 | AF30: No | AG30: https://fst.univ-lorraine.fr/formations/ | AH30: Pour le Master 1 : Niveau licence en électronique, électrotechnique, Automatique, Informatique industrielle exigé. Niveau B2 en langue française exigé. Aucun dossier transmis en dehors de la campagne d'ouverture de Campu | AI30: Open in EEF
A31: 30 | B31: ★★★★★ | C31: 5 – Core fit (embedded/biomedical/health tech) | D31: Biomedical / Health tech | E31: Master Sciences, technologies, santé, mention Ingénierie de la santé | F31: Master Science, Technology, Health (STS), – major: Health Engineering | G31: Master indifférencié (recherche et professionnel) | H31: Faculté de Santé | I31: Université Jean Monnet Saint-Etienne | J31: Site de Saint-Etienne | K31: 42270 Saint-Priest-en-Jarez | L31: Public university | M31: French | N31: General | O31: Bac +4 | P31: Eligible on level (4-yr BS ≈ Bac+4) | Q31: 1 | S31: 3950 | T31: 255 | U31: 2 | V31: =IF(S31="","",S31*U31) | W31: Catalogue: €3,950. = national differentiated master fee (2026-27: €3,950). Exemption to ~€255 possible (university quota). | X31: High | Y31: 3950 | Z31: Master : 3950 € + le paiement de la CVEC : 105 € (tarif indicatif 2026/2027) | AC31: Open | AD31: 2026-10-01 | AE31: 2027-03-15 | AF31: No | AG31: https://medecine.univ-st-etienne.fr/fr/formation-initiale/licence-masters.html | AH31: Niveaux de langues : B2 minimum en Français et en Anglais | AI31: Open in EEF
A32: 31 | B32: ★★★★★ | C32: 5 – Core fit (embedded/biomedical/health tech) | D32: Biomedical / Health tech | E32: Master Sciences, technologies, santé, mention Ingénierie de la santé parcours Dispositif médical et affaires réglementaires | F32: Master Science, Technology, Health (STS), – major: Health Engineering – track: Dispositif Medical & affaires réglementaires | G32: Master indifférencié (recherche et professionnel) | H32: Université de technologie de Compiègne | J32: Site de Compiègne | L32: Public university | M32: French | N32: General | O32: Bac +4 / Bac +5 | P32: Eligible on level (4-yr BS ≈ Bac+4) | Q32: 1/2 | S32: 3950 | T32: 255 | U32: 2 | V32: =IF(S32="","",S32*U32) | W32: Catalogue: €3,950. = national differentiated master fee (2026-27: €3,950). Exemption to ~€255 possible (university quota). | X32: High | Y32: 3950 | AC32: Open | AD32: 2026-10-01 | AE32: 2027-03-15 | AF32: No | AG32: https://www.utc.fr/formations/diplome-de-master/mention-ingenierie-de-la-sante-ids/parcours-dispositif-medical-et-affaires-reglementaires-dmar/ | AH32: Pour les parcours DMAR et TBTS Attention, le recrutement en M1 est commun. Ainsi, en candidatant sur l’un vous candidatez également sur l’autre, pas besoin de déposer votre dossier de candidature deux fois. Mentions de l | AI32: Open in EEF
A33: 32 | B33: ★★★★★ | C33: 5 – Core fit (embedded/biomedical/health tech) | D33: Biomedical / Health tech | E33: Master Sciences, technologies, santé, mention Ingénierie de la santé parcours Ingénierie des formations en santé (IFS) | F33: Master Science, Technology, Health (STS), – major: Health Engineering – track: Engineering of formations in Health (IFS) | G33: Master indifférencié (recherche et professionnel) | H33: UFR de santé médecine biologie humaine - Léonard de Vinci | I33: Université Sorbonne Paris Nord | J33: Site de Bobigny | L33: Public university | M33: French | N33: General | O33: Bac +4 / Bac +5 | P33: Eligible on level (4-yr BS ≈ Bac+4) | Q33: 1/2 | S33: 3950 | T33: 255 | U33: 2 | V33: =IF(S33="","",S33*U33) | W33: Catalogue: €3,950. = national differentiated master fee (2026-27: €3,950). Exemption to ~€255 possible (university quota). | X33: High | Y33: 3950 | AC33: Open | AD33: 2026-10-01 | AE33: 2027-03-15 | AF33: No | AI33: Open in EEF
A34: 33 | B34: ★★★★★ | C34: 5 – Core fit (embedded/biomedical/health tech) | D34: Biomedical / Health tech | E34: Master Sciences, technologies, santé, mention Ingénierie de la santé parcours Qualité, sécurité des parcours de soins (QSPS) | F34: Master Science, Technology, Health (STS), – major: Health Engineering – track: Quality, Security of – track: of soins (QSPS) | G34: Master indifférencié (recherche et professionnel) | H34: UFR de santé médecine biologie humaine - Léonard de Vinci | I34: Université Sorbonne Paris Nord | J34: Site de Bobigny | L34: Public university | M34: French | N34: General | O34: Bac +4 | P34: Eligible on level (4-yr BS ≈ Bac+4) | Q34: 1 | S34: 3950 | T34: 255 | U34: 2 | V34: =IF(S34="","",S34*U34) | W34: Catalogue: €3,950. = national differentiated master fee (2026-27: €3,950). Exemption to ~€255 possible (university quota). | X34: High | Y34: 3950 | AC34: Open | AD34: 2026-10-01 | AE34: 2027-03-15 | AF34: No | AI34: Open in EEF
A35: 34 | B35: ★★★★★ | C35: 5 – Core fit (embedded/biomedical/health tech) | D35: Biomedical / Health tech | E35: Master Sciences, technologies, santé mention sciences et techniques des activités physiques et sportives spécialité ingénierie de la rééducation, du handicap et de la performance motrice | F35: Master Science, Technology, Health (STS) – major: Sciences & Techniques of activités physiques & sportives – specialisation: Engineering of the rééducation, of handicap & of the Performance motrice | G35: Master indifférencié (recherche et professionnel) | H35: UFR de sciences et techniques | I35: Le Mans Université | J35: UFR STS - Le Mans | K35: 72085 LE MANS CEDEX | L35: Public university | M35: French | N35: General | O35: Bac +4 / Bac +5 | P35: Eligible on level (4-yr BS ≈ Bac+4) | Q35: 1/2 | R35: 12 | S35: 3950 | T35: 255 | U35: 2 | V35: =IF(S35="","",S35*U35) | W35: Catalogue: €3,950. = national differentiated master fee (2026-27: €3,950). Exemption to ~€255 possible (university quota). | X35: High | Y35: 3950 | AA35: Le Mans governance formally opposed the decree; exemption policy not published. | AB35: https://www.letudiant.fr/educpros/actualite/droits-d-inscription-majores-pour-les-etudiants-etrangers-pourquoi-l-application-du-decret-met-en-difficulte-de-nombreuses-universites.html | AC35: Open | AD35: 2026-10-01 | AE35: 2027-03-15 | AF35: No | AG35: http://sciences.univ-lemans.fr | AH35: TCF B2 minimum Pour candidature en M1 STAPS APAS : Licence 3 STAPS APAS déjà validée ou diplôme équivalent. | AI35: Open in EEF
A36: 35 | B36: ★★★★★ | C36: 5 – Core fit (embedded/biomedical/health tech) | D36: Signal / Image / Vision | E36: Master Sciences, technologies, santé, Optique, image, vision, mutlimédia parcours M2 Signaux et image en médecine (SIM) | F36: Master Science, Technology, Health (STS), Optics, Image, Vision, Multimedia – track: M2 Signaux & Image in Medicine (SIM) | G36: Master indifférencié (recherche et professionnel) | H36: UFR des sciences et technologie | I36: Université Paris-Est Créteil Val-de-Marne | J36: Site de Créteil | L36: Public university | M36: French | N36: General | O36: Bac +4 / Bac +5 | P36: Eligible on level (4-yr BS ≈ Bac+4) | Q36: 1/2 | R36: 12 | S36: 3950 | T36: 255 | U36: 2 | V36: =IF(S36="","",S36*U36) | W36: Catalogue: €3,950. = national differentiated master fee (2026-27: €3,950). Exemption to ~€255 possible (university quota). | X36: High | Y36: 3950 | AC36: Open | AD36: 2026-10-01 | AE36: 2027-03-15 | AF36: No | AG36: https://sciences-tech.u-pec.fr/formation/master-optique-image-vision-multimedia-parcours-signaux-et-image-en-medecine-sim | AH36: C2 ( C1 si anglophone) , Etre titulaire d'un master 1 en Sciences pour l'Ingénieur avec de bons résultats en Mathématiques, Programmation et Data Science. Pré-requis indispensable : avoir reçu un enseignement des fondame | AI36: Open in EEF
A37: 36 | B37: ★★★★★ | C37: 5 – Core fit (embedded/biomedical/health tech) | D37: Signal / Image / Vision | E37: Master Sciences, technologies, santé, Optique, image, vision, mutlimédia parcours M2 Intelligence artificielle, Science des données et systèmes cyber-physiques (IA2S) | F37: Master Science, Technology, Health (STS), Optics, Image, Vision, Multimedia – track: M2 Artificial Intelligence, Data Science & Systems cyber-physiques (IA2S) | G37: Master indifférencié (recherche et professionnel) | H37: UFR des sciences et technologie | I37: Université Paris-Est Créteil Val-de-Marne | J37: Site de Créteil | L37: Public university | M37: French | N37: General | O37: Bac +4 / Bac +5 | P37: Eligible on level (4-yr BS ≈ Bac+4) | Q37: 1/2 | R37: 10 | S37: 3950 | T37: 255 | U37: 2 | V37: =IF(S37="","",S37*U37) | W37: Catalogue: €3,950. = national differentiated master fee (2026-27: €3,950). Exemption to ~€255 possible (university quota). | X37: High | Y37: 3950 | AC37: Open | AD37: 2026-10-01 | AE37: 2027-03-15 | AF37: No | AG37: https://sciences-tech.u-pec.fr/formation/master-optique-image-vision-multimedia-parcours-intelligence-artificielle-sciences-des-donnees-et-systemes-cyber-physiques-ia2s | AI37: Open in EEF
A38: 37 | B38: ★★★★★ | C38: 5 – Core fit (embedded/biomedical/health tech) | D38: IoT / Telecom / Networks | E38: Master Sciences, technologies, santé, Traitement du signal et des images parcours Objets connectés | F38: Master Science, Technology, Health (STS), Signal & Image Processing – track: Connected Objects (IoT) | G38: Master indifférencié (recherche et professionnel) | H38: UFR de sciences fondamentales et appliquées - Université de Poitiers | I38: Université de Poitiers | J38: Site de Poitiers | L38: Public university | M38: French | N38: General | O38: Bac +4 / Bac +5 | P38: Eligible on level (4-yr BS ≈ Bac+4) | Q38: 1/2 | S38: 3950 | T38: 255 | U38: 2 | V38: =IF(S38="","",S38*U38) | W38: Catalogue: €3,950. = national differentiated master fee (2026-27: €3,950). Exemption to ~€255 possible (university quota). | X38: High | Y38: 3950 | AC38: Open | AD38: 2026-10-01 | AE38: 2027-03-15 | AF38: No | AG38: https://sfa.univ-poitiers.fr/formation/offre-de-formation-sciences-technologies-sante/ | AH38: Année 1 L'attention de la commission de recrutement sera portée notamment sur les résultats obtenus sur les matières en lien avec la discipline visée et sur l'aptitude du candidat à exposer ses motivations et son projet | AI38: Open in EEF
A39: 38 | B39: ★★★★★ | C39: 5 – Core fit (embedded/biomedical/health tech) | D39: Embedded systems / Electronics | E39: Master Systèmes intelligents, Mobiles et Embarqués (SIME) | F39: Master Systems Intelligent, Mobile & Embedded (SIME) | G39: Master indifférencié (recherche et professionnel) | H39: UFR Sciences et Techniques | I39: Université de Rouen | J39: Saint-Etienne-du-Rouvray | L39: Public university | M39: French | N39: General | O39: Bac +4 / Bac +5 | P39: Eligible on level (4-yr BS ≈ Bac+4) | Q39: 1/2 | R39: 10 | S39: 3950 | T39: 255 | U39: 2 | V39: =IF(S39="","",S39*U39) | W39: Catalogue: €3,950. = national differentiated master fee (2026-27: €3,950). Exemption to ~€255 possible (university quota). | X39: High | Y39: 3950 | AA39: Rouen: individual exemptions up to 30% quota, priority to social/economic hardship. | AB39: https://www.univ-rouen.fr/actualites/application-des-droits-dinscription-differencies-a-luniversite-de-rouen-normandie-a-compter-de-la-rentree-universitaire-2026-2027/ | AC39: Open | AD39: 2026-10-01 | AE39: 2027-03-15 | AF39: No | AG39: http://sciences-techniques.univ-rouen.fr/ | AH39: Master mention Science des Données sur 2 ans constitué de deux parcours au choix à partir de la 1ère année : - Apprentissage Automatique pour l'Intelligence Artificielle (A2IA) - Systèmes Intelligents Mobiles et Embarqué | AI39: Open in EEF
A40: 39 | B40: ★★★★★ | C40: 5 – Core fit (embedded/biomedical/health tech) | D40: Biomedical / Health tech | E40: Master BioMedical Engineering | F40: Master BioMedical Engineering | G40: Master indifférencié (recherche et professionnel) | H40: UFR des Sciences pharmaceutiques et biologiques | I40: Université de Montpellier | J40: Site de Montpellier | K40: 34090 Montpellier | L40: Public university | M40: French | N40: General | O40: Bac +4 | P40: Eligible on level (4-yr BS ≈ Bac+4) | Q40: 1 | R40: 12 | S40: 3950 | T40: 255 | U40: 2 | V40: =IF(S40="","",S40*U40) | W40: Not in catalogue. Public national master → 2026-27 differentiated fee €3,950; exemption to ~€254-255 depends on university quota (25% cap in 2027-28). | X40: Medium | AA40: Montpellier 2026-27: new non-EU entrants pay the differentiated fee unless individual exemption (limited). | AB40: https://www.umontpellier.fr/en/international/etudier-a-letranger/etudiants-internationaux-annee-universitaire-2026-2027/ | AC40: Open | AD40: 2026-10-01 | AE40: 2027-03-15 | AF40: No | AG40: https://idil.edu.umontpellier.fr/master-idil/les-parcours/ | AH40: Conditions d’accès Diplôme de licence dans la discipline choisie IDIL Niveau d’anglais B2 minimum CV et lettre de motivation 2 lettres de soutien d’un chercheur et/ou professeur (recommandé, mais non obligatoire) Estimat | AI40: Open in EEF
A41: 40 | B41: ★★★★★ | C41: 5 – Core fit (embedded/biomedical/health tech) | D41: Biomedical / Health tech | E41: Master indifférencié (recherche et professionnel) Sciences et technologies mention STAPS: ingénierie et ergonomie de l'activité physique parcours Bio-ingénierie des tissus et des implants (BTI) | F41: Science & Technology – major: STAPS: Engineering & Ergonomics of l'activité Physics – track: Bioengineering of Tissues & of Implants (BTI) | G41: Master indifférencié (recherche et professionnel) | H41: Faculté des sciences du sport | I41: Université d'Aix-Marseille | J41: Site de Marseille | L41: Public university | M41: French | N41: General | O41: Bac +4 | P41: Eligible on level (4-yr BS ≈ Bac+4) | Q41: 1 | R41: 12 | S41: 3950 | T41: 255 | U41: 2 | V41: =IF(S41="","",S41*U41) | W41: Not in catalogue. Public national master → 2026-27 differentiated fee €3,950; exemption to ~€254-255 depends on university quota (25% cap in 2027-28). | X41: Medium | AA41: AMU 2026-27: limited exemptions (≈1,800 of 5,500 students) – priority to continuing students, conflict zones, excellence scholarships. New master entrants usually pay €3,950. | AB41: https://www.univ-amu.fr/fr/actualites/aix-marseille-universite-mobilise-pleinement-capacite-dexoneration-continuer-accueillir | AC41: Open | AD41: 2026-10-01 | AE41: 2027-03-15 | AF41: No | AG41: http://fss.univ-amu.fr/ | AH41: Niveau en langues : Niveau B2 en Français pour les non francophones. Niveau B2 en anglais pour les non anglophones Compétences académiques : Mathématiques, Mécanique, Physique pour les étudiants issus d’un cursus Science | AI41: Open in EEF
A42: 41 | B42: ★★★★★ | C42: 5 – Core fit (embedded/biomedical/health tech) | D42: Biomedical / Health tech | E42: Master indifférencié (recherche et professionnel) Sciences, technologies, santé mention Biotechnologies parcours Bioingénierie, Recherche et Application Biomédicale | F42: Science, Technology, Health (STS) – major: Biotechnologies – track: Bioengineering, Research & Application Biomedical | G42: Master indifférencié (recherche et professionnel) | H42: Faculté des Sciences et d'Ingénierie | I42: Université de Toulouse | J42: Site de Toulouse | L42: Public university | M42: French | N42: General | O42: Bac +4 / Bac +5 | P42: Eligible on level (4-yr BS ≈ Bac+4) | Q42: 1/2 | S42: 3950 | T42: 255 | U42: 2 | V42: =IF(S42="","",S42*U42) | W42: Not in catalogue. Public national master → 2026-27 differentiated fee €3,950; exemption to ~€254-255 depends on university quota (25% cap in 2027-28). | X42: Medium | AA42: Board decision (Feb 2026, pre-decree): partial exemption for ALL non-EU students subject to differentiated fees, until end of cycle. Re-check for 2027-28. | AB42: https://www.utoulouse.fr/medias/fichier/2026-02-ca-075_1774430647495-pdf | AC42: Open | AD42: 2026-10-01 | AE42: 2027-03-15 | AF42: No | AG42: http://www.univ-tlse3.fr/ | AH42: https://www.univ-tlse3.fr/master-parcours-bio-ingenierie-recherche-et-application-biomedicale-birab Si vous ne maîtrisez pas encore le français au niveau exigé pour intégrer une formation en France, le DU FUSEE (Diplôme | AI42: Open in EEF
A43: 42 | B43: ★★★★★ | C43: 5 – Core fit (embedded/biomedical/health tech) | D43: Embedded systems / Electronics | E43: Master indifférencié (recherche et professionnel) Sciences, technologies, santé mention Electronique, Energie électrique, Automatique parcours Capteurs Electronique et Objets Connectés - CEO | F43: Science, Technology, Health (STS) – major: Electronics, Electrical Energy & Automation (EEA) – track: Sensors Electronics & Connected Objects (IoT) - CEO | G43: Master indifférencié (recherche et professionnel) | H43: UFR des Sciences de Montpellier | I43: Université de Montpellier | J43: Site de Montpellier | L43: Public university | M43: French | N43: General | O43: Bac +4 / Bac +5 | P43: Eligible on level (4-yr BS ≈ Bac+4) | Q43: 1/2 | S43: 3950 | T43: 255 | U43: 2 | V43: =IF(S43="","",S43*U43) | W43: Not in catalogue. Public national master → 2026-27 differentiated fee €3,950; exemption to ~€254-255 depends on university quota (25% cap in 2027-28). | X43: Medium | AA43: Montpellier 2026-27: new non-EU entrants pay the differentiated fee unless individual exemption (limited). | AB43: https://www.umontpellier.fr/en/international/etudier-a-letranger/etudiants-internationaux-annee-universitaire-2026-2027/ | AC43: Open | AD43: 2026-10-01 | AE43: 2027-03-15 | AF43: No | AG43: http://sciences.edu.umontpellier.fr/ | AH43: Niveau de Français B2 au minimum, exigé. 12/20 min les années précédentes | AI43: Open in EEF
A44: 43 | B44: ★★★★★ | C44: 5 – Core fit (embedded/biomedical/health tech) | D44: Embedded systems / Electronics | E44: Master indifférencié (recherche et professionnel) Sciences, technologies, santé mention Electronique, Energie électrique, Automatique parcours Systèmes Électroniques Intégrés et Embarqués - SEIE | F44: Science, Technology, Health (STS) – major: Electronics, Electrical Energy & Automation (EEA) – track: Systems Electronic Integrated & Embedded - SEIE | G44: Master indifférencié (recherche et professionnel) | H44: UFR des Sciences de Montpellier | I44: Université de Montpellier | J44: Site de Montpellier | L44: Public university | M44: French | N44: General | O44: Bac +4 / Bac +5 | P44: Eligible on level (4-yr BS ≈ Bac+4) | Q44: 1/2 | S44: 3950 | T44: 255 | U44: 2 | V44: =IF(S44="","",S44*U44) | W44: Not in catalogue. Public national master → 2026-27 differentiated fee €3,950; exemption to ~€254-255 depends on university quota (25% cap in 2027-28). | X44: Medium | AA44: Montpellier 2026-27: new non-EU entrants pay the differentiated fee unless individual exemption (limited). | AB44: https://www.umontpellier.fr/en/international/etudier-a-letranger/etudiants-internationaux-annee-universitaire-2026-2027/ | AC44: Open | AD44: 2026-10-01 | AE44: 2027-03-15 | AF44: No | AG44: http://sciences.edu.umontpellier.fr/ | AH44: Niveau de Français B2 au minimum, exigé. 12/20 min les années précédentes | AI44: Open in EEF
A45: 44 | B45: ★★★★★ | C45: 5 – Core fit (embedded/biomedical/health tech) | D45: Embedded systems / Electronics | E45: Master indifférencié (recherche et professionnel) Sciences, technologies, santé mention Electronique, Energie électrique et Automatique parcours Electronique des systèmes embarqués et télécommunications | F45: Science, Technology, Health (STS) – major: Electronics, Electrical Energy & Automation (EEA) – track: Electronics of Embedded Systems & Telecommunications | G45: Master indifférencié (recherche et professionnel) | H45: Faculté des Sciences et d'Ingénierie | I45: Université de Toulouse | J45: Site de Toulouse | L45: Public university | M45: French | N45: General | O45: Bac +4 / Bac +5 | P45: Eligible on level (4-yr BS ≈ Bac+4) | Q45: 1/2 | S45: 3950 | T45: 255 | U45: 2 | V45: =IF(S45="","",S45*U45) | W45: Not in catalogue. Public national master → 2026-27 differentiated fee €3,950; exemption to ~€254-255 depends on university quota (25% cap in 2027-28). | X45: Medium | AA45: Board decision (Feb 2026, pre-decree): partial exemption for ALL non-EU students subject to differentiated fees, until end of cycle. Re-check for 2027-28. | AB45: https://www.utoulouse.fr/medias/fichier/2026-02-ca-075_1774430647495-pdf | AC45: Open | AD45: 2026-10-01 | AE45: 2027-03-15 | AF45: No | AG45: http://www.univ-tlse3.fr/ | AH45: https://www.utoulouse.fr/decouvrir-nos-diplomes/les-mentions-de-masters Si vous ne maîtrisez pas encore le français au niveau exigé pour intégrer une formation en France, le DU FUSEE (Diplôme Universitaire de Français po | AI45: Open in EEF
A46: 45 | B46: ★★★★★ | C46: 5 – Core fit (embedded/biomedical/health tech) | D46: Embedded systems / Electronics | E46: Master indifférencié (recherche et professionnel) Sciences, technologies, santé mention Electronique, Energie électrique et Automatique parcours Systèmes et Microsystèmes Embarqués | F46: Science, Technology, Health (STS) – major: Electronics, Electrical Energy & Automation (EEA) – track: Systems & MicroEmbedded Systems | G46: Master indifférencié (recherche et professionnel) | H46: Faculté des Sciences et d'Ingénierie | I46: Université de Toulouse | J46: Site de Toulouse | L46: Public university | M46: French | N46: General | O46: Bac +4 / Bac +5 | P46: Eligible on level (4-yr BS ≈ Bac+4) | Q46: 1/2 | S46: 3950 | T46: 255 | U46: 2 | V46: =IF(S46="","",S46*U46) | W46: Not in catalogue. Public national master → 2026-27 differentiated fee €3,950; exemption to ~€254-255 depends on university quota (25% cap in 2027-28). | X46: Medium | AA46: Board decision (Feb 2026, pre-decree): partial exemption for ALL non-EU students subject to differentiated fees, until end of cycle. Re-check for 2027-28. | AB46: https://www.utoulouse.fr/medias/fichier/2026-02-ca-075_1774430647495-pdf | AC46: Open | AD46: 2026-10-01 | AE46: 2027-03-15 | AF46: No | AG46: http://www.univ-tlse3.fr/ | AH46: https://www.utoulouse.fr/decouvrir-nos-diplomes/les-mentions-de-masters Si vous ne maîtrisez pas encore le français au niveau exigé pour intégrer une formation en France, le DU FUSEE (Diplôme Universitaire de Français po | AI46: Open in EEF
A47: 46 | B47: ★★★★★ | C47: 5 – Core fit (embedded/biomedical/health tech) | D47: Cybersecurity | E47: Master indifférencié (recherche et professionnel) Sciences, technologies, santé mention informatique parcours Cybersécurité et e-santé | F47: Science, Technology, Health (STS) – major: Computer Science – track: Cybersecurity & e-santé | G47: Master indifférencié (recherche et professionnel) | H47: UFR des Sciences Fondamentales et Biomédicales | I47: Université Paris Cité | J47: Site de Paris | K47: 75006 Paris | L47: Public university | M47: French | N47: General | O47: Bac +4 / Bac +5 | P47: Eligible on level (4-yr BS ≈ Bac+4) | Q47: 1/2 | S47: 3950 | T47: 255 | U47: 2 | V47: =IF(S47="","",S47*U47) | W47: Not in catalogue. Public national master → 2026-27 differentiated fee €3,950; exemption to ~€254-255 depends on university quota (25% cap in 2027-28). | X47: Medium | AA47: Paris Cité historically exempted non-EU master students (paid EU rate). 2026-27/2027-28 policy not yet published – confirm. | AB47: https://u-paris.fr/droits-dinscription-tarifs-exonerations/ | AC47: Open | AD47: 2026-10-01 | AE47: 2027-03-15 | AF47: No | AG47: https://odf.u-paris.fr/fr/offre-de-formation/master-XB/sciences-technologies-sante-STS/informatique-K2NDIF4R//master-informatique-parcours-cybersecurite-et-esante-JT5NZSOS.html | AH47: https://odf.u-paris.fr/fr/offre-de-formation/master-XB/sciences-technologies-sante-STS/informatique-K2NDIF4R//master-informatique-parcours-cybersecurite-et-esante-JT5NZSOS.html Droits d’inscriptions différenciés 2027-202 | AI47: Open in EEF
A48: 47 | B48: ★★★★★ | C48: 5 – Core fit (embedded/biomedical/health tech) | D48: Embedded systems / Electronics | E48: Master indifférencié (recherche et professionnel) Sciences, technologies, santé mention informatique parcours Systèmes Embarqués et Connectés : Infrastructures et Logiciels | F48: Science, Technology, Health (STS) – major: Computer Science – track: Embedded Systems & Connected : Infrastructures & Software | G48: Master indifférencié (recherche et professionnel) | H48: Faculté des Sciences et d'Ingénierie | I48: Université de Toulouse | J48: Site de Toulouse | L48: Public university | M48: French | N48: General | O48: Bac +4 / Bac +5 | P48: Eligible on level (4-yr BS ≈ Bac+4) | Q48: 1/2 | S48: 3950 | T48: 255 | U48: 2 | V48: =IF(S48="","",S48*U48) | W48: Not in catalogue. Public national master → 2026-27 differentiated fee €3,950; exemption to ~€254-255 depends on university quota (25% cap in 2027-28). | X48: Medium | AA48: Board decision (Feb 2026, pre-decree): partial exemption for ALL non-EU students subject to differentiated fees, until end of cycle. Re-check for 2027-28. | AB48: https://www.utoulouse.fr/medias/fichier/2026-02-ca-075_1774430647495-pdf | AC48: Open | AD48: 2026-10-01 | AE48: 2027-03-15 | AF48: No | AG48: http://www.univ-tlse3.fr/ | AH48: https://www.univ-tlse3.fr/master-parcours-systemes-embarques-et-connectes-infrastructures-et-logiciels-secil | AI48: Open in EEF
A49: 48 | B49: ★★★★★ | C49: 5 – Core fit (embedded/biomedical/health tech) | D49: Biomedical / Health tech | E49: Master indifférencié (recherche et professionnel) Sciences, technologies, santé mention Ingénierie de la santé parcours Technologies, imagerie et physique pour la santé | F49: Science, Technology, Health (STS) – major: Health Engineering – track: Technologies, Imaging & Physics for the Health | G49: Master indifférencié (recherche et professionnel) | H49: UFR Médecine - Pharmacie | I49: Université de Grenoble Alpes | J49: Site de Grenoble - Campus de La Merci - La Tronche | L49: Public university | M49: French | N49: General | O49: Bac +4 | P49: Eligible on level (4-yr BS ≈ Bac+4) | Q49: 1 | S49: 3950 | T49: 255 | U49: 2 | V49: =IF(S49="","",S49*U49) | W49: Not in catalogue. Public national master → 2026-27 differentiated fee €3,950; exemption to ~€254-255 depends on university quota (25% cap in 2027-28). | X49: Medium | AA49: UGA (incl. Grenoble INP masters): 2026-27 broad exemptions on request (pay national €254). From 2027-28 the decree caps apply; exemptions based on resources. | AB49: https://www.univ-grenoble-alpes.fr/actualites/a-la-une/actualites-universite/etudiants-internationaux-ce-que-change-le-nouveau-decret-sur-les-droits-d-inscription-a-l-uga-1775870.kjsp | AC49: Open | AD49: 2026-10-01 | AE49: 2027-03-15 | AF49: No | AG49: https://formations.univ-grenoble-alpes.fr/fr/catalogue-2021/master-XB/master-ingenierie-de-la-sante-IAQKSXOB.html | AH49: licence ou master 1 dans les domaines de l'imagerie ou la radioprotection ou la modelisation en santé ou la recherche clinique, niveau d'anglais B1 conseillé | AI49: Open in EEF
A50: 49 | B50: ★★★★★ | C50: 5 – Core fit (embedded/biomedical/health tech) | D50: Biomedical / Health tech | E50: Master indifférencié (recherche et professionnel) Sciences, technologies, santé mention Sciences et numérique pour la santé parcours PHYSIQUE BIOMEDICALE (PHYMED) | F50: Science, Technology, Health (STS) – major: Sciences & Digital for the Health – track: Physics BIOMEDICALE (PHYMED) | G50: Master indifférencié (recherche et professionnel) | H50: UFR des Sciences de Montpellier | I50: Université de Montpellier | J50: Site de Montpellier | L50: Public university | M50: French | N50: General | O50: Bac +4 | P50: Eligible on level (4-yr BS ≈ Bac+4) | Q50: 1 | S50: 3950 | T50: 255 | U50: 2 | V50: =IF(S50="","",S50*U50) | W50: Not in catalogue. Public national master → 2026-27 differentiated fee €3,950; exemption to ~€254-255 depends on university quota (25% cap in 2027-28). | X50: Medium | AA50: Montpellier 2026-27: new non-EU entrants pay the differentiated fee unless individual exemption (limited). | AB50: https://www.umontpellier.fr/en/international/etudier-a-letranger/etudiants-internationaux-annee-universitaire-2026-2027/ | AC50: Open | AD50: 2026-10-01 | AE50: 2027-03-15 | AF50: No | AG50: http://www.fdsweb.univ-montp2.fr/etudier-a-la-fds/catalogue-de-formation-675 | AH50: L3 Scientifique et Santé | AI50: Open in EEF
A51: 50 | B51: ★★★★★ | C51: 5 – Core fit (embedded/biomedical/health tech) | D51: Biomedical / Health tech | E51: Master Sciences et technologies mention Ingénierie de la santé | F51: Master Science & Technology – major: Health Engineering | G51: Master indifférencié (recherche et professionnel) | H51: UFR Santé | I51: Université Marie et Louis Pasteur | J51: Site de Besançon | K51: 25030 BESANCON | L51: Public university | M51: French | N51: General | O51: Bac +4 / Bac +5 | P51: Eligible on level (4-yr BS ≈ Bac+4) | Q51: 1/2 | R51: 12 | S51: 3950 | T51: 255 | U51: 2 | V51: =IF(S51="","",S51*U51) | W51: Not in catalogue. Public national master → 2026-27 differentiated fee €3,950; exemption to ~€254-255 depends on university quota (25% cap in 2027-28). | X51: Medium | AA51: UMLP: individual exemption requests assessed on personal resources. | AB51: https://www.umlp.fr/sites/default/files/2026-07-02-page-droits-differencies-vf.pdf | AC51: Open | AD51: 2026-10-01 | AE51: 2027-03-15 | AF51: No | AI51: Open in EEF
A52: 51 | B52: ★★★★★ | C52: 5 – Core fit (embedded/biomedical/health tech) | D52: Biomedical / Health tech | E52: Master Sciences, technologies, santé mention Sciences du médicament et des produits de santé parcours Pharmacologie, Pharmacochimie, Bioingénierie des Biomolécules. | F52: Master Science, Technology, Health (STS) – major: Sciences of médicament & of produits of Health – track: Pharmacology, Pharmacochimie, Bioengineering of Biomolecules. | G52: Master indifférencié (recherche et professionnel) | H52: UFR de Pharmacie | I52: Université Paris Cité | J52: Site de Paris | K52: 75006 Paris | L52: Public university | M52: French | N52: General | O52: Bac +4 | P52: Eligible on level (4-yr BS ≈ Bac+4) | Q52: 1 | S52: 3950 | T52: 255 | U52: 2 | V52: =IF(S52="","",S52*U52) | W52: Not in catalogue. Public national master → 2026-27 differentiated fee €3,950; exemption to ~€254-255 depends on university quota (25% cap in 2027-28). | X52: Medium | AA52: Paris Cité historically exempted non-EU master students (paid EU rate). 2026-27/2027-28 policy not yet published – confirm. | AB52: https://u-paris.fr/droits-dinscription-tarifs-exonerations/ | AC52: Open | AD52: 2026-10-01 | AE52: 2027-03-15 | AF52: No | AG52: https://pharmacie.u-paris.fr/ | AH52: https://odf.u-paris.fr/fr/offre-de-formation/master-XB/sciences-technologies-sante-STS/sciences-du-medicament-et-des-produits-de-sante-K2NDKZA2/master-sciences-du-medicament-et-des-produits-de-sante-parcours-pharmacologi | AI52: Open in EEF
A53: 52 | B53: ★★★★★ | C53: 5 – Core fit (embedded/biomedical/health tech) | D53: Biomedical / Health tech | E53: Sciences de la santé parcours Ingénierie de la santé et intelligence artificielle | F53: Sciences of the Health – track: Health Engineering & Artificial Intelligence | G53: Master indifférencié (recherche et professionnel) | H53: UFR Santé | I53: Université Marie et Louis Pasteur | J53: Site de Besançon | K53: 25030 BESANCON | L53: Public university | M53: French | N53: General | O53: Bac +4 / Bac +5 | P53: Eligible on level (4-yr BS ≈ Bac+4) | Q53: 1/2 | R53: 12 | S53: 3950 | T53: 255 | U53: 2 | V53: =IF(S53="","",S53*U53) | W53: Not in catalogue. Public national master → 2026-27 differentiated fee €3,950; exemption to ~€254-255 depends on university quota (25% cap in 2027-28). | X53: Medium | AA53: UMLP: individual exemption requests assessed on personal resources. | AB53: https://www.umlp.fr/sites/default/files/2026-07-02-page-droits-differencies-vf.pdf | AC53: Open | AD53: 2026-10-01 | AE53: 2027-03-15 | AF53: No | AH53: Niveau de langue C1 minimum Entretien visio ou téléphonique obligatoire | AI53: Open in EEF
A54: 53 | B54: ★★★★★ | C54: 5 – Core fit (embedded/biomedical/health tech) | D54: Embedded systems / Electronics | E54: Master professionnel Sciences, technologies, santé mention ingénierie des systèmes complexes parcours Cyber-sécurité des systèmes embarqués | F54: Professional Master Science, Technology, Health (STS) – major: Complex Systems Engineering – track: Cyber-sécurité of Embedded Systems | G54: Master professionnel | H54: Faculté des sciences et sciences de l'ingénieur (Campus de Lorient) | I54: Université Bretagne-Sud | J54: Site de Lorient | L54: Public university | M54: French | N54: General | O54: Bac +4 / Bac +5 | P54: Eligible on level (4-yr BS ≈ Bac+4) | Q54: 1/2 | S54: 3950 | T54: 255 | U54: 2 | V54: =IF(S54="","",S54*U54) | W54: Not in catalogue. Public national master → 2026-27 differentiated fee €3,950; exemption to ~€254-255 depends on university quota (25% cap in 2027-28). | X54: Medium | AC54: Open | AD54: 2026-10-01 | AE54: 2027-03-15 | AF54: No | AG54: https://www.univ-ubs.fr/fr/formation-initiale-continue/formations-2017-2018/master-XB/sciences-technologies-sante-STS/master-cyber-securite-des-systemes-embarques-program-5scy00-217-5scy01.html | AH54: Moyenne cumulative (études sécondaires et études supérieures) : 13/20 Niveau C1 exigé en français. Pour les étudiants en alternance : date limite la fin du mois d'octobre de l'année en cours | AI54: Open in EEF
A55: 54 | B55: ★★★★★ | C55: 5 – Core fit (embedded/biomedical/health tech) | D55: Embedded systems / Electronics | E55: Master professionnel Sciences, technologies, santé mention ingénierie des systèmes complexes parcours Systèmes embarqués / systèmes intégrés | F55: Professional Master Science, Technology, Health (STS) – major: Complex Systems Engineering – track: Embedded Systems / Systems Integrated | G55: Master professionnel | H55: Faculté des sciences et sciences de l'ingénieur (Campus de Lorient) | I55: Université Bretagne-Sud | J55: Site de Lorient | L55: Public university | M55: French | N55: General | O55: Bac +4 / Bac +5 | P55: Eligible on level (4-yr BS ≈ Bac+4) | Q55: 1/2 | S55: 3950 | T55: 255 | U55: 2 | V55: =IF(S55="","",S55*U55) | W55: Not in catalogue. Public national master → 2026-27 differentiated fee €3,950; exemption to ~€254-255 depends on university quota (25% cap in 2027-28). | X55: Medium | AC55: Open | AD55: 2026-10-01 | AE55: 2027-03-15 | AF55: No | AG55: https://www.univ-ubs.fr/fr/formation-initiale-continue/formations-2017-2018/master-XB/sciences-technologies-sante-STS/master-systemes-embarques-systemes-integres-program-5ssy00-217-4ssy01.html | AH55: Moyenne cumulative (études sécondaires et études supérieures) : 13/20 Niveau B2 exigé en français. Pour l'alternance: date limite pour la signature du contrat 31 octobre 2027 | AI55: Open in EEF
A56: 55 | B56: ★★★★★ | C56: 5 – Core fit (embedded/biomedical/health tech) | D56: Embedded systems / Electronics | E56: diplôme d'ingénieur de l'Ecole d'ingénieurs de l'Université de Caen spécialité systèmes embarqués | F56: Engineering diploma of School of Engineers of University of Caen – specialisation: Embedded Systems | G56: Diplôme d'ingénieur | H56: Ecole supérieur d'ingénieurs _ ESIX | I56: Université Caen Normandie | J56: Site de Caen | L56: Public school / institute | M56: French | N56: General | O56: Bac +3 / Bac +4 | P56: Eligible on level (4-yr BS ≈ Bac+4) | Q56: 1/2 | R56: 10 | S56: 601 | U56: 2 | V56: =IF(S56="","",S56*U56) | W56: Catalogue lists €601 (EU/national rate). Confirm whether non-EU surcharge applies. | X56: Medium | Y56: 601 | AC56: Open | AD56: 2026-10-01 | AE56: 2027-03-15 | AF56: No | AG56: https://esix.unicaen.fr | AH56: - Entrer en formation avec un niveau Bac+3 validé - Avoir un niveau B1 en Anglais - Avoir un niveau B2 en français Vous avez des problèmes de santé ou une situation de handicap qui peut impacter vos études ? Penser à ant | AI56: Open in EEF
A57: 56 | B57: ★★★★★ | C57: 5 – Core fit (embedded/biomedical/health tech) | D57: Embedded systems / Electronics | E57: diplôme d'ingénieur de 'Université Sorbonne Paris Nord spécialité instrumentation : Systèmes embarqués et génie médical | F57: Engineering diploma of 'Université Sorbonne Paris Nord – specialisation: Instrumentation : Embedded Systems & Engineering Medical | G57: Diplôme d'ingénieur | H57: Institut Galilée | I57: Université Sorbonne Paris Nord | J57: Site de Villetaneuse | L57: Public school / institute | M57: French | N57: General | O57: Bac +3 / Bac +4 | P57: Eligible on level (4-yr BS ≈ Bac+4) | Q57: 3/4 | S57: 628 | U57: 2 | V57: =IF(S57="","",S57*U57) | W57: Catalogue lists €628 (EU/national rate). Confirm whether non-EU surcharge applies. | X57: Medium | Y57: 628 | AC57: Open | AD57: 2026-10-01 | AE57: 2027-03-15 | AF57: No | AG57: http://www.sup-galilee.univ-paris13.fr/ | AI57: Open in EEF
A58: 57 | B58: ★★★★★ | C58: 5 – Core fit (embedded/biomedical/health tech) | D58: Biomedical / Health tech | E58: spécialité Biomédical et Santé | F58: specialisation: Biomedical & Health | G58: Diplôme d'ingénieur | H58: Ecole Publique d'Ingénieurs de la Santé et du Numérique - EPISEN | I58: Université Paris-Est Créteil Val-de-Marne | J58: Site de Créteil | K58: 94000 Créteil | L58: Public university | M58: French | N58: General | O58: Bac +3 / Bac +4 | P58: Eligible on level (4-yr BS ≈ Bac+4) | Q58: 1/2 | R58: 12 | S58: 628 | U58: 2 | V58: =IF(S58="","",S58*U58) | W58: Catalogue lists €628 (EU/national rate). Confirm whether non-EU surcharge applies. | X58: Medium | Y58: 628 | Z58: Montant frais inscription 2025-2026 = 628€, susceptibles d’augmenter en 2026-2027 … n biologie - Bon niveau de Français et d'anglais Montant frais inscription 2025-2026 = 628€, susceptibles d’augmenter en 2026-2027 | AC58: Open | AD58: 2026-10-01 | AE58: 2027-03-15 | AF58: No | AG58: https://episen.u-pec.fr/ | AH58: Être issu d'une filière fournissant des compétences de base en mathématiques, en informatique, en mécanique OU en biologie - Bon niveau de Français et d'anglais | AI58: Open in EEF
A59: 58 | B59: ★★★★★ | C59: 5 – Core fit (embedded/biomedical/health tech) | D59: Biomedical / Health tech | E59: spécialité Ingénierie et Technologies pour la santé | F59: specialisation: Engineering & Technologies for the Health | G59: Diplôme d'ingénieur | H59: Ecole Publique d'Ingénieurs de la Santé et du Numérique - EPISEN | I59: Université Paris-Est Créteil Val-de-Marne | J59: Site de Créteil | K59: 94000 Créteil | L59: Public university | M59: French | N59: General | O59: Bac +3 / Bac +4 | P59: Eligible on level (4-yr BS ≈ Bac+4) | Q59: 1/2 | R59: 12 | S59: 628 | U59: 2 | V59: =IF(S59="","",S59*U59) | W59: Catalogue lists €628 (EU/national rate). Confirm whether non-EU surcharge applies. | X59: Medium | Y59: 628 | Z59: Montant frais inscription 2025-2026 = 628€, susceptibles d’augmenter en 2026-2027 … Bon niveau d'anglais et de français Montant frais inscription 2025-2026 = 628€, susceptibles d’augmenter en 2026-2027 | AC59: Open | AD59: 2026-10-01 | AE59: 2027-03-15 | AF59: No | AG59: https://episen.u-pec.fr/ | AH59: 1ère année : Informatique et Mathématiques niveau Classe Préparatoire, L2 info ou science, L3 info ou science, BUT ou DUT Info, RT, GEII. Bon niveau d'anglais et de français 2ème année : Informatique et Mathématiques niv | AI59: Open in EEF
A60: 59 | B60: ★★★★★ | C60: 5 – Core fit (embedded/biomedical/health tech) | D60: IoT / Telecom / Networks | E60: diplôme d'ingénieur de l'Ecole polytechnique universitaire de Lille, Université Lille I, sciences et technologies spécialité Internet des Objets et Cybersécurité | F60: Engineering diploma of the University Polytechnic School of Lille, University Lille I, Science & Technology – specialisation: Internet of Things & Cybersecurity | G60: Diplôme d'ingénieur | H60: Polytech Lille | I60: Groupement Polytech | J60: Site de Villeneuve-d'Ascq | L60: Public school / institute | M60: French | N60: General | O60: Bac +3 / Bac +4 | P60: Eligible on level (4-yr BS ≈ Bac+4) | Q60: 3/4 | R60: 12 | S60: 3950 | T60: 628 | U60: 2 | V60: =IF(S60="","",S60*U60) | W60: Not in catalogue. Public engineering diploma: national rate ~€601-628; many schools charge non-EU up to ~€3,950. Verify. | X60: Low | AC60: Open | AD60: 2026-10-01 | AE60: 2027-03-15 | AF60: Yes | AG60: https://www.polytech-lille.fr/formation/ingenieur-internet-des-objets-cybersecurite/ | AH60: Les systèmes embarqués connectés sont au cœur de la spécialité « internet des objets et cybersécurité ». Ces systèmes sont présents partout, pour l’agriculture, pour la défense nationale, dans le domaine de la santé, en | AI60: Open in EEF
A61: 60 | B61: ★★★★★ | C61: 5 – Core fit (embedded/biomedical/health tech) | D61: Biomedical / Health tech | E61: diplôme d'ingénieur de l'École polytechnique universitaire de Marseille de l'Université d'Aix-Marseille spécialité génie biomédical | F61: Engineering diploma of the University Polytechnic School of Marseille of University d'Aix-Marseille – specialisation: Biomedical Engineering | G61: Diplôme d'ingénieur | H61: Polytech Marseille | I61: Groupement Polytech | J61: Site de Luminy | L61: Public school / institute | M61: French | N61: General | O61: Bac +3 / Bac +4 | P61: Eligible on level (4-yr BS ≈ Bac+4) | Q61: 3/4 | S61: 3950 | T61: 628 | U61: 2 | V61: =IF(S61="","",S61*U61) | W61: Not in catalogue. Public engineering diploma: national rate ~€601-628; many schools charge non-EU up to ~€3,950. Verify. | X61: Low | AA61: AMU 2026-27: limited exemptions (≈1,800 of 5,500 students) – priority to continuing students, conflict zones, excellence scholarships. New master entrants usually pay €3,950. | AB61: https://www.univ-amu.fr/fr/actualites/aix-marseille-universite-mobilise-pleinement-capacite-dexoneration-continuer-accueillir | AC61: Open | AD61: 2026-10-01 | AE61: 2027-03-15 | AF61: Yes | AG61: https://polytech.univ-amu.fr/fr/formations/cycle-ingenieur/genie-biomedical | AH61: Les informations qui suivent, concernent la candidature en cycle ingénieur (diplôme niveau Bac+5) du réseau Polytech. Les candidatures sont possibles : - en 3ème année (1ère année cycle ingénieur) avec un niveau Bac+2/Ba | AI61: Open in EEF
A62: 61 | B62: ★★★★★ | C62: 5 – Core fit (embedded/biomedical/health tech) | D62: Embedded systems / Electronics | E62: diplôme d'ingénieur de l'Ecole polytechnique universitaire de Savoie de l'université de Chambéry spécialité Systèmes embarqués - Automatique (SEA) | F62: Engineering diploma of the University Polytechnic School of Savoie of University of Chambéry – specialisation: Embedded Systems - Automation (SEA) | G62: Diplôme d'ingénieur | H62: Polytech Annecy-Chambéry | I62: Groupement Polytech | J62: Site d'Annecy | L62: Public school / institute | M62: French | N62: General | O62: Bac +3 / Bac +4 | P62: Eligible on level (4-yr BS ≈ Bac+4) | Q62: 3/4 | R62: 12 | S62: 3950 | T62: 628 | U62: 2 | V62: =IF(S62="","",S62*U62) | W62: Not in catalogue. Public engineering diploma: national rate ~€601-628; many schools charge non-EU up to ~€3,950. Verify. | X62: Low | AC62: Open | AD62: 2026-10-01 | AE62: 2027-03-15 | AF62: Yes | AG62: http://www.polytech.univ-savoie.fr | AH62: Les informations qui suivent, concernent la candidature en cycle ingénieur (diplôme niveau Bac+5) du réseau Polytech. Les candidatures sont possibles : - en 3ème année (1ère année cycle ingénieur) avec un niveau Bac+2/Ba | AI62: Open in EEF
A63: 62 | B63: ★★★★★ | C63: 5 – Core fit (embedded/biomedical/health tech) | D63: Embedded systems / Electronics | E63: diplôme d'ingénieur de l'Ecole Polytech Paris-Saclay parcours Electronique et Informatique pour l'Embarqué | F63: Engineering diploma of School Polytech Paris-Saclay – track: Electronics & Computer Science for l'Embarqué | G63: Diplôme d'ingénieur | H63: Polytech Paris-Saclay | I63: Groupement Polytech | J63: Site d'Orsay | K63: 91400 Orsay | L63: Public school / institute | M63: French | N63: General | O63: Bac +3 / Bac +4 | P63: Eligible on level (4-yr BS ≈ Bac+4) | Q63: 3/4 | R63: 12 | S63: 3950 | T63: 628 | U63: 2 | V63: =IF(S63="","",S63*U63) | W63: Not in catalogue. Public engineering diploma: national rate ~€601-628; many schools charge non-EU up to ~€3,950. Verify. | X63: Low | AC63: Open | AD63: 2026-10-01 | AE63: 2027-03-15 | AF63: Yes | AG63: https://www.polytech.universite-paris-saclay.fr/formation/electronique-et-informatique-pour-lembarque | AI63: Open in EEF
A64: 63 | B64: ★★★★★ | C64: 5 – Core fit (embedded/biomedical/health tech) | D64: Biomedical / Health tech | E64: diplôme d'ingénieur de l'Institut supérieur d'ingénieurs de Franche Comté de l'Université de Besançon spécialité génie biomédical | F64: Engineering diploma of Institute Higher of Engineers of Franche Comté of University of Besançon – specialisation: Biomedical Engineering | G64: Diplôme d'ingénieur | H64: Institut Supérieur d'Ingénieurs de Franche-Comté | I64: Université Marie et Louis Pasteur | J64: Site de Besançon | L64: Public school / institute | M64: French | N64: General | O64: Bac +3 / Bac +4 | P64: Eligible on level (4-yr BS ≈ Bac+4) | Q64: 1/2 | S64: 3950 | T64: 628 | U64: 2 | V64: =IF(S64="","",S64*U64) | W64: Not in catalogue. Public engineering diploma: national rate ~€601-628; many schools charge non-EU up to ~€3,950. Verify. | X64: Low | AA64: UMLP: individual exemption requests assessed on personal resources. | AB64: https://www.umlp.fr/sites/default/files/2026-07-02-page-droits-differencies-vf.pdf | AC64: Open | AD64: 2026-10-01 | AE64: 2027-03-15 | AF64: No | AG64: http://isifc.univ-fcomte.fr | AH64: Niveau B2 en français Niveau B1 en anglais Connaissances de bases solides en Mathématiques | AI64: Open in EEF
A65: 64 | B65: ★★★★★ | C65: 5 – Core fit (embedded/biomedical/health tech) | D65: Embedded systems / Electronics | E65: Diplôme d'ingénieur de l'école polytechnique universitaire de l'université d'Orléans, spécialité Génie physique et système embarqués | F65: Engineering diploma of the University Polytechnic School of University d'Orléans, – specialisation: Engineering Physics & Embedded Systems | G65: Diplôme d'ingénieur | H65: Polytech Orléans | I65: Groupement Polytech | J65: Site d'Orléans | K65: 45100 Orléans | L65: Public school / institute | M65: French | N65: General | O65: Bac +3 / Bac +4 | P65: Eligible on level (4-yr BS ≈ Bac+4) | Q65: 3/4 | R65: 12 | S65: 635 | U65: 2 | V65: =IF(S65="","",S65*U65) | W65: Catalogue lists €635 (EU/national rate). Confirm whether non-EU surcharge applies. | X65: Medium | Y65: 635 | AC65: Open | AD65: 2026-10-01 | AE65: 2027-03-15 | AF65: Yes | AG65: http://www.polytech-orleans.fr | AH65: Les informations qui suivent, concernent la candidature en cycle ingénieur (diplôme niveau Bac+5) du réseau Polytech. Les candidatures sont possibles : - en 3ème année (1ère année cycle ingénieur) avec un niveau Bac+2/Ba | AI65: Open in EEF
A66: 65 | B66: ★★★★★ | C66: 5 – Core fit (embedded/biomedical/health tech) | D66: Embedded systems / Electronics | E66: diplôme d'ingénieur de l'Ecole nationale supérieure d'ingénieurs de Caen spécialité génie physique et systèmes embarqués | F66: Engineering diploma of the National Graduate School of Engineers of Caen – specialisation: Engineering Physics & Embedded Systems | G66: Diplôme d'ingénieur | H66: Ecole nationale supérieure d'ingénieurs de Caen et centre de recherche | J66: Site de Caen | L66: Public school / institute | M66: French | N66: General | O66: Bac +3 / Bac +4 | P66: Eligible on level (4-yr BS ≈ Bac+4) | Q66: 1/2 | S66: 3879 | U66: 2 | V66: =IF(S66="","",S66*U66) | W66: Catalogue fee €3,879/yr (entered by institution). | X66: High | Y66: 3941/3879 | AC66: Open | AD66: 2026-10-01 | AE66: 2027-03-15 | AF66: Yes | AG66: https://www.ensicaen.fr/ | AH66: Le candidat doit obligatoirement suivre la procédure d'admission sur dossier de l'ENSICAEN dont le détail se trouve sur le site internet de l'établissement. Dates clés : Téléchargement et ouverture du dépôt des dossiers | AI66: Open in EEF
A67: 66 | B67: ★★★★★ | C67: 5 – Core fit (embedded/biomedical/health tech) | D67: Embedded systems / Electronics | E67: diplôme d'ingénieur de l'Ecole Polytechnique d'Université Côte d'Azur parcours électronique et systèmes embarqués | F67: Engineering diploma of School Polytechnique of University Côte d'Azur – track: Electronics & Embedded Systems | G67: Diplôme d'ingénieur | H67: Polytech Nice-Sophia | I67: Groupement Polytech | J67: Site de Biot | L67: Public school / institute | M67: French | N67: General | O67: Bac +3 / Bac +4 | P67: Eligible on level (4-yr BS ≈ Bac+4) | Q67: 3/4 | R67: 36/24 | S67: 3879 | U67: 2 | V67: =IF(S67="","",S67*U67) | W67: Catalogue fee €3,879/yr (entered by institution). | X67: High | Y67: 3879 | AC67: Open | AD67: 2026-10-01 | AE67: 2027-03-15 | AF67: Yes | AG67: https://polytech.univ-cotedazur.fr/ | AH67: Le curriculum de la formation se trouve sur Internet : http://www.polytech.univ-cotedazur.fr/ Frais d'inscription : Etudiants français ou d'un pays de l'union européenne, de l'espace économique européen ou de la Suisse : | AI67: Open in EEF
A68: 67 | B68: ★★★★★ | C68: 5 – Core fit (embedded/biomedical/health tech) | D68: Embedded systems / Electronics | E68: Diplôme d'ingénieur de l'Ecole Polytechnique de l'Université Clermont Auvergne parcours Systèmes Embarqués, Energie Electrique et Robotique | F68: Engineering diploma of School Polytechnique of University Clermont Auvergne – track: Embedded Systems, Energy Electrical & Robotics | G68: Diplôme d'ingénieur | H68: Polytech Clermont | I68: Groupement Polytech | J68: Clermont-Ferrand (Campus des Cézeaux - AUBIERE) | K68: 63178 AUBIERE CEDEX FRANCE | L68: Public school / institute | M68: French | N68: General | O68: Bac +3 / Bac +4 / Bac +5 | P68: Eligible on level (4-yr BS ≈ Bac+4) | Q68: 3/4/5 | R68: 12 | S68: 3879 | U68: 2 | V68: =IF(S68="","",S68*U68) | W68: Catalogue fee €3,879/yr (entered by institution). | X68: High | Y68: 3879 | AA68: UCA board (Dec 2025) kept its partial-exemption framework for 2026-27 (pre-decree; re-check). | AB68: https://www.uca.fr/medias/fichier/delib-ca-20251205-15-tarifs-differencies_1765204050111-pdf | AC68: Open | AD68: 2026-10-01 | AE68: 2027-03-15 | AF68: Yes | AG68: http://www.polytech-clermont.fr | AI68: Open in EEF
A69: 68 | B69: ★★★★★ | C69: 5 – Core fit (embedded/biomedical/health tech) | D69: Embedded systems / Electronics | E69: diplôme d'ingénieur de l'Ecole polytechnique de l'université Grenoble Alpes parcours informatique et électronique des systèmes embarqués | F69: Engineering diploma of School polytechnique of University Grenoble Alpes – track: Computer Science & Electronics of Embedded Systems | G69: Diplôme d'ingénieur | H69: Polytech Grenoble | I69: Groupement Polytech | J69: Site de Grenoble | L69: Public school / institute | M69: French | N69: General | O69: Bac +3 / Bac +4 | P69: Eligible on level (4-yr BS ≈ Bac+4) | Q69: 3/4 | R69: 12 | S69: 3950 | U69: 2 | V69: =IF(S69="","",S69*U69) | W69: Catalogue fee €3,950/yr (entered by institution). | X69: High | Y69: 3950 | AA69: UGA (incl. Grenoble INP masters): 2026-27 broad exemptions on request (pay national €254). From 2027-28 the decree caps apply; exemptions based on resources. | AB69: https://www.univ-grenoble-alpes.fr/actualites/a-la-une/actualites-universite/etudiants-internationaux-ce-que-change-le-nouveau-decret-sur-les-droits-d-inscription-a-l-uga-1775870.kjsp | AC69: Open | AD69: 2026-10-01 | AE69: 2027-03-15 | AF69: Yes | AG69: https://polytech.grenoble-inp.fr/ | AH69: Les informations qui suivent, concernent la candidature en cycle ingénieur (diplôme niveau Bac+5) du réseau Polytech. Les candidatures possibles - en 3ème année (1ère année cycle ingénieur) avec un niveau Bac+2/Bac+3 . - | AI69: Open in EEF
A70: 69 | B70: ★★★★★ | C70: 5 – Core fit (embedded/biomedical/health tech) | D70: Biomedical / Health tech | E70: diplôme d'ingénieur de l'École polytechnique universitaire de l'Université Lyon I spécialité génie biomédical | F70: Engineering diploma of the University Polytechnic School of University Lyon I – specialisation: Biomedical Engineering | G70: Diplôme d'ingénieur | H70: Polytech Lyon | I70: Groupement Polytech | J70: Site de Villeurbanne | L70: Public school / institute | M70: French | N70: General | O70: Bac +3 / Bac +4 | P70: Eligible on level (4-yr BS ≈ Bac+4) | Q70: 3/4 | R70: 12 | S70: 3950 | U70: 2 | V70: =IF(S70="","",S70*U70) | W70: Catalogue fee €3,950/yr (entered by institution). | X70: High | Y70: 3950 | AC70: Open | AD70: 2026-10-01 | AE70: 2027-03-15 | AF70: Yes | AG70: http://polytech.univ-lyon1.fr | AH70: Les informations qui suivent, concernent la candidature en cycle ingénieur (diplôme niveau Bac+5 ) du réseau Polytech. Les candidatures sont possibles : - en 3ème année (1ère année cycle ingénieur) avec un niveau Bac+2/B | AI70: Open in EEF
A71: 70 | B71: ★★★★★ | C71: 5 – Core fit (embedded/biomedical/health tech) | D71: Cybersecurity | E71: Master of science Cyber-Physical Social Systems | F71: Master of science Cyber-Physical Social Systems | G71: Master of Science (MSc) | H71: Ecole nationale supérieure des mines de Saint-Etienne | J71: Site de Saint-Etienne | L71: Public school / institute | M71: English | N71: Taught in English | O71: Bac +4 | P71: Eligible on level (4-yr BS ≈ Bac+4) | Q71: 1 | R71: 24 | S71: 4150 | U71: 2 | V71: =IF(S71="","",S71*U71) | W71: Not in catalogue. Mastersportal lists €4,150/yr for Mines Saint-Étienne MSc (verify with school). | X71: Low | AC71: Open | AD71: 2026-10-01 | AE71: 2027-03-15 | AF71: Yes | AG71: https://www.mines-stetienne.fr/en/academic/msc-cyber-physical-social-systems-cps2/ | AH71: Applicants with at least a Bachelor degree level (180 ECTS) or M1 degree level (240 ECTS) in computer science or equivalent are invited to apply. A good command of English is mandatory. International students’ applicatio | AI71: Open in EEF
A72: 71 | B72: ★★★★★ | C72: 5 – Core fit (embedded/biomedical/health tech) | D72: Cybersecurity | E72: Master indifférencié (recherche et professionnel) Sciences, technologies, santé mention informatique parcours Master of science Cyber-Physical Social Systems | F72: Science, Technology, Health (STS) – major: Computer Science – track: Master of Science Cyber-Physical Social Systems | G72: Master indifférencié (recherche et professionnel) | H72: Ecole nationale supérieure des mines de Saint-Etienne | J72: Site de Saint-Etienne | L72: Public school / institute | M72: French | N72: General | O72: Bac +4 / Bac +5 | P72: Eligible on level (4-yr BS ≈ Bac+4) | Q72: 1/2 | R72: 24/12 | S72: 4150 | U72: 2 | V72: =IF(S72="","",S72*U72) | W72: Not in catalogue. Mastersportal lists €4,150/yr for Mines Saint-Étienne MSc (verify with school). | X72: Low | AC72: Open | AD72: 2026-10-01 | AE72: 2027-03-15 | AF72: Yes | AI72: Open in EEF
A73: 72 | B73: ★★★★★ | C73: 5 – Core fit (embedded/biomedical/health tech) | D73: Biomedical / Health tech | E73: Master BioMedical Engineering | F73: Master BioMedical Engineering | G73: Master indifférencié (recherche et professionnel) | H73: Institut Supérieur d'Ingénieurs de Franche-Comté | I73: Université Marie et Louis Pasteur | J73: Site de Besançon | L73: Public school / institute | M73: English | N73: General | O73: Bac +4 / Bac +5 | P73: Eligible on level (4-yr BS ≈ Bac+4) | Q73: 1/2 | S73: 5000 | U73: 2 | V73: =IF(S73="","",S73*U73) | W73: Catalogue fee €5,000/yr (entered by institution). | X73: High | Y73: 5000 | AA73: UMLP: individual exemption requests assessed on personal resources. | AB73: https://www.umlp.fr/sites/default/files/2026-07-02-page-droits-differencies-vf.pdf | AC73: Open | AD73: 2026-10-01 | AE73: 2027-03-15 | AF73: Yes | AG73: http://isifc.univ-fcomte.fr | AI73: Open in EEF
A74: 73 | B74: ★★★★☆ | C74: 4 – Strong fit (electronics/signal/robotics/IoT/sensors) | D74: Signal / Image / Vision | E74: Master Sciences, technologies, santé, Optique, image, vision, mutlimédia | F74: Master Science, Technology, Health (STS), Optics, Image, Vision, Multimedia | G74: Master indifférencié (recherche et professionnel) | H74: UFR des sciences et technologie | I74: Université Paris-Est Créteil Val-de-Marne | J74: Site de Créteil | L74: Public university | M74: French | N74: General | O74: Bac +4 | P74: Eligible on level (4-yr BS ≈ Bac+4) | Q74: 1 | R74: 11 | S74: 254 | U74: 2 | V74: =IF(S74="","",S74*U74) | W74: Catalogue lists €254 (EU/national rate). Confirm whether non-EU surcharge applies. | X74: Medium | Y74: 254 | AC74: Open | AD74: 2026-10-01 | AE74: 2027-03-15 | AF74: No | AG74: http://sciences-tech.u-pec.fr | AH74: C2 ( C1 si anglophone) Etre titulaire d'une licence en Sciences pour l'Ingénieur avec de bons résultats en Mathématiques, Programmation et Data Science Bonjour Tout recours doit se faire par mail à l’adresse suivante : R | AI74: Open in EEF
A75: 74 | B75: ★★★★☆ | C75: 4 – Strong fit (electronics/signal/robotics/IoT/sensors) | D75: Robotics / Automation / Mechatronics | E75: Master indifférencié (recherche et professionnel) mention Automatique et Systèmes Électriques1 parcours Energie électrique et développement durable / electrical engineering for sustainable development. | F75: major: Automation & Systems Electrical1 – track: Energy Electrical & Development Sustainable / electrical engineering for sustainable development. | G75: Master indifférencié (recherche et professionnel) | H75: Faculté des sciences et technologies | I75: Université de Lille | J75: Département Electronique, électrotechnique et automatique | L75: Public university | M75: English | N75: Taught in English | O75: Bac +4 / Bac +5 | P75: Eligible on level (4-yr BS ≈ Bac+4) | Q75: 1/2 | R75: 12 | S75: 255 | U75: 2 | V75: =IF(S75="","",S75*U75) | W75: Catalogue lists €255 (EU/national rate). Confirm whether non-EU surcharge applies. | X75: Medium | Y75: 255/3950 | AA75: Lille opposed the decree; continues exemptions for part of non-EU students (master €254 if exempted). Apply for exemption early. | AB75: https://observalgerie.com/2026/06/13/misc/frais-dinscription-en-france-lille-maintient-un-avantage-pour-les-etudiants-etrangers/ | AC75: Open | AD75: 2026-10-01 | AE75: 2027-03-15 | AF75: No | AG75: https://formation.univ-lille.fr/fr/offre-de-formation/master-lmd-XB/master-automatique-et-systemes-electriques-MG001978/energie-electrique-et-developpement-durable-electrical-engineering-for-sustainable-development-m2-MX002024.html | AH75: Le candidat doit avoir un niveau M1 ou équivalent en EEA (Electronique, Electrotechique et Automatique). Niveau d'anglais C1 exigé. | AI75: Open in EEF
A76: 75 | B76: ★★★★☆ | C76: 4 – Strong fit (electronics/signal/robotics/IoT/sensors) | D76: Neuroscience / Neuro-engineering | E76: Euro-mediterranean Master in Neurosciences Online - | F76: Euro-mediterranean Master in Neuroscience Online | G76: Master indifférencié (recherche et professionnel) | H76: Faculté des sciences de la vie | I76: Université de Strasbourg | J76: Site de Strasbourg | K76: 67000 Strasbourg | L76: Public university | M76: English | N76: General | O76: Bac +4 | P76: Eligible on level (4-yr BS ≈ Bac+4) | Q76: 1 | S76: 3950 | T76: 255 | U76: 2 | V76: =IF(S76="","",S76*U76) | W76: Catalogue: €3,950. = national differentiated master fee (2026-27: €3,950). Exemption to ~€255 possible (university quota). | X76: High | Y76: 3950 | AA76: Unistra: master entrants who did not do their licence at Unistra pay the differentiated fee (€3,950). | AB76: https://www.unistra.fr/fr/node/8168 | AC76: Open | AD76: 2026-10-01 | AE76: 2027-03-15 | AF76: No | AG76: http://sciencesvie.unistra.fr/ | AH76: Le programme propose un cursus international en neuroscience, avec des cours et des évaluations identiques dispensés par chacune des 4 Universités Françaises ainsi que 14 partenaires issus d’Europe et de la zone méditerr | AI76: Open in EEF
A77: 76 | B77: ★★★★☆ | C77: 4 – Strong fit (electronics/signal/robotics/IoT/sensors) | D77: Neuroscience / Neuro-engineering | E77: Interdisciplinary trainining in Neuroscience and Pain | F77: Interdisciplinary trainining in Neuroscience and Pain | G77: Master indifférencié (recherche et professionnel) | H77: Faculté des sciences de la vie | I77: Université de Strasbourg | J77: Site de Strasbourg | K77: 67000 Strasbourg | L77: Public university | M77: English | N77: General | O77: Bac +4 / Bac +5 | P77: Eligible on level (4-yr BS ≈ Bac+4) | Q77: 1/2 | S77: 3950 | T77: 255 | U77: 2 | V77: =IF(S77="","",S77*U77) | W77: Catalogue: €3,950. = national differentiated master fee (2026-27: €3,950). Exemption to ~€255 possible (university quota). | X77: High | Y77: 3950 | AA77: Unistra: master entrants who did not do their licence at Unistra pay the differentiated fee (€3,950). | AB77: https://www.unistra.fr/fr/node/8168 | AC77: Open | AD77: 2026-10-01 | AE77: 2027-03-15 | AF77: No | AG77: http://sciencesvie.unistra.fr/ | AH77: M1 : La sélection et le classement des dossiers de candidature reposeront sur l'examen des résultats académiques de l'ensemble de la licence, permettant de justifier d'un niveau suffisant pour une poursuite en master dan | AI77: Open in EEF
A78: 77 | B78: ★★★★☆ | C78: 4 – Strong fit (electronics/signal/robotics/IoT/sensors) | D78: Signal / Image / Vision | E78: Master indifférencié (recherche et professionnel) Sciences, technologies, santé mention Optique, image, vision, mutlimédia parcours international biométrie et vision intelligente (I-BVI) | F78: Science, Technology, Health (STS) – major: Optics, Image, Vision, Multimedia – track: international biométrie & Vision intelligente (I-BVI) | G78: Master indifférencié (recherche et professionnel) | H78: UFR des sciences et technologie | I78: Université Paris-Est Créteil Val-de-Marne | J78: Site de Créteil | L78: Public university | M78: English | N78: General | O78: Bac +4 / Bac +5 | P78: Eligible on level (4-yr BS ≈ Bac+4) | Q78: 1/2 | R78: 10 | S78: 3950 | T78: 255 | U78: 2 | V78: =IF(S78="","",S78*U78) | W78: Catalogue: €3,950. = national differentiated master fee (2026-27: €3,950). Exemption to ~€255 possible (university quota). | X78: High | Y78: 3950 | AC78: Open | AD78: 2026-10-01 | AE78: 2027-03-15 | AF78: No | AG78: http://sciences-tech.u-pec.fr | AH78: traitement d'image, programmation Python | AI78: Open in EEF
A79: 78 | B79: ★★★★☆ | C79: 4 – Strong fit (electronics/signal/robotics/IoT/sensors) | D79: Neuroscience / Neuro-engineering | E79: Master indifférencié (recherche et professionnel) Sciences, technologies, santé mention sciences du vivant parcours Dual Master in Neuroscience | F79: Science, Technology, Health (STS) – major: Sciences of Life – track: Dual Master in Neuroscience | G79: Master indifférencié (recherche et professionnel) | H79: Faculté des sciences de la vie | I79: Université de Strasbourg | J79: Site de Strasbourg | K79: 67000 Strasbourg | L79: Public university | M79: English | N79: General | O79: Bac +4 | P79: Eligible on level (4-yr BS ≈ Bac+4) | Q79: 1 | S79: 3950 | T79: 255 | U79: 2 | V79: =IF(S79="","",S79*U79) | W79: Catalogue: €3,950. = national differentiated master fee (2026-27: €3,950). Exemption to ~€255 possible (university quota). | X79: High | Y79: 3950 | AA79: Unistra: master entrants who did not do their licence at Unistra pay the differentiated fee (€3,950). | AB79: https://www.unistra.fr/fr/node/8168 | AC79: Open | AD79: 2026-10-01 | AE79: 2027-03-15 | AF79: No | AG79: http://sciencesvie.unistra.fr/ | AH79: Le parcours DMN est un parcours international de formation avancée en neuroscience organise conjointement par l’université du Manitoba (Canada) et celle de Strasbourg (France). Ce programme délivre un double diplôme de n | AI79: Open in EEF
A80: 79 | B80: ★★★★☆ | C80: 4 – Strong fit (electronics/signal/robotics/IoT/sensors) | D80: Robotics / Automation / Mechatronics | E80: Master indifférencié (recherche et professionnel) Sciences, technologies, santé mention Traitement Automatique des Langues (TAL) | F80: Science, Technology, Health (STS) – major: Processing Automation of Languages (TAL) | G80: Master indifférencié (recherche et professionnel) | H80: Institut des Sciences du Digital, Management et Cognition | I80: Université de Lorraine | J80: Site de Nancy | L80: Public school / institute | M80: English | N80: Taught in English | O80: Bac +4 | P80: Eligible on level (4-yr BS ≈ Bac+4) | Q80: 1 | S80: 3950 | T80: 255 | U80: 2 | V80: =IF(S80="","",S80*U80) | W80: Catalogue: €3,950. = national differentiated master fee (2026-27: €3,950). Exemption to ~€255 possible (university quota). | X80: High | Y80: 3950 | Z80: • Application fees for Msc 1 = 3950€ + Student Life and Campus Contribution (CVEC) whi … ch came to 105€ in 2026/2027 | AC80: Open | AD80: 2026-10-01 | AE80: 2027-03-15 | AF80: No | AG80: https://idmc.univ-lorraine.fr/idmc-master-degree-in-natural-language-processing/ | AH80: Deadline for transmitting the application form: ( date to be confirmed by the ambassy) Deadline for attending courses: September 01st 2027 Fluency in English required : C1 Academic qualifications : You must hold a « Bac+ | AI80: Open in EEF
A81: 80 | B81: ★★★★☆ | C81: 4 – Strong fit (electronics/signal/robotics/IoT/sensors) | D81: Sensors / Instrumentation / Micro-Nano / Photonics | E81: Master indifférencié (recherche et professionnel) spécialité Physique fondamentale et applications parcours Quantum and Photonic Technologies | F81: specialisation: Physics Fundamental & Applications – track: Quantum and Photonic Technologies | G81: Master indifférencié (recherche et professionnel) | H81: Faculté des sciences et technologies | I81: Université de Lille | J81: Département Physique | L81: Public university | M81: English | N81: Taught in English | O81: Bac +4 / Bac +5 | P81: Eligible on level (4-yr BS ≈ Bac+4) | Q81: 1/2 | R81: 12 | S81: 3950 | T81: 255 | U81: 2 | V81: =IF(S81="","",S81*U81) | W81: Catalogue: €3,950. = national differentiated master fee (2026-27: €3,950). Exemption to ~€255 possible (university quota). | X81: High | Y81: 3950 | AA81: Lille opposed the decree; continues exemptions for part of non-EU students (master €254 if exempted). Apply for exemption early. | AB81: https://observalgerie.com/2026/06/13/misc/frais-dinscription-en-france-lille-maintient-un-avantage-pour-les-etudiants-etrangers/ | AC81: Open | AD81: 2026-10-01 | AE81: 2027-03-15 | AF81: No | AG81: https://formation.univ-lille.fr/fr/offre-de-formation/master-lmd-XB/master-physique-fondamentale-et-applications-MG001988/quantum-and-photonic-technologies-m1-m2-MX195427.html | AH81: M1 : Bachelor degree in physics with courses on quantum theory, statistical physics, electromagnetism, optics, waves, thermodynamics, mechanics and mathematical tools for physics M2 : Equivalent to a first year graduate | AI81: Open in EEF
A82: 81 | B82: ★★★★☆ | C82: 4 – Strong fit (electronics/signal/robotics/IoT/sensors) | D82: Neuroscience / Neuro-engineering | E82: Master Sciences, technologies, santé, mention Neurosciences | F82: Master Science, Technology, Health (STS), – major: Neuroscience | G82: Master indifférencié (recherche et professionnel) | H82: UFR Biosciences (Biologie, Biochimie) | I82: Université Claude Bernard - Lyon 1 | J82: Site de Villeurbanne | L82: Public university | M82: English | N82: General | O82: Bac +4 | P82: Eligible on level (4-yr BS ≈ Bac+4) | Q82: 1 | S82: 3950 | T82: 255 | U82: 2 | V82: =IF(S82="","",S82*U82) | W82: Catalogue: €3,950. = national differentiated master fee (2026-27: €3,950). Exemption to ~€255 possible (university quota). | X82: High | Y82: 3950 | Z82: Pour les pré-requis, consulter le site web https://masterneuro | AA82: Lyon 1: individual exemptions within the 30% quota (2026-27), apply via eCandidat. | AB82: https://www.univ-lyon1.fr/formation/inscription-et-scolarite/etudiantes-et-etudiants-internationaux-droits-dinscription-differencies-et-exonerations | AC82: Open | AD82: 2026-10-01 | AE82: 2027-03-15 | AF82: No | AG82: https://ufr-biosciences.univ-lyon1.fr | AH82: La formation est intégralement en anglais et nécessite donc la justification d'un niveau B2 en Anglais. Pour les pré-requis, consulter le site web: https://masterneuro.univ-lyon1.fr/paths/m1-main/m1-admission/ Il est ess | AI82: Open in EEF
A83: 82 | B83: ★★★★☆ | C83: 4 – Strong fit (electronics/signal/robotics/IoT/sensors) | D83: IoT / Telecom / Networks | E83: Master's degree in Telecommunications and Networks | F83: Master's degree in Telecommunications and Networks | G83: Master indifférencié (recherche et professionnel) | H83: Conservatoire national des arts et métiers - CNAM | J83: Cnam Etablissement Public - EPN3 Electronics, Electrical engineering, Applied physics | L83: Public school / institute | M83: English | N83: Taught in English | O83: Bac +4 / Bac +5 | P83: Eligible on level (4-yr BS ≈ Bac+4) | Q83: 1/2 | R83: 12 | S83: 3950 | T83: 255 | U83: 2 | V83: =IF(S83="","",S83*U83) | W83: Catalogue: €3,950. = national differentiated master fee (2026-27: €3,950). Exemption to ~€255 possible (university quota). | X83: High | Y83: 3950 | AC83: Open | AD83: 2026-10-01 | AE83: 2027-03-15 | AF83: Yes | AG83: https://eeap.cnam.fr | AH83: This program is aimed at graduates with a Bachelor of Science or equivalent degree obtained after 4 years' higher education in Telecommunications and Networks. Application procedure opens from early April to late June. A | AI83: Open in EEF
A84: 83 | B84: ★★★★☆ | C84: 4 – Strong fit (electronics/signal/robotics/IoT/sensors) | D84: Embedded systems / Electronics | E84: mention Nanosciences and Nanotechnologies parcours Electronic technologies for smart communicating systems | F84: major: Nanosciences and Nanotechnologies – track: Electronic Technologies for smart communicating systems | G84: Master indifférencié (recherche et professionnel) | H84: Faculté des sciences et technologies | I84: Université de Lille | J84: Département Electronique, électrotechnique et automatique | L84: Public university | M84: English | N84: Taught in English | O84: Bac +4 / Bac +5 | P84: Eligible on level (4-yr BS ≈ Bac+4) | Q84: 1/2 | R84: 12 | S84: 3950 | T84: 255 | U84: 2 | V84: =IF(S84="","",S84*U84) | W84: Catalogue: €3,950. = national differentiated master fee (2026-27: €3,950). Exemption to ~€255 possible (university quota). | X84: High | Y84: 3950 | AA84: Lille opposed the decree; continues exemptions for part of non-EU students (master €254 if exempted). Apply for exemption early. | AB84: https://observalgerie.com/2026/06/13/misc/frais-dinscription-en-france-lille-maintient-un-avantage-pour-les-etudiants-etrangers/ | AC84: Open | AD84: 2026-10-01 | AE84: 2027-03-15 | AF84: No | AG84: https://www.univ-lille.fr/formations/fr-00002031 | AH84: Prérequis affichés aux étudiants : Bachelor in Electronic, Electrical Engineering, applied physics, physics, Engineering school. Physics of semiconductor, microelectronic, nanoelectronic, Electronic devices, circuits, mi | AI84: Open in EEF
A85: 84 | B85: ★★★★☆ | C85: 4 – Strong fit (electronics/signal/robotics/IoT/sensors) | D85: Sensors / Instrumentation / Micro-Nano / Photonics | E85: Master rech. Sciences, technologies, santé mention micro et nanotechnologies | F85: Research Master Science, Technology, Health (STS) – major: micro & Nanotechnologies | G85: Master recherche | H85: Institut national des sciences appliquées de Lyon | J85: Site de Villeurbanne | L85: Public school / institute | M85: English | N85: General | O85: Bac +4 | P85: Eligible on level (4-yr BS ≈ Bac+4) | Q85: 1 | R85: 12 | S85: 3950 | T85: 255 | U85: 1 | V85: =IF(S85="","",S85*U85) | W85: Catalogue: €3,941. = national differentiated master fee (2026-27: €3,950). Exemption to ~€255 possible (university quota). | X85: High | Y85: 3941 | AC85: Open | AD85: 2026-10-01 | AE85: 2027-03-15 | AF85: Yes | AG85: https://www.ec-lyon.fr/formation/international-master-nanoscale-engineering | AH85: Le Master est accessible en M1 à tous les étudiants titulaires d’une Licence de Sciences et Technologies (physique, chimie, sciences des matériaux, biologie…) ou directement au niveau M2 aux élèves-ingénieurs/étudiants a | AI85: Open in EEF
A86: 85 | B86: ★★★★☆ | C86: 4 – Strong fit (electronics/signal/robotics/IoT/sensors) | D86: Sensors / Instrumentation / Micro-Nano / Photonics | E86: Master rech. Sciences, technologies, santé, mention Nanosciences Nanotechnologies | F86: Research Master Science, Technology, Health (STS), – major: Nanosciences Nanotechnologies | G86: Master recherche | H86: Institut national des sciences appliquées de Lyon | J86: Site de Villeurbanne | L86: Public school / institute | M86: English | N86: General | O86: Bac +4 | P86: Eligible on level (4-yr BS ≈ Bac+4) | Q86: 2 | R86: 12 | S86: 3950 | T86: 255 | U86: 1 | V86: =IF(S86="","",S86*U86) | W86: Catalogue: €3,941. = national differentiated master fee (2026-27: €3,950). Exemption to ~€255 possible (university quota). | X86: High | Y86: 3941 | AC86: Open | AD86: 2026-10-01 | AE86: 2027-03-15 | AF86: Yes | AG86: https://www.ec-lyon.fr/formation/international-master-nanoscale-engineering | AH86: Le Master est accessible en M1 à tous les étudiants titulaires d’une Licence de Sciences et Technologies (physique, chimie, sciences des matériaux, biologie…) ou directement au niveau M2 aux élèves-ingénieurs/étudiants a | AI86: Open in EEF
A87: 86 | B87: ★★★★☆ | C87: 4 – Strong fit (electronics/signal/robotics/IoT/sensors) | D87: Electrical energy | E87: International Master of Science in Electrical Engineering for Smart Grids and Buildings (SGB) | F87: International Master of Science in Electrical Engineering for Smart Grids and Buildings (SGB) | G87: Master indifférencié (recherche et professionnel) | H87: Ecole nationale supérieure de l'énergie, l'eau et l'environnement - Grenoble INP | I87: Grenoble INP | J87: Site de Grenoble | L87: Public school / institute | M87: English | N87: Taught in English | O87: Bac +4 / Bac +5 | P87: Eligible on level (4-yr BS ≈ Bac+4) | Q87: 1/2 | S87: 3950 | T87: 255 | U87: 2 | V87: =IF(S87="","",S87*U87) | W87: Not in catalogue. Public national master → 2026-27 differentiated fee €3,950; exemption to ~€254-255 depends on university quota (25% cap in 2027-28). | X87: Medium | AA87: UGA (incl. Grenoble INP masters): 2026-27 broad exemptions on request (pay national €254). From 2027-28 the decree caps apply; exemptions based on resources. | AB87: https://www.univ-grenoble-alpes.fr/actualites/a-la-une/actualites-universite/etudiants-internationaux-ce-que-change-le-nouveau-decret-sur-les-droits-d-inscription-a-l-uga-1775870.kjsp | AC87: Open | AD87: 2026-10-01 | AE87: 2027-03-15 | AF87: Yes | AG87: https://ense3.grenoble-inp.fr/en/study-at-ense3/masters-in-english | AH87: ***PAGE CURRENTLY BEING UPDATED FOR THE 2027–2028 ACADEMIC YEAR*** Before applying, it is important to check the cost of the programme as well as the level of financial resources required for your year of study in France | AI87: Open in EEF
A88: 87 | B88: ★★★★☆ | C88: 4 – Strong fit (electronics/signal/robotics/IoT/sensors) | D88: Embedded systems / Electronics | E88: Master indifférencié (recherche et professionnel) mention Master EMIMEP : European Master for Industry in Microwave Electronics and Photonics | F88: major: Master EMIMEP : European Master for Industry in Microwave Electronics and Photonics | G88: Master indifférencié (recherche et professionnel) | H88: Faculté des Sciences et Techniques | I88: Université de Limoges | J88: Campus de la Borie Limoges | L88: Public university | M88: English | N88: Taught in English | O88: Bac +4 / Bac +5 | P88: Eligible on level (4-yr BS ≈ Bac+4) | Q88: 1/2 | R88: 10 | S88: 3950 | T88: 255 | U88: 2 | V88: =IF(S88="","",S88*U88) | W88: Not in catalogue. Public national master → 2026-27 differentiated fee €3,950; exemption to ~€254-255 depends on university quota (25% cap in 2027-28). | X88: Medium | AC88: Open | AD88: 2026-10-01 | AE88: 2027-03-15 | AF88: Yes | AG88: https://www.erasmus-mundus.emimep.eu/ | AH88: Bachelor diploma in Electronic Engineering, telecommunication engineering, or applied physics with solid bases in signal processing, electromagnetism, telecommunications, embedded systems, analogue and digital electronic | AI88: Open in EEF
A89: 88 | B89: ★★★★☆ | C89: 4 – Strong fit (electronics/signal/robotics/IoT/sensors) | D89: Sensors / Instrumentation / Micro-Nano / Photonics | E89: Master indifférencié (recherche et professionnel) mention Physique fondamentale et applications parcours Engineering Physics & Advanced Photonics Technologies | F89: major: Physics Fundamental & Applications – track: Engineering Physics & Advanced Photonics Technologies | G89: Master indifférencié (recherche et professionnel) | H89: UFR Sciences et Techniques | I89: Université Marie et Louis Pasteur | J89: Site de Besançon | K89: 25030 BESANCON CEDEX | L89: Public university | M89: English | N89: Taught in English | O89: Bac +4 | P89: Eligible on level (4-yr BS ≈ Bac+4) | Q89: 1 | R89: 12 | S89: 3950 | T89: 255 | U89: 2 | V89: =IF(S89="","",S89*U89) | W89: Not in catalogue. Public national master → 2026-27 differentiated fee €3,950; exemption to ~€254-255 depends on university quota (25% cap in 2027-28). | X89: Medium | AA89: UMLP: individual exemption requests assessed on personal resources. | AB89: https://www.umlp.fr/sites/default/files/2026-07-02-page-droits-differencies-vf.pdf | AC89: Open | AD89: 2026-10-01 | AE89: 2027-03-15 | AF89: No | AG89: https://taughtie.campusfrance.org/tiesearch/#/program/3551 | AH89: Course in English for students holding a degree in Physics or equivalent (License, Bachelor of Sciences, Licenciatura, etc.).English level B2, or equivalent, is required. The prerequisite disciplines are general physics, | AI89: Open in EEF
A90: 89 | B90: ★★★★☆ | C90: 4 – Strong fit (electronics/signal/robotics/IoT/sensors) | D90: Sensors / Instrumentation / Micro-Nano / Photonics | E90: Master indifférencié (recherche et professionnel) Nanosciences and Nanotechnologies parcours Nanoscale and Quantum Engineering | F90: Nanosciences and Nanotechnologies – track: Nanoscale and Quantum Engineering | G90: Master indifférencié (recherche et professionnel) | H90: UFR Sciences | I90: Université d'Aix-Marseille | J90: Site de Marseille - St Jérôme | L90: Public university | M90: English | N90: Taught in English | O90: Bac +4 / Bac +5 | P90: Eligible on level (4-yr BS ≈ Bac+4) | Q90: 1/2 | R90: 12 | S90: 3950 | T90: 255 | U90: 2 | V90: =IF(S90="","",S90*U90) | W90: Not in catalogue. Public national master → 2026-27 differentiated fee €3,950; exemption to ~€254-255 depends on university quota (25% cap in 2027-28). | X90: Medium | AA90: AMU 2026-27: limited exemptions (≈1,800 of 5,500 students) – priority to continuing students, conflict zones, excellence scholarships. New master entrants usually pay €3,950. | AB90: https://www.univ-amu.fr/fr/actualites/aix-marseille-universite-mobilise-pleinement-capacite-dexoneration-continuer-accueillir | AC90: Open | AD90: 2026-10-01 | AE90: 2027-03-15 | AF90: No | AG90: https://formations.univ-amu.fr/fr/master/5SNN/PRSNN5C3 | AH90: 4 important points for your application : Your application must be complete and validated by the Espace Etudes in France The faculty will review the applications The level of English required is B2 Opportunity to apply f | AI90: Open in EEF
A91: 90 | B91: ★★★★☆ | C91: 4 – Strong fit (electronics/signal/robotics/IoT/sensors) | D91: Neuroscience / Neuro-engineering | E91: Master indifférencié (recherche et professionnel) parcours IDIL - Master Integrative Neuroscience and Omics | F91: track: IDIL - Master Integrative Neuroscience and Omics | G91: Master indifférencié (recherche et professionnel) | H91: UFR des Sciences de Montpellier | I91: Université de Montpellier | J91: Site de Montpellier | L91: Public university | M91: English | N91: Taught in English | O91: Bac +4 / Bac +5 | P91: Eligible on level (4-yr BS ≈ Bac+4) | Q91: 1/2 | R91: 12 | S91: 3950 | T91: 255 | U91: 2 | V91: =IF(S91="","",S91*U91) | W91: Not in catalogue. Public national master → 2026-27 differentiated fee €3,950; exemption to ~€254-255 depends on university quota (25% cap in 2027-28). | X91: Medium | AA91: Montpellier 2026-27: new non-EU entrants pay the differentiated fee unless individual exemption (limited). | AB91: https://www.umontpellier.fr/en/international/etudier-a-letranger/etudiants-internationaux-annee-universitaire-2026-2027/ | AC91: Open | AD91: 2026-10-01 | AE91: 2027-03-15 | AF91: No | AG91: https://idil.edu.umontpellier.fr/ | AH91: Conditions d’accès Diplôme de licence dans la discipline choisie IDIL Niveau d’anglais B2 minimum CV et lettre de motivation 2 lettres de soutien d’un chercheur et/ou professeur (recommandé, mais non obligatoire) Estimat | AI91: Open in EEF
A92: 91 | B92: ★★★★☆ | C92: 4 – Strong fit (electronics/signal/robotics/IoT/sensors) | D92: Biomedical / Health tech | E92: Master indifférencié (recherche et professionnel) parcours IDIL - Master Photonics & Electronics Sensors for Environment & Health | F92: track: IDIL - Master Photonics & Electronics Sensors for Environment & Health | G92: Master indifférencié (recherche et professionnel) | H92: UFR des Sciences de Montpellier | I92: Université de Montpellier | J92: Site de Montpellier | L92: Public university | M92: English | N92: Taught in English | O92: Bac +4 / Bac +5 | P92: Eligible on level (4-yr BS ≈ Bac+4) | Q92: 1/2 | R92: 12 | S92: 3950 | T92: 255 | U92: 2 | V92: =IF(S92="","",S92*U92) | W92: Not in catalogue. Public national master → 2026-27 differentiated fee €3,950; exemption to ~€254-255 depends on university quota (25% cap in 2027-28). | X92: Medium | AA92: Montpellier 2026-27: new non-EU entrants pay the differentiated fee unless individual exemption (limited). | AB92: https://www.umontpellier.fr/en/international/etudier-a-letranger/etudiants-internationaux-annee-universitaire-2026-2027/ | AC92: Open | AD92: 2026-10-01 | AE92: 2027-03-15 | AF92: No | AG92: https://idil.edu.umontpellier.fr/ | AH92: Diplôme de licence dans le champ disciplinaire • Niveau d’anglais B2 minimum • CV et lettre de motivation • 2 lettres de soutien d’un chercheur et/ou professeur • Estimation du classement de l’étudiant dans sa promotion | AI92: Open in EEF
A93: 92 | B93: ★★★★☆ | C93: 4 – Strong fit (electronics/signal/robotics/IoT/sensors) | D93: Robotics / Automation / Mechatronics | E93: Master indifférencié (recherche et professionnel) parcours Master in Advanced Mechatronics | F93: track: Master in Advanced Mechatronics | G93: Master indifférencié (recherche et professionnel) | H93: Polytech Annecy-Chambéry | I93: Groupement Polytech | J93: Site d'Annecy | L93: Public school / institute | M93: English | N93: Taught in English | O93: Bac +4 / Bac +5 | P93: Eligible on level (4-yr BS ≈ Bac+4) | Q93: 1/2 | R93: 10/12 | S93: 3950 | T93: 255 | U93: 2 | V93: =IF(S93="","",S93*U93) | W93: Not in catalogue. Public national master → 2026-27 differentiated fee €3,950; exemption to ~€254-255 depends on university quota (25% cap in 2027-28). | X93: Medium | AC93: Open | AD93: 2026-10-01 | AE93: 2027-03-15 | AF93: No | AG93: http://www.polytech.univ-smb.fr/en/programs/masters/advanced-mechatronics.html | AI93: Open in EEF
A94: 93 | B94: ★★★★☆ | C94: 4 – Strong fit (electronics/signal/robotics/IoT/sensors) | D94: Robotics / Automation / Mechatronics | E94: Master indifférencié (recherche et professionnel) Sciences, Technologie, Santé mention Automatique, robotique parcours Advanced robotics mechatronics and automatic control | F94: Sciences, Technology, Health – major: Automation, Robotics – track: Advanced robotics mechatronics and automatic control | G94: Master indifférencié (recherche et professionnel) | H94: UFR Sciences et Techniques | I94: Université Marie et Louis Pasteur | J94: Site de Besançon | K94: 25030 BESANCON CEDEX | L94: Public university | M94: English | N94: Taught in English | O94: Bac +4 | P94: Eligible on level (4-yr BS ≈ Bac+4) | Q94: 1 | R94: 12 | S94: 3950 | T94: 255 | U94: 2 | V94: =IF(S94="","",S94*U94) | W94: Not in catalogue. Public national master → 2026-27 differentiated fee €3,950; exemption to ~€254-255 depends on university quota (25% cap in 2027-28). | X94: Medium | AA94: UMLP: individual exemption requests assessed on personal resources. | AB94: https://www.umlp.fr/sites/default/files/2026-07-02-page-droits-differencies-vf.pdf | AC94: Open | AD94: 2026-10-01 | AE94: 2027-03-15 | AF94: No | AG94: https://taughtie.campusfrance.org/tiesearch/#/program/3549 | AH94: Bachelor in Electrical, Mechanical, Mechatronics or Control Engineering; English level equivalent to B2 | AI94: Open in EEF
A95: 94 | B95: ★★★★☆ | C95: 4 – Strong fit (electronics/signal/robotics/IoT/sensors) | D95: Embedded systems / Electronics | E95: Master indifférencié (recherche et professionnel) Sciences, Technologies, Santé mention Electronique, énergie électrique, automatique parcours Electrical Engineering and Control Systems Parcours International | F95: Science, Technology, Health (STS) – major: Electronics, Electrical Energy & Automation (EEA) – track: Electrical Engineering and Control Systems – track: International | G95: Master indifférencié (recherche et professionnel) | H95: UFR de Physique, ingénierie, terre, environnement, mécanique | I95: Université de Grenoble Alpes | J95: Site de Grenoble - Polygone scientifique - GreEn-ER | L95: Public university | M95: English | N95: Taught in English | O95: Bac +4 | P95: Eligible on level (4-yr BS ≈ Bac+4) | Q95: 1 | S95: 3950 | T95: 255 | U95: 2 | V95: =IF(S95="","",S95*U95) | W95: Not in catalogue. Public national master → 2026-27 differentiated fee €3,950; exemption to ~€254-255 depends on university quota (25% cap in 2027-28). | X95: Medium | AA95: UGA (incl. Grenoble INP masters): 2026-27 broad exemptions on request (pay national €254). From 2027-28 the decree caps apply; exemptions based on resources. | AB95: https://www.univ-grenoble-alpes.fr/actualites/a-la-une/actualites-universite/etudiants-internationaux-ce-que-change-le-nouveau-decret-sur-les-droits-d-inscription-a-l-uga-1775870.kjsp | AC95: Open | AD95: 2026-10-01 | AE95: 2027-03-15 | AF95: No | AG95: https://formations.univ-grenoble-alpes.fr/fr/catalogue-2021/master-XB/master-electronique-energie-electrique-automatique-IFZ3DRB9/parcours-electrical-engineering-and-control-systems-1ere-annee-KVQSSM5S.html | AH95: "General requirements: - hold a M1, bachelor or equivalent degree completed after four full years of University studies; - prove an English proficiency with CEFR (B2), TOEFL (IBT 87-109), IELTS (5.5-6.5), TOEIC (785-945) | AI95: Open in EEF
A96: 95 | B96: ★★★★☆ | C96: 4 – Strong fit (electronics/signal/robotics/IoT/sensors) | D96: Embedded systems / Electronics | E96: Master indifférencié (recherche et professionnel) Sciences, technologies, santé mention Electronique, énergie électrique, automatique parcours Master of Science in Electrical Engineering for Smart Grids and Buildings (SGB) | F96: Science, Technology, Health (STS) – major: Electronics, Electrical Energy & Automation (EEA) – track: Master of Science in Electrical Engineering for Smart Grids and Buildings (SGB) | G96: Master indifférencié (recherche et professionnel) | H96: Ecole nationale supérieure de l'énergie, l'eau et l'environnement - Grenoble INP | I96: Grenoble INP | J96: Site de Grenoble | L96: Public school / institute | M96: English | N96: General | O96: Bac +4 / Bac +5 | P96: Eligible on level (4-yr BS ≈ Bac+4) | Q96: 1/2 | S96: 3950 | T96: 255 | U96: 2 | V96: =IF(S96="","",S96*U96) | W96: Not in catalogue. Public national master → 2026-27 differentiated fee €3,950; exemption to ~€254-255 depends on university quota (25% cap in 2027-28). | X96: Medium | Z96: ropean Economic Area, Andorra or Switzerland) and for students from Quebec fees will be : €1485 per year , plus campus tax* For non EU-studen … ts fees will be : €5180 per year , plus campus tax* * Fees are indica | AA96: UGA (incl. Grenoble INP masters): 2026-27 broad exemptions on request (pay national €254). From 2027-28 the decree caps apply; exemptions based on resources. | AB96: https://www.univ-grenoble-alpes.fr/actualites/a-la-une/actualites-universite/etudiants-internationaux-ce-que-change-le-nouveau-decret-sur-les-droits-d-inscription-a-l-uga-1775870.kjsp | AC96: Open | AD96: 2026-10-01 | AE96: 2027-03-15 | AF96: Yes | AG96: https://ense3.grenoble-inp.fr/en/study-at-ense3/masters-in-english | AH96: ***PAGE CURRENTLY BEING UPDATED FOR THE 2027–2028 ACADEMIC YEAR*** Before applying, it is important to check the cost of the programme as well as the level of financial resources required for your year of study in France | AI96: Open in EEF
A97: 96 | B97: ★★★★☆ | C97: 4 – Strong fit (electronics/signal/robotics/IoT/sensors) | D97: Embedded systems / Electronics | E97: Master indifférencié (recherche et professionnel) Sciences, technologies, santé mention Electronique, Energie électrique, Automatique parcours Robotique | F97: Science, Technology, Health (STS) – major: Electronics, Electrical Energy & Automation (EEA) – track: Robotics | G97: Master indifférencié (recherche et professionnel) | H97: UFR des Sciences de Montpellier | I97: Université de Montpellier | J97: Site de Montpellier | L97: Public university | M97: English | N97: General | O97: Bac +4 / Bac +5 | P97: Eligible on level (4-yr BS ≈ Bac+4) | Q97: 1/2 | S97: 3950 | T97: 255 | U97: 2 | V97: =IF(S97="","",S97*U97) | W97: Not in catalogue. Public national master → 2026-27 differentiated fee €3,950; exemption to ~€254-255 depends on university quota (25% cap in 2027-28). | X97: Medium | AA97: Montpellier 2026-27: new non-EU entrants pay the differentiated fee unless individual exemption (limited). | AB97: https://www.umontpellier.fr/en/international/etudier-a-letranger/etudiants-internationaux-annee-universitaire-2026-2027/ | AC97: Open | AD97: 2026-10-01 | AE97: 2027-03-15 | AF97: No | AG97: http://www.eea.univ-montp2.fr/?-Robotique-Automatique- | AH97: Description: second year master in Robotics - one year course taught in English Requirements: At least four years of university studies (equivalent of 240 ECTS), in a field related to Robotics, such as: • Mechatronics • | AI97: Open in EEF
A98: 97 | B98: ★★★★☆ | C98: 4 – Strong fit (electronics/signal/robotics/IoT/sensors) | D98: Sensors / Instrumentation / Micro-Nano / Photonics | E98: Master indifférencié (recherche et professionnel) Sciences, Technologies, Santé mention Nanosciences et nanotechnologies parcours Nanophysics - Quantum Physics Parcours International | F98: Science, Technology, Health (STS) – major: Nanosciences & Nanotechnologies – track: Nanophysics - Quantum Physics – track: International | G98: Master indifférencié (recherche et professionnel) | H98: UFR de Physique, ingénierie, terre, environnement, mécanique | I98: Université de Grenoble Alpes | J98: Site de Grenoble - Campus de Saint Martin d'Hères | L98: Public university | M98: English | N98: Taught in English | O98: Bac +4 / Bac +5 | P98: Eligible on level (4-yr BS ≈ Bac+4) | Q98: 1/2 | S98: 3950 | T98: 255 | U98: 2 | V98: =IF(S98="","",S98*U98) | W98: Not in catalogue. Public national master → 2026-27 differentiated fee €3,950; exemption to ~€254-255 depends on university quota (25% cap in 2027-28). | X98: Medium | AA98: UGA (incl. Grenoble INP masters): 2026-27 broad exemptions on request (pay national €254). From 2027-28 the decree caps apply; exemptions based on resources. | AB98: https://www.univ-grenoble-alpes.fr/actualites/a-la-une/actualites-universite/etudiants-internationaux-ce-que-change-le-nouveau-decret-sur-les-droits-d-inscription-a-l-uga-1775870.kjsp | AC98: Open | AD98: 2026-10-01 | AE98: 2027-03-15 | AF98: No | AG98: https://formations.univ-grenoble-alpes.fr/fr/catalogue-2021/master-XB/master-nanosciences-et-nanotechnologies-IAQK78RT/parcours-nanophysics-quantum-physics-1re-annee-KLQGAWF7.html | AH98: "The program is open to students who will have completed a Bachelor in physics, nanoscience, or physical-chemistry (with at least 180 ECTS) and containing general courses in physics, but also dedicated courses in quantum | AI98: Open in EEF
A99: 98 | B99: ★★★★☆ | C99: 4 – Strong fit (electronics/signal/robotics/IoT/sensors) | D99: Sensors / Instrumentation / Micro-Nano / Photonics | E99: Master indifférencié (recherche et professionnel) Sciences, Technologies, Santé mention Nanosciences et nanotechnologies parcours Physics of Complex Matter Parcours International | F99: Science, Technology, Health (STS) – major: Nanosciences & Nanotechnologies – track: Physics of Complex Matter – track: International | G99: Master indifférencié (recherche et professionnel) | H99: UFR de Physique, ingénierie, terre, environnement, mécanique | I99: Université de Grenoble Alpes | J99: Site de Grenoble - Campus de Saint Martin d'Hères | L99: Public university | M99: English | N99: Taught in English | O99: Bac +4 / Bac +5 | P99: Eligible on level (4-yr BS ≈ Bac+4) | Q99: 1/2 | S99: 3950 | T99: 255 | U99: 2 | V99: =IF(S99="","",S99*U99) | W99: Not in catalogue. Public national master → 2026-27 differentiated fee €3,950; exemption to ~€254-255 depends on university quota (25% cap in 2027-28). | X99: Medium | AA99: UGA (incl. Grenoble INP masters): 2026-27 broad exemptions on request (pay national €254). From 2027-28 the decree caps apply; exemptions based on resources. | AB99: https://www.univ-grenoble-alpes.fr/actualites/a-la-une/actualites-universite/etudiants-internationaux-ce-que-change-le-nouveau-decret-sur-les-droits-d-inscription-a-l-uga-1775870.kjsp | AC99: Open | AD99: 2026-10-01 | AE99: 2027-03-15 | AF99: No | AG99: https://formations.univ-grenoble-alpes.fr/fr/catalogue-2021/master-XB/master-nanosciences-et-nanotechnologies-IAQK78RT/parcours-physics-of-complex-matter-parcours-international-1re-annee-IATOD7FB.html | AH99: M1 : Students who will have completed at a good level by the end of the current academic year a bachelor program (e.g. at least 180 ECTS) in Physics, Physical chemistry, Engineering (Chemical, mechanical, or nanotechnolo | AI99: Open in EEF
A100: 99 | B100: ★★★★☆ | C100: 4 – Strong fit (electronics/signal/robotics/IoT/sensors) | D100: Sensors / Instrumentation / Micro-Nano / Photonics | E100: Master indifférencié (recherche et professionnel) Sciences, technologies, santé mention nanosciences, nanotechnologies parcours NanoMédecine Biologie Structurale | F100: Science, Technology, Health (STS) – major: Nanosciences, Nanotechnologies – track: NanoMédecine Biology Structural | G100: Master indifférencié (recherche et professionnel) | H100: Ecole nationale supérieure de physique, électronique, matériaux - Grenoble INP | I100: Grenoble INP | J100: Site de Grenoble | L100: Public school / institute | M100: English | N100: General | O100: Bac +4 / Bac +5 | P100: Eligible on level (4-yr BS ≈ Bac+4) | Q100: 1/2 | S100: 3950 | T100: 255 | U100: 2 | V100: =IF(S100="","",S100*U100) | W100: Not in catalogue. Public national master → 2026-27 differentiated fee €3,950; exemption to ~€254-255 depends on university quota (25% cap in 2027-28). | X100: Medium | Z100: As a reference, for the 2026–2027 academic year, these fees amounted to €3,950 per year, subject to change based on the pol … To cover living expenses (housing, food, other essentials), a minimum monthly budget of €650 | AA100: UGA (incl. Grenoble INP masters): 2026-27 broad exemptions on request (pay national €254). From 2027-28 the decree caps apply; exemptions based on resources. | AB100: https://www.univ-grenoble-alpes.fr/actualites/a-la-une/actualites-universite/etudiants-internationaux-ce-que-change-le-nouveau-decret-sur-les-droits-d-inscription-a-l-uga-1775870.kjsp | AC100: Open | AD100: 2026-10-01 | AE100: 2027-03-15 | AF100: Yes | AG100: https://phelma.grenoble-inp.fr/fr/formation/master-nanosciences-and-nanotechnologies-parcours-nanomedicine-and-structural-biology#page-presentation | AH100: ***PAGE EN COURS D'ACTUALISATION POUR LA RENTREE UNIVERSITAIRE 2027- 2028 **** (PAGE CURRENTLY BEING UPDATED FOR THE 2027–2028 ACADEMIC YEAR) Avant de candidater, il est important de vérifier le coût de la formation et l | AI100: Open in EEF
...

Sheet Summary
A1: Field | B1: Programs | C1: Eligible on level | D1: Taught in English (incl. FR&EN) | E1: Est. fee ≤ €4,000 | F1: Est. fee > €6,000 | G1: Cheapest est. fee (€, excl. apprenticeship €0)
A2: AI / Data science | B2: =COUNTIF('All Programs'!$D$2:$D$1000,A2) | C2: =COUNTIFS('All Programs'!$D$2:$D$1000,A2,'All Programs'!$P$2:$P$1000,"Eligible*") | D2: =COUNTIFS('All Programs'!$D$2:$D$1000,A2,'All Programs'!$M$2:$M$1000,"*English*") | E2: =COUNTIFS('All Programs'!$D$2:$D$1000,A2,'All Programs'!$S$2:$S$1000,"<=4000") | F2: =COUNTIFS('All Programs'!$D$2:$D$1000,A2,'All Programs'!$S$2:$S$1000,">6000") | G2: =_xlfn.MINIFS('All Programs'!$S$2:$S$1000,'All Programs'!$D$2:$D$1000,A2,'All Programs'!$S$2:$S$1000,">0")
A3: Bioinformatics | B3: =COUNTIF('All Programs'!$D$2:$D$1000,A3) | C3: =COUNTIFS('All Programs'!$D$2:$D$1000,A3,'All Programs'!$P$2:$P$1000,"Eligible*") | D3: =COUNTIFS('All Programs'!$D$2:$D$1000,A3,'All Programs'!$M$2:$M$1000,"*English*") | E3: =COUNTIFS('All Programs'!$D$2:$D$1000,A3,'All Programs'!$S$2:$S$1000,"<=4000") | F3: =COUNTIFS('All Programs'!$D$2:$D$1000,A3,'All Programs'!$S$2:$S$1000,">6000") | G3: =_xlfn.MINIFS('All Programs'!$S$2:$S$1000,'All Programs'!$D$2:$D$1000,A3,'All Programs'!$S$2:$S$1000,">0")
A4: Biomedical / Health tech | B4: =COUNTIF('All Programs'!$D$2:$D$1000,A4) | C4: =COUNTIFS('All Programs'!$D$2:$D$1000,A4,'All Programs'!$P$2:$P$1000,"Eligible*") | D4: =COUNTIFS('All Programs'!$D$2:$D$1000,A4,'All Programs'!$M$2:$M$1000,"*English*") | E4: =COUNTIFS('All Programs'!$D$2:$D$1000,A4,'All Programs'!$S$2:$S$1000,"<=4000") | F4: =COUNTIFS('All Programs'!$D$2:$D$1000,A4,'All Programs'!$S$2:$S$1000,">6000") | G4: =_xlfn.MINIFS('All Programs'!$S$2:$S$1000,'All Programs'!$D$2:$D$1000,A4,'All Programs'!$S$2:$S$1000,">0")
A5: Computer science / Software | B5: =COUNTIF('All Programs'!$D$2:$D$1000,A5) | C5: =COUNTIFS('All Programs'!$D$2:$D$1000,A5,'All Programs'!$P$2:$P$1000,"Eligible*") | D5: =COUNTIFS('All Programs'!$D$2:$D$1000,A5,'All Programs'!$M$2:$M$1000,"*English*") | E5: =COUNTIFS('All Programs'!$D$2:$D$1000,A5,'All Programs'!$S$2:$S$1000,"<=4000") | F5: =COUNTIFS('All Programs'!$D$2:$D$1000,A5,'All Programs'!$S$2:$S$1000,">6000") | G5: =_xlfn.MINIFS('All Programs'!$S$2:$S$1000,'All Programs'!$D$2:$D$1000,A5,'All Programs'!$S$2:$S$1000,">0")
A6: Cybersecurity | B6: =COUNTIF('All Programs'!$D$2:$D$1000,A6) | C6: =COUNTIFS('All Programs'!$D$2:$D$1000,A6,'All Programs'!$P$2:$P$1000,"Eligible*") | D6: =COUNTIFS('All Programs'!$D$2:$D$1000,A6,'All Programs'!$M$2:$M$1000,"*English*") | E6: =COUNTIFS('All Programs'!$D$2:$D$1000,A6,'All Programs'!$S$2:$S$1000,"<=4000") | F6: =COUNTIFS('All Programs'!$D$2:$D$1000,A6,'All Programs'!$S$2:$S$1000,">6000") | G6: =_xlfn.MINIFS('All Programs'!$S$2:$S$1000,'All Programs'!$D$2:$D$1000,A6,'All Programs'!$S$2:$S$1000,">0")
A7: Electrical energy | B7: =COUNTIF('All Programs'!$D$2:$D$1000,A7) | C7: =COUNTIFS('All Programs'!$D$2:$D$1000,A7,'All Programs'!$P$2:$P$1000,"Eligible*") | D7: =COUNTIFS('All Programs'!$D$2:$D$1000,A7,'All Programs'!$M$2:$M$1000,"*English*") | E7: =COUNTIFS('All Programs'!$D$2:$D$1000,A7,'All Programs'!$S$2:$S$1000,"<=4000") | F7: =COUNTIFS('All Programs'!$D$2:$D$1000,A7,'All Programs'!$S$2:$S$1000,">6000") | G7: =_xlfn.MINIFS('All Programs'!$S$2:$S$1000,'All Programs'!$D$2:$D$1000,A7,'All Programs'!$S$2:$S$1000,">0")
A8: Embedded systems / Electronics | B8: =COUNTIF('All Programs'!$D$2:$D$1000,A8) | C8: =COUNTIFS('All Programs'!$D$2:$D$1000,A8,'All Programs'!$P$2:$P$1000,"Eligible*") | D8: =COUNTIFS('All Programs'!$D$2:$D$1000,A8,'All Programs'!$M$2:$M$1000,"*English*") | E8: =COUNTIFS('All Programs'!$D$2:$D$1000,A8,'All Programs'!$S$2:$S$1000,"<=4000") | F8: =COUNTIFS('All Programs'!$D$2:$D$1000,A8,'All Programs'!$S$2:$S$1000,">6000") | G8: =_xlfn.MINIFS('All Programs'!$S$2:$S$1000,'All Programs'!$D$2:$D$1000,A8,'All Programs'!$S$2:$S$1000,">0")
A9: IoT / Telecom / Networks | B9: =COUNTIF('All Programs'!$D$2:$D$1000,A9) | C9: =COUNTIFS('All Programs'!$D$2:$D$1000,A9,'All Programs'!$P$2:$P$1000,"Eligible*") | D9: =COUNTIFS('All Programs'!$D$2:$D$1000,A9,'All Programs'!$M$2:$M$1000,"*English*") | E9: =COUNTIFS('All Programs'!$D$2:$D$1000,A9,'All Programs'!$S$2:$S$1000,"<=4000") | F9: =COUNTIFS('All Programs'!$D$2:$D$1000,A9,'All Programs'!$S$2:$S$1000,">6000") | G9: =_xlfn.MINIFS('All Programs'!$S$2:$S$1000,'All Programs'!$D$2:$D$1000,A9,'All Programs'!$S$2:$S$1000,">0")
A10: Neuroscience / Neuro-engineering | B10: =COUNTIF('All Programs'!$D$2:$D$1000,A10) | C10: =COUNTIFS('All Programs'!$D$2:$D$1000,A10,'All Programs'!$P$2:$P$1000,"Eligible*") | D10: =COUNTIFS('All Programs'!$D$2:$D$1000,A10,'All Programs'!$M$2:$M$1000,"*English*") | E10: =COUNTIFS('All Programs'!$D$2:$D$1000,A10,'All Programs'!$S$2:$S$1000,"<=4000") | F10: =COUNTIFS('All Programs'!$D$2:$D$1000,A10,'All Programs'!$S$2:$S$1000,">6000") | G10: =_xlfn.MINIFS('All Programs'!$S$2:$S$1000,'All Programs'!$D$2:$D$1000,A10,'All Programs'!$S$2:$S$1000,">0")
A11: Other engineering / maths | B11: =COUNTIF('All Programs'!$D$2:$D$1000,A11) | C11: =COUNTIFS('All Programs'!$D$2:$D$1000,A11,'All Programs'!$P$2:$P$1000,"Eligible*") | D11: =COUNTIFS('All Programs'!$D$2:$D$1000,A11,'All Programs'!$M$2:$M$1000,"*English*") | E11: =COUNTIFS('All Programs'!$D$2:$D$1000,A11,'All Programs'!$S$2:$S$1000,"<=4000") | F11: =COUNTIFS('All Programs'!$D$2:$D$1000,A11,'All Programs'!$S$2:$S$1000,">6000") | G11: =_xlfn.MINIFS('All Programs'!$S$2:$S$1000,'All Programs'!$D$2:$D$1000,A11,'All Programs'!$S$2:$S$1000,">0")
A12: Robotics / Automation / Mechatronics | B12: =COUNTIF('All Programs'!$D$2:$D$1000,A12) | C12: =COUNTIFS('All Programs'!$D$2:$D$1000,A12,'All Programs'!$P$2:$P$1000,"Eligible*") | D12: =COUNTIFS('All Programs'!$D$2:$D$1000,A12,'All Programs'!$M$2:$M$1000,"*English*") | E12: =COUNTIFS('All Programs'!$D$2:$D$1000,A12,'All Programs'!$S$2:$S$1000,"<=4000") | F12: =COUNTIFS('All Programs'!$D$2:$D$1000,A12,'All Programs'!$S$2:$S$1000,">6000") | G12: =_xlfn.MINIFS('All Programs'!$S$2:$S$1000,'All Programs'!$D$2:$D$1000,A12,'All Programs'!$S$2:$S$1000,">0")
A13: Sensors / Instrumentation / Micro-Nano / Photonics | B13: =COUNTIF('All Programs'!$D$2:$D$1000,A13) | C13: =COUNTIFS('All Programs'!$D$2:$D$1000,A13,'All Programs'!$P$2:$P$1000,"Eligible*") | D13: =COUNTIFS('All Programs'!$D$2:$D$1000,A13,'All Programs'!$M$2:$M$1000,"*English*") | E13: =COUNTIFS('All Programs'!$D$2:$D$1000,A13,'All Programs'!$S$2:$S$1000,"<=4000") | F13: =COUNTIFS('All Programs'!$D$2:$D$1000,A13,'All Programs'!$S$2:$S$1000,">6000") | G13: =_xlfn.MINIFS('All Programs'!$S$2:$S$1000,'All Programs'!$D$2:$D$1000,A13,'All Programs'!$S$2:$S$1000,">0")
A14: Signal / Image / Vision | B14: =COUNTIF('All Programs'!$D$2:$D$1000,A14) | C14: =COUNTIFS('All Programs'!$D$2:$D$1000,A14,'All Programs'!$P$2:$P$1000,"Eligible*") | D14: =COUNTIFS('All Programs'!$D$2:$D$1000,A14,'All Programs'!$M$2:$M$1000,"*English*") | E14: =COUNTIFS('All Programs'!$D$2:$D$1000,A14,'All Programs'!$S$2:$S$1000,"<=4000") | F14: =COUNTIFS('All Programs'!$D$2:$D$1000,A14,'All Programs'!$S$2:$S$1000,">6000") | G14: =_xlfn.MINIFS('All Programs'!$S$2:$S$1000,'All Programs'!$D$2:$D$1000,A14,'All Programs'!$S$2:$S$1000,">0")
A15: TOTAL | B15: =SUM(B2:B14) | C15: =SUM(C2:C14) | D15: =SUM(D2:D14) | E15: =SUM(E2:E14) | F15: =SUM(F2:F14)

Sheet English-taught
A1: # | B1: Relevance | C1: Relevance note | D1: Field (category) | E1: Program title (as in Études en France) | F1: Approx. English title (auto-translated) | G1: Degree type | H1: Institution / faculty | I1: University / group | J1: Campus / site | K1: City / postcode | L1: Institution type | M1: Teaching language | N1: Catalogue | O1: Entry level required | P1: Your eligibility (4-yr BS, 3 yrs exp.) | Q1: Entry year(s) | R1: Duration (months, per catalogue) | S1: Est. tuition / year non-EU (€) | T1: Lowest possible with exemption (€) | U1: Years to finish (est.) | V1: Est. total tuition (€) | W1: Fee basis & source | X1: Fee confidence | Y1: Fees found in catalogue (€) | Z1: Fee note from catalogue text | AA1: University exemption policy 2026-27 | AB1: Policy source | AC1: EEF status | AD1: Apply from | AE1: Apply until (EEF) | AF1: Extra school application required? | AG1: Program website | AH1: Requirements (excerpt) | AI1: Catalogue link
A2: 1 | B2: ★★★★★ | C2: 5 – Core fit (embedded/biomedical/health tech) | D2: IoT / Telecom / Networks | E2: Master indifférencié (recherche et professionnel) Master Computer Networks and IoT Systems | F2: Master Computer Networks and IoT Systems | G2: Master indifférencié (recherche et professionnel) | H2: Conservatoire national des arts et métiers - CNAM | J2: Cnam Etablissement Public - EPN5 Computer Science | K2: 75003 Paris | L2: Public school / institute | M2: English | N2: Taught in English | O2: Bac +4 / Bac +5 | P2: Eligible on level (4-yr BS ≈ Bac+4) | Q2: 1/2 | R2: 12 | S2: 3950 | T2: 255 | U2: 2 | V2: =IF(S2="","",S2*U2) | W2: Catalogue: €3,770. = national differentiated master fee (2026-27: €3,950). Exemption to ~€255 possible (university quota). | X2: High | Y2: 3770 | AC2: Open | AD2: 2026-10-01 | AE2: 2027-03-15 | AF2: Yes | AG2: https://master.roc.cnam.fr | AH2: International, European and French students willing to pursue a master degree in English, and possessing a Bachelor-level degree in one of these fields: Computer Science, Electronics, Computer Engineering, Electrical Eng | AI2: Open in EEF
A3: 2 | B3: ★★★★★ | C3: 5 – Core fit (embedded/biomedical/health tech) | D3: Biomedical / Health tech | E3: Master indifférencié (recherche et professionnel) mention Biomedical Engineering (BME) | F3: major: Biomedical Engineering (BME) | G3: Master indifférencié (recherche et professionnel) | H3: UFR des Sciences pharmaceutiques et biologiques | I3: Université de Montpellier | J3: Site de Montpellier | K3: 34090 Montpellier | L3: Public university | M3: English | N3: Taught in English | O3: Bac +4 | P3: Eligible on level (4-yr BS ≈ Bac+4) | Q3: 1 | R3: 12 | S3: 3950 | T3: 255 | U3: 2 | V3: =IF(S3="","",S3*U3) | W3: Not in catalogue. Public national master → 2026-27 differentiated fee €3,950; exemption to ~€254-255 depends on university quota (25% cap in 2027-28). | X3: Medium | AA3: Montpellier 2026-27: new non-EU entrants pay the differentiated fee unless individual exemption (limited). | AB3: https://www.umontpellier.fr/en/international/etudier-a-letranger/etudiants-internationaux-annee-universitaire-2026-2027/ | AC3: Open | AD3: 2026-10-01 | AE3: 2027-03-15 | AF3: No | AG3: https://idil.edu.umontpellier.fr/master-idil/les-parcours/ | AH3: Conditions d’accès Diplôme de licence dans la discipline choisie IDIL Niveau d’anglais B2 minimum CV et lettre de motivation 2 lettres de soutien d’un chercheur et/ou professeur (recommandé, mais non obligatoire) Estimat | AI3: Open in EEF
A4: 3 | B4: ★★★★★ | C4: 5 – Core fit (embedded/biomedical/health tech) | D4: Embedded systems / Electronics | E4: Master indifférencié (recherche et professionnel) mention Electronique, énergies électriques et automatique* parcours Electronique, Outils Libres pour l'instrumentation et les Systèmes Embarqués (ELISE) * | F4: major: Electronics, Energies Electrical & Automation* – track: Electronics, Outils Libres for Instrumentation & the Embedded Systems (ELISE) * | G4: Master indifférencié (recherche et professionnel) | H4: UFR Sciences et Techniques | I4: Université Marie et Louis Pasteur | J4: Site de Besançon | K4: 25030 BESANCON CEDEX | L4: Public university | M4: English | N4: Taught in English | O4: Bac +4 | P4: Eligible on level (4-yr BS ≈ Bac+4) | Q4: 1 | S4: 3950 | T4: 255 | U4: 2 | V4: =IF(S4="","",S4*U4) | W4: Not in catalogue. Public national master → 2026-27 differentiated fee €3,950; exemption to ~€254-255 depends on university quota (25% cap in 2027-28). | X4: Medium | AA4: UMLP: individual exemption requests assessed on personal resources. | AB4: https://www.umlp.fr/sites/default/files/2026-07-02-page-droits-differencies-vf.pdf | AC4: Open | AD4: 2026-10-01 | AE4: 2027-03-15 | AF4: No | AG4: https://formations.univ-fcomte.fr/fr/formations/feuilleter-le-catalogue/master-lmd-XB/master-electronique-energie-electrique-automatique-M4QUAZ0D.html | AH4: C langage programming, digital electronics, microcontroller programming, analog electronics, instrumentation, Python programming, signal processing, mathematics (basic algebra and analysis), Linux operating system Langue | AI4: Open in EEF
A5: 4 | B5: ★★★★★ | C5: 5 – Core fit (embedded/biomedical/health tech) | D5: Biomedical / Health tech | E5: Master indifférencié (recherche et professionnel) Sciences, Technologies, Santé mention Biologie Santé parcours Bioingénierie Moléculaire et Cellulaire | F5: Science, Technology, Health (STS) – major: Biology-Health – track: Bioengineering Molecular & Cellular | G5: Master indifférencié (recherche et professionnel) | H5: UFR de Chimie et Biologie | I5: Université de Grenoble Alpes | J5: Site de Grenoble - Campus de Saint Martin d'Hères | L5: Public university | M5: English | N5: Taught in English | O5: Bac +4 | P5: Eligible on level (4-yr BS ≈ Bac+4) | Q5: 1 | S5: 3950 | T5: 255 | U5: 2 | V5: =IF(S5="","",S5*U5) | W5: Not in catalogue. Public national master → 2026-27 differentiated fee €3,950; exemption to ~€254-255 depends on university quota (25% cap in 2027-28). | X5: Medium | AA5: UGA (incl. Grenoble INP masters): 2026-27 broad exemptions on request (pay national €254). From 2027-28 the decree caps apply; exemptions based on resources. | AB5: https://www.univ-grenoble-alpes.fr/actualites/a-la-une/actualites-universite/etudiants-internationaux-ce-que-change-le-nouveau-decret-sur-les-droits-d-inscription-a-l-uga-1775870.kjsp | AC5: Open | AD5: 2026-10-01 | AE5: 2027-03-15 | AF5: No | AG5: https://formations.univ-grenoble-alpes.fr/fr/offre-de-formation/master-XB/master-biologie-sante-IAQKB0GE/parcours-molecular-and-cellular-biology-1re-annee-IK43J2QV.html | AH5: The "Bioingénierie Moléculaire et Cellulaire" M1 program is open to students having completed a bachelor’s degree in Sciences or are enrolled in the ﬁnal semester of a bachelor’s program in Sciences with a solid backgrou | AI5: Open in EEF
A6: 5 | B6: ★★★★★ | C6: 5 – Core fit (embedded/biomedical/health tech) | D6: Biomedical / Health tech | E6: Master indifférencié (recherche et professionnel) Sciences, Technologies, Santé mention Ingénierie de la santé parcours Bio Health Engineering | F6: Science, Technology, Health (STS) – major: Health Engineering – track: Bio Health Engineering | G6: Master indifférencié (recherche et professionnel) | H6: UFR Médecine - Pharmacie | I6: Université de Grenoble Alpes | J6: Site de Grenoble - Campus de La Merci - La Tronche | L6: Public university | M6: English | N6: Taught in English | O6: Bac +4 / Bac +5 | P6: Eligible on level (4-yr BS ≈ Bac+4) | Q6: 1/2 | S6: 3950 | T6: 255 | U6: 2 | V6: =IF(S6="","",S6*U6) | W6: Not in catalogue. Public national master → 2026-27 differentiated fee €3,950; exemption to ~€254-255 depends on university quota (25% cap in 2027-28). | X6: Medium | AA6: UGA (incl. Grenoble INP masters): 2026-27 broad exemptions on request (pay national €254). From 2027-28 the decree caps apply; exemptions based on resources. | AB6: https://www.univ-grenoble-alpes.fr/actualites/a-la-une/actualites-universite/etudiants-internationaux-ce-que-change-le-nouveau-decret-sur-les-droits-d-inscription-a-l-uga-1775870.kjsp | AC6: Open | AD6: 2026-10-01 | AE6: 2027-03-15 | AF6: No | AG6: https://formations.univ-grenoble-alpes.fr/fr/catalogue-2021/master-XB/master-ingenierie-de-la-sante-IAQKSXOB.html | AH6: Requirement M1: - Strong theoritical and practical skills in biology or biochemistry or pharmaceutical sciences or biotechnologies. - B2 level in english mandatory. Requirement M2: - Strong theoritical and practical skil | AI6: Open in EEF
A7: 6 | B7: ★★★★★ | C7: 5 – Core fit (embedded/biomedical/health tech) | D7: Biomedical / Health tech | E7: Master indifférencié (recherche et professionnel) Sciences, technologies, santé mention sciences du vivant parcours Biomedical and Computational Sciences in Ageing (imAGEin) | F7: Science, Technology, Health (STS) – major: Sciences of Life – track: Biomedical and Computational Sciences in Ageing (imAGEin) | G7: Master indifférencié (recherche et professionnel) | H7: Sciences | I7: Université Côte d'Azur | J7: Site de Nice | L7: Public university | M7: English | N7: General | O7: Bac +3 | P7: Eligible on level (4-yr BS ≈ Bac+4) | Q7: 1 | S7: 3950 | T7: 255 | U7: 2 | V7: =IF(S7="","",S7*U7) | W7: Not in catalogue. Public national master → 2026-27 differentiated fee €3,950; exemption to ~€254-255 depends on university quota (25% cap in 2027-28). | X7: Medium | AC7: Open | AD7: 2026-10-01 | AE7: 2027-03-15 | AF7: Yes | AG7: https://life.univ-cotedazur.fr/international/imagein | AH7: Consulter le site web | AI7: Open in EEF
A8: 7 | B8: ★★★★★ | C8: 5 – Core fit (embedded/biomedical/health tech) | D8: IoT / Telecom / Networks | E8: Master Sciences, technologies, santé mention informatique parcours Internet of Things | F8: Master Science, Technology, Health (STS) – major: Computer Science – track: Internet of Things | G8: Master indifférencié (recherche et professionnel) | H8: UFR Sciences, Techniques et Gestion de l'Industrie | I8: Université Marie et Louis Pasteur | J8: Site de Montbéliard | K8: 25211 MONTBELIARD CEDEX | L8: Public university | M8: English | N8: General | O8: Bac +4 / Bac +5 | P8: Eligible on level (4-yr BS ≈ Bac+4) | Q8: 1/2 | R8: 12 | S8: 3950 | T8: 255 | U8: 2 | V8: =IF(S8="","",S8*U8) | W8: Not in catalogue. Public national master → 2026-27 differentiated fee €3,950; exemption to ~€254-255 depends on university quota (25% cap in 2027-28). | X8: Medium | Z8: (Pour information, le montant de la CVEC, pour la rentrée 2026-2027, était de 105€) … (Pour information, le montant de la CVEC, pour la rentrée 2025-2026, était de 105€) | AA8: UMLP: individual exemption requests assessed on personal resources. | AB8: https://www.umlp.fr/sites/default/files/2026-07-02-page-droits-differencies-vf.pdf | AC8: Open | AD8: 2026-10-01 | AE8: 2027-03-15 | AF8: No | AG8: https://stgi.umlp.fr/ | AH8: Le Master Internet of Things (IOT) est un Master en Informatique spécialisé dans le développement des objets communiquants. Il est attendu des candidats en M1 : Licence Informatique avec de bonnes connaissances en algori | AI8: Open in EEF
A9: 8 | B9: ★★★★★ | C9: 5 – Core fit (embedded/biomedical/health tech) | D9: Biomedical / Health tech | E9: Master indifférencié (recherche et professionnel) Sciences, technologies, santé mention Biotechnologies parcours Biomédicaments : conception et production | F9: Science, Technology, Health (STS) – major: Biotechnologies – track: Biodrugs : Design & Production | G9: Master indifférencié (recherche et professionnel) | H9: Faculté de pharmacie | I9: Université de Strasbourg | J9: Site de Illkirch-Graffenstaden | L9: Public university | M9: French & English | N9: General | O9: Bac +4 | P9: Eligible on level (4-yr BS ≈ Bac+4) | Q9: 1 | S9: 3950 | T9: 255 | U9: 2 | V9: =IF(S9="","",S9*U9) | W9: Catalogue: €3,950. = national differentiated master fee (2026-27: €3,950). Exemption to ~€255 possible (university quota). | X9: High | Y9: 3950 | AA9: Unistra: master entrants who did not do their licence at Unistra pay the differentiated fee (€3,950). | AB9: https://www.unistra.fr/fr/node/8168 | AC9: Open | AD9: 2026-10-01 | AE9: 2027-03-15 | AF9: No | AG9: https://pharmacie.unistra.fr | AH9: Entrée en M1 avoir effectué un curus en : - biologie cellulaire et moléculaire, biochimie, - avoir des bases en chimie Entrée en M2 avoir effectué un cursus en - biologie moléculaire et cellulaire avancée, - avoir des ba | AI9: Open in EEF
A10: 9 | B10: ★★★★★ | C10: 5 – Core fit (embedded/biomedical/health tech) | D10: Biomedical / Health tech | E10: Master indifférencié (recherche et professionnel) Sciences, technologies, santé mention sciences du vivant parcours Bioinformatique et Bioimagerie Structurale | F10: Science, Technology, Health (STS) – major: Sciences of Life – track: Bioinformatics & Bioimagerie Structural | G10: Master indifférencié (recherche et professionnel) | H10: Faculté des sciences de la vie | I10: Université de Strasbourg | J10: Site de Strasbourg | K10: 67000 Strasbourg | L10: Public university | M10: French & English | N10: General | O10: Bac +4 / Bac +5 | P10: Eligible on level (4-yr BS ≈ Bac+4) | Q10: 1/2 | S10: 3950 | T10: 255 | U10: 2 | V10: =IF(S10="","",S10*U10) | W10: Catalogue: €3,950. = national differentiated master fee (2026-27: €3,950). Exemption to ~€255 possible (university quota). | X10: High | Y10: 3950 | AA10: Unistra: master entrants who did not do their licence at Unistra pay the differentiated fee (€3,950). | AB10: https://www.unistra.fr/fr/node/8168 | AC10: Open | AD10: 2026-10-01 | AE10: 2027-03-15 | AF10: No | AG10: http://sciencesvie.unistra.fr/ | AH10: M1 : Cette formation s’adresse aux étudiants désirant acquérir une formation pluridisciplinaire alliant une culture biologique à une maîtrise ou une expertise de plusieurs outils et méthodes informatiques, bioinformatiqu | AI10: Open in EEF
A11: 10 | B11: ★★★★★ | C11: 5 – Core fit (embedded/biomedical/health tech) | D11: IoT / Telecom / Networks | E11: Master indifférencié (recherche et professionnel) Sciences, technologies, santé mention Traitement du signal et des images parcours EUR Smart IoT | F11: Science, Technology, Health (STS) – major: Signal & Image Processing – track: EUR Smart IoT | G11: Master indifférencié (recherche et professionnel) | H11: UFR de sciences fondamentales et appliquées - Université de Poitiers | I11: Université de Poitiers | J11: Site de Poitiers | L11: Public university | M11: French & English | N11: Taught in English | O11: Bac +4 / Bac +5 | P11: Eligible on level (4-yr BS ≈ Bac+4) | Q11: 1/2 | S11: 3950 | T11: 255 | U11: 2 | V11: =IF(S11="","",S11*U11) | W11: Catalogue: €3,950. = national differentiated master fee (2026-27: €3,950). Exemption to ~€255 possible (university quota). | X11: High | Y11: 3950 | AC11: Open | AD11: 2026-10-01 | AE11: 2027-03-15 | AF11: No | AG11: https://www.unilim.fr/gradschool-ceramics-ict/formation/smart-iot/ | AH11: Year 1 The admissions committee will focus in particular on the candidate’s grades in subjects related to the intended field of study and on the candidate’s ability to articulate their motivations and career goals. Minim | AI11: Open in EEF
A12: 11 | B12: ★★★★★ | C12: 5 – Core fit (embedded/biomedical/health tech) | D12: Biomedical / Health tech | E12: Master Sciences, technologies, santé, mention Ingéniérie de la santé parcours Biomatériaux et bio ingénierie pour la santé | F12: Master Science, Technology, Health (STS), – major: Engineering of the Health – track: Biomaterials & bio Engineering for Health | G12: Master indifférencié (recherche et professionnel) | H12: Faculté de chirurgie dentaire | I12: Université de Strasbourg | J12: Site de Strasbourg | L12: Public university | M12: French & English | N12: General | O12: Bac +4 / Bac +5 | P12: Eligible on level (4-yr BS ≈ Bac+4) | Q12: 1/2 | S12: 3950 | T12: 255 | U12: 2 | V12: =IF(S12="","",S12*U12) | W12: Catalogue: €3,950. = national differentiated master fee (2026-27: €3,950). Exemption to ~€255 possible (university quota). | X12: High | Y12: 3950 | AA12: Unistra: master entrants who did not do their licence at Unistra pay the differentiated fee (€3,950). | AB12: https://www.unistra.fr/fr/node/8168 | AC12: Open | AD12: 2026-10-01 | AE12: 2027-03-15 | AF12: No | AG12: https://chirurgie-dentaire.unistra.fr/ | AH12: Formation à enseignement mixte : français/anglais. Niveau de langue (anglais B1, français C1) | AI12: Open in EEF
A13: 12 | B13: ★★★★★ | C13: 5 – Core fit (embedded/biomedical/health tech) | D13: Biomedical / Health tech | E13: Master Sciences, technologies, santé, mention Ingénierie de la santé parcours Jumeaux numériques pour la santé | F13: Master Science, Technology, Health (STS), – major: Health Engineering – track: Jumeaux Digital for the Health | G13: Master indifférencié (recherche et professionnel) | H13: Université de technologie de Compiègne | J13: Site de Compiègne | L13: Public university | M13: French & English | N13: General | O13: Bac +4 / Bac +5 | P13: Eligible on level (4-yr BS ≈ Bac+4) | Q13: 1/2 | S13: 3950 | T13: 255 | U13: 2 | V13: =IF(S13="","",S13*U13) | W13: Catalogue: €3,950. = national differentiated master fee (2026-27: €3,950). Exemption to ~€255 possible (university quota). | X13: High | Y13: 3950 | AC13: Open | AD13: 2026-10-01 | AE13: 2027-03-15 | AF13: No | AH13: Parcours DTH Mentions de licences conseillées : Informatique Mathématiques Physique Mécanique Sciences et technologies Sciences pour l'ingénieur Attendus : Avoir des compétences en mathématiques appliquées, en mécanique | AI13: Open in EEF
A14: 13 | B14: ★★★★★ | C14: 5 – Core fit (embedded/biomedical/health tech) | D14: Biomedical / Health tech | E14: Master indifférencié (recherche et professionnel) Sciences, technologies, santé mention Electronique, énergie électrique, automatique parcours Ingénierie pour la santé | F14: Science, Technology, Health (STS) – major: Electronics, Electrical Energy & Automation (EEA) – track: Engineering for Health | G14: Master indifférencié (recherche et professionnel) | H14: Sciences et Ingénierie | I14: Sorbonne Université | J14: Site de Paris | L14: Public university | M14: French & English | N14: General | O14: Bac +4 / Bac +5 | P14: Eligible on level (4-yr BS ≈ Bac+4) | Q14: 1/2 | S14: 3950 | T14: 255 | U14: 2 | V14: =IF(S14="","",S14*U14) | W14: Not in catalogue. Public national master → 2026-27 differentiated fee €3,950; exemption to ~€254-255 depends on university quota (25% cap in 2027-28). | X14: Medium | AA14: Board vote 7 Jul 2026: Sorbonne Université says it can exempt all eligible non-EU applicants (pay same as EU, ~€254) for 2026-27. | AB14: https://www.sorbonne-universite.fr/actualites/le-conseil-dadministration-de-sorbonne-universite-vote-lunanimite-le-7-juillet-2026-sa | AC14: Open | AD14: 2026-10-01 | AE14: 2027-03-15 | AF14: No | AG14: https://masters-sdi.sorbonne-universite.fr/electronique-energie-electrique-automatique | AI14: Open in EEF
A15: 14 | B15: ★★★★★ | C15: 5 – Core fit (embedded/biomedical/health tech) | D15: Embedded systems / Electronics | E15: Master indifférencié (recherche et professionnel) Sciences, technologies, santé mention Electronique, énergie électrique, automatique parcours Microélectronique Intégration des Systèmes Temps Réels et Embarqués (EEA MISTRE) | F15: Science, Technology, Health (STS) – major: Electronics, Electrical Energy & Automation (EEA) – track: Microelectronics Integration of Systems Real-Times & Embedded (EEA MISTRE) | G15: Master indifférencié (recherche et professionnel) | H15: UFR de Physique, ingénierie, terre, environnement, mécanique | I15: Université de Grenoble Alpes | J15: Site de Grenoble - Polygone scientifique - GreEn-ER | L15: Public university | M15: French & English | N15: General | O15: Bac +4 / Bac +5 | P15: Eligible on level (4-yr BS ≈ Bac+4) | Q15: 1/2 | S15: 3950 | T15: 255 | U15: 2 | V15: =IF(S15="","",S15*U15) | W15: Not in catalogue. Public national master → 2026-27 differentiated fee €3,950; exemption to ~€254-255 depends on university quota (25% cap in 2027-28). | X15: Medium | AA15: UGA (incl. Grenoble INP masters): 2026-27 broad exemptions on request (pay national €254). From 2027-28 the decree caps apply; exemptions based on resources. | AB15: https://www.univ-grenoble-alpes.fr/actualites/a-la-une/actualites-universite/etudiants-internationaux-ce-que-change-le-nouveau-decret-sur-les-droits-d-inscription-a-l-uga-1775870.kjsp | AC15: Open | AD15: 2026-10-01 | AE15: 2027-03-15 | AF15: No | AG15: https://formations.univ-grenoble-alpes.fr/fr/catalogue-2021/master-XB/master-electronique-energie-electrique-automatique-IFZ3DRB9/parcours-microelectronique-integration-des-systemes-temps-reels-embarques-mistre-1re-et-2e-annees-IFZ5TP7C.html | AH15: Master 1 : - Les candidats titulaires d'un diplôme de BAC+5 au moment de la candidature ne seront pas admis en master 1. Seules les candidatures de BAC+3 ou BAC+4 seront considérées. - Prérequis : Electronique, automatiq | AI15: Open in EEF
A16: 15 | B16: ★★★★★ | C16: 5 – Core fit (embedded/biomedical/health tech) | D16: Embedded systems / Electronics | E16: Master indifférencié (recherche et professionnel) Sciences, technologies, santé mention Electronique, énergie électrique, automatique parcours Systèmes Communicants | F16: Science, Technology, Health (STS) – major: Electronics, Electrical Energy & Automation (EEA) – track: Systems Communicating | G16: Master indifférencié (recherche et professionnel) | H16: Sciences et Ingénierie | I16: Sorbonne Université | J16: Site de Paris | L16: Public university | M16: French & English | N16: General | O16: Bac +4 / Bac +5 | P16: Eligible on level (4-yr BS ≈ Bac+4) | Q16: 1/2 | S16: 3950 | T16: 255 | U16: 2 | V16: =IF(S16="","",S16*U16) | W16: Not in catalogue. Public national master → 2026-27 differentiated fee €3,950; exemption to ~€254-255 depends on university quota (25% cap in 2027-28). | X16: Medium | AA16: Board vote 7 Jul 2026: Sorbonne Université says it can exempt all eligible non-EU applicants (pay same as EU, ~€254) for 2026-27. | AB16: https://www.sorbonne-universite.fr/actualites/le-conseil-dadministration-de-sorbonne-universite-vote-lunanimite-le-7-juillet-2026-sa | AC16: Open | AD16: 2026-10-01 | AE16: 2027-03-15 | AF16: No | AG16: https://masters-sdi.sorbonne-universite.fr/electronique-energie-electrique-automatique | AI16: Open in EEF
A17: 16 | B17: ★★★★★ | C17: 5 – Core fit (embedded/biomedical/health tech) | D17: Biomedical / Health tech | E17: Master Sciences de la santé mention Ingénierie de la santé | F17: Master Sciences of the Health – major: Health Engineering | G17: Master indifférencié (recherche et professionnel) | H17: UFR des Sciences Fondamentales et Biomédicales | I17: Université Paris Cité | J17: Site de Paris | K17: 75006 Paris | L17: Public university | M17: French & English | N17: General | O17: Bac +4 | P17: Eligible on level (4-yr BS ≈ Bac+4) | Q17: 1 | S17: 3950 | T17: 255 | U17: 2 | V17: =IF(S17="","",S17*U17) | W17: Not in catalogue. Public national master → 2026-27 differentiated fee €3,950; exemption to ~€254-255 depends on university quota (25% cap in 2027-28). | X17: Medium | AA17: Paris Cité historically exempted non-EU master students (paid EU rate). 2026-27/2027-28 policy not yet published – confirm. | AB17: https://u-paris.fr/droits-dinscription-tarifs-exonerations/ | AC17: Open | AD17: 2026-10-01 | AE17: 2027-03-15 | AF17: Yes | AG17: https://odf.u-paris.fr/fr/offre-de-formation/master-XB/sciences-technologies-sante-STS/ingenierie-de-la-sante-K2NDJ7KW.html | AH17: All courses are taught in English, so candidates must demonstrate a perfect command of English (C1 level certificate required) with no French prerequisites for non-French speaking students. Candidates must: - excel in th | AI17: Open in EEF
A18: 17 | B18: ★★★★★ | C18: 5 – Core fit (embedded/biomedical/health tech) | D18: Cybersecurity | E18: Master of science Cyber-Physical Social Systems | F18: Master of science Cyber-Physical Social Systems | G18: Master of Science (MSc) | H18: Ecole nationale supérieure des mines de Saint-Etienne | J18: Site de Saint-Etienne | L18: Public school / institute | M18: English | N18: Taught in English | O18: Bac +4 | P18: Eligible on level (4-yr BS ≈ Bac+4) | Q18: 1 | R18: 24 | S18: 4150 | U18: 2 | V18: =IF(S18="","",S18*U18) | W18: Not in catalogue. Mastersportal lists €4,150/yr for Mines Saint-Étienne MSc (verify with school). | X18: Low | AC18: Open | AD18: 2026-10-01 | AE18: 2027-03-15 | AF18: Yes | AG18: https://www.mines-stetienne.fr/en/academic/msc-cyber-physical-social-systems-cps2/ | AH18: Applicants with at least a Bachelor degree level (180 ECTS) or M1 degree level (240 ECTS) in computer science or equivalent are invited to apply. A good command of English is mandatory. International students’ applicatio | AI18: Open in EEF
A19: 18 | B19: ★★★★★ | C19: 5 – Core fit (embedded/biomedical/health tech) | D19: Biomedical / Health tech | E19: Master BioMedical Engineering | F19: Master BioMedical Engineering | G19: Master indifférencié (recherche et professionnel) | H19: Institut Supérieur d'Ingénieurs de Franche-Comté | I19: Université Marie et Louis Pasteur | J19: Site de Besançon | L19: Public school / institute | M19: English | N19: General | O19: Bac +4 / Bac +5 | P19: Eligible on level (4-yr BS ≈ Bac+4) | Q19: 1/2 | S19: 5000 | U19: 2 | V19: =IF(S19="","",S19*U19) | W19: Catalogue fee €5,000/yr (entered by institution). | X19: High | Y19: 5000 | AA19: UMLP: individual exemption requests assessed on personal resources. | AB19: https://www.umlp.fr/sites/default/files/2026-07-02-page-droits-differencies-vf.pdf | AC19: Open | AD19: 2026-10-01 | AE19: 2027-03-15 | AF19: Yes | AG19: http://isifc.univ-fcomte.fr | AI19: Open in EEF
A20: 19 | B20: ★★★★★ | C20: 5 – Core fit (embedded/biomedical/health tech) | D20: Embedded systems / Electronics | E20: MSc. "Connected Embedded Intelligent Systems" | F20: MSc. "Connected Embedded Intelligent Systems" | G20: Mastère en sciences (MSc) | H20: Ecole supérieure d'ingénieurs en génie électrique | J20: Site de Saint-Etienne-du-Rouvray | L20: Private / EESPIG | M20: English | N20: General | O20: Bac +3 / Bac +4 | P20: Eligible on level (4-yr BS ≈ Bac+4) | Q20: 1/2 | S20: 6100 | U20: 2 | V20: =IF(S20="","",S20*U20) | W20: Catalogue fee €6,100/yr (entered by institution). | X20: High | Y20: 6100 | AC20: Open | AD20: 2026-10-01 | AE20: 2027-03-15 | AF20: Yes | AG20: http://www.esigelec.fr | AH20: Merci de contacter directement vidya.suresh@esigelec.fr | AI20: Open in EEF
A21: 20 | B21: ★★★★★ | C21: 5 – Core fit (embedded/biomedical/health tech) | D21: Embedded systems / Electronics | E21: Master indifférencié (recherche et professionnel) MSc in Information Technology (IT), track in Embedded AI (EMBAI) | F21: MSc in Information Technology (IT), track in Embedded AI (EMBAI) | G21: Master indifférencié (recherche et professionnel) | H21: IMT Atlantique | I21: IMT Atlantique | J21: Campus de Brest | K21: 83818 | L21: Public school / institute | M21: English | N21: Taught in English | O21: Bac +4 | P21: Eligible on level (4-yr BS ≈ Bac+4) | Q21: 1 | S21: 6500 | U21: 2 | V21: =IF(S21="","",S21*U21) | W21: Catalogue fee €6,500/yr (entered by institution). | X21: High | Y21: 6500 | AC21: Open | AD21: 2026-10-01 | AE21: 2027-03-15 | AF21: Yes | AG21: https://www.imt-atlantique.fr/en/study/masters/msc/it-embedded-ai | AH21: 100% taught in English Admission This program is aimed at graduates with a Bachelor of Science or equivalent degree obtained after 4 years' higher education in fields such as Computer Science, Electronics, Telecommunicat | AI21: Open in EEF
A22: 21 | B22: ★★★★★ | C22: 5 – Core fit (embedded/biomedical/health tech) | D22: IoT / Telecom / Networks | E22: Master of Science in Information technology (IT), track in Next-generation Networks for Agentic systems and IoT (NETAI) | F22: Master of Science in Information technology (IT), track in Next-generation Networks for Agentic systems and IoT (NETAI) | G22: Master indifférencié (recherche et professionnel) | H22: IMT Atlantique | I22: IMT Atlantique | J22: Campus de Rennes | L22: Public school / institute | M22: English | N22: Taught in English | O22: Bac +4 / Bac +5 | P22: Eligible on level (4-yr BS ≈ Bac+4) | Q22: 1/2 | S22: 6500 | U22: 2 | V22: =IF(S22="","",S22*U22) | W22: Catalogue fee €6,500/yr (entered by institution). | X22: High | Y22: 6500 | AC22: Open | AD22: 2026-10-01 | AE22: 2027-03-15 | AF22: Yes | AG22: https://www.imt-atlantique.fr/en/study/masters/msc/it-aeiot | AH22: 100% taught in English Admission This program is aimed at graduates with a Bachelor of Science or equivalent degree obtained after 4 years' higher education in Electronics and/or Computer Science. A good background in Ma | AI22: Open in EEF
A23: 22 | B23: ★★★★★ | C23: 5 – Core fit (embedded/biomedical/health tech) | D23: Biomedical / Health tech | E23: Master recherche mention International Master in BioMedical Engineering | F23: Research Master – major: International Master in BioMedical Engineering | G23: Master recherche | H23: Centrale Lille Institut | I23: Centrale Lille Institut | J23: Site de Villeneuve d'Ascq | K23: 20048 F | L23: Public school / institute | M23: English | N23: Taught in English | O23: Bac +4 | P23: Eligible on level (4-yr BS ≈ Bac+4) | Q23: 1 | R23: 12 | S23: 7500 | U23: 1 | V23: =IF(S23="","",S23*U23) | W23: Catalogue fee €7,500/yr (entered by institution). | X23: High | Y23: 7500 | Z23: Fees: 5 000€ including a personal laptop, project material, pe | AC23: Open | AD23: 2026-10-01 | AE23: 2027-03-15 | AF23: Yes | AG23: https://centralelille.fr/en/formation/masters/master-biomedical-engineering/ | AH23: Background in Physics or Mechanical Engineering or Electronics is expected but students with Medical, Biotech or Computer Sciences skills are eligible and may also apply. Applicants must be fluent in English - written an | AI23: Open in EEF
A24: 23 | B24: ★★★★★ | C24: 5 – Core fit (embedded/biomedical/health tech) | D24: Embedded systems / Electronics | E24: Master of Science (MSc) parcours MSc-Master of Science® in Intelligent Embedded Systems Engineering | F24: Master of Science (MSc) parcours MSc-Master of Science® in Intelligent Embedded Systems Engineering | G24: Master of Science (MSc) | H24: Institut supérieur de l'électronique et du numérique Toulon | J24: ISEN Méditerranée - Campus Toulon | K24: 83000 France | L24: Private / EESPIG | M24: English | N24: Taught in English | O24: Bac +3 | P24: Eligible on level (4-yr BS ≈ Bac+4) | Q24: 1 | R24: 15 | S24: 8800 | U24: 2 | V24: =IF(S24="","",S24*U24) | W24: Catalogue fee €8,800/yr (entered by institution). | X24: High | Y24: 8800 | AC24: Open | AD24: 2026-10-01 | AE24: 2027-03-15 | AF24: Yes | AG24: https://isen-mediterranee.fr/en/formation/msc-master-of-science-in-intelligent-embedded-systems-engineering/ | AH24: Admission This program is open to students who have completed a three-year degree in a field related to the program, or who hold an RNCP 6 qualification. | AI24: Open in EEF
A25: 24 | B25: ★★★★★ | C25: 5 – Core fit (embedded/biomedical/health tech) | D25: Embedded systems / Electronics | E25: International Master of Science in Electronics for Embedded ApplicationS | F25: International Master of Science in Electronics for Embedded ApplicationS | G25: Master indifférencié (recherche et professionnel) | H25: Institut national des sciences appliquées de Toulouse | J25: Site de Toulouse | K25: 31077 Toulouse Cedex | L25: Public school / institute | M25: English | N25: Taught in English | O25: Bac +4 / Bac +5 | P25: Eligible on level (4-yr BS ≈ Bac+4) | Q25: 1/2 | R25: 9 | S25: 9000 | U25: 2 | V25: =IF(S25="","",S25*U25) | W25: Catalogue fee €9,000/yr (entered by institution). | X25: High | Y25: 9000 | Z25: ucation English proficiency Fluent French proficiency Not required Tuition fees are 9 000 € including administrative registration and health … Fees can be reduced to 5 000 € under specific conditions : - top level stud | AC25: Open | AD25: 2026-10-01 | AE25: 2027-03-15 | AF25: Yes | AG25: http://www.insa-toulouse.fr/fr/formation.html | AH25: All courses are taught in English Admission Bachelor of Sciences or Engineering degree or 4 years in higher education English proficiency Fluent French proficiency Not required Tuition fees are 9 000 € including administ | AI25: Open in EEF
A26: 25 | B26: ★★★★★ | C26: 5 – Core fit (embedded/biomedical/health tech) | D26: Embedded systems / Electronics | E26: Master indifférencié (recherche et professionnel) MSc - Electronic Systems for Embedded and Communicating Applications (ESECA) | F26: MSc - Electronic Systems for Embedded and Communicating Applications (ESECA) | G26: Master indifférencié (recherche et professionnel) | H26: École nationale supérieure d'électrotechnique, d'électronique, d'informatique, d'hydraulique et des télécommunications | I26: Institut national polytechnique de Toulouse | J26: Site de Toulouse | K26: 31071 Toulouse Cedex | L26: Public school / institute | M26: English | N26: Taught in English | O26: Bac +4 / Bac +5 | P26: Eligible on level (4-yr BS ≈ Bac+4) | Q26: 1/2 | R26: 12 | S26: 9000 | U26: 2 | V26: =IF(S26="","",S26*U26) | W26: Catalogue fee €9,000/yr (entered by institution). | X26: High | Y26: 9000 | Z26: excellent level, or coming from associated universities, the fees are lowered to 5 , 473 €/year … excellent level, or coming from associated universities, the fees are lowered to 5 , 473 €/year | AC26: Open | AD26: 2026-10-01 | AE26: 2027-03-15 | AF26: Yes | AI26: Open in EEF
A27: 26 | B27: ★★★★★ | C27: 5 – Core fit (embedded/biomedical/health tech) | D27: Biomedical / Health tech | E27: Master of Science (MSc) Biomedical and Health Engineering | F27: Master of Science (MSc) Biomedical and Health Engineering | G27: Master of Science (MSc) | H27: JUNIA | I27: Université catholique de Lille | J27: Lille | L27: Private / EESPIG | M27: English | N27: Taught in English | O27: Bac +4 | P27: Eligible on level (4-yr BS ≈ Bac+4) | Q27: 1 | R27: 12 | S27: 9527 | U27: 1 | V27: =IF(S27="","",S27*U27) | W27: Catalogue fee €9,527/yr (entered by institution). | X27: High | Y27: 9527 | AC27: Open | AD27: 2026-10-01 | AE27: 2027-03-15 | AF27: Yes | AG27: https://www.junia.com/en/home/ | AH27: Minimum Bachelor degree in Life sciences (biology, health science or any related field), general engineering, physics. B2 level in English certified by an official test score (TOEFL, TOEIC, IELTS) except for students fro | AI27: Open in EEF
A28: 27 | B28: ★★★★★ | C28: 5 – Core fit (embedded/biomedical/health tech) | D28: Embedded systems / Electronics | E28: Diplôme d'ingénieur Master of Science and Engineering ISEN – Electronics and Embedded systems | F28: Engineering diploma Master of Science and Engineering ISEN – Electronics and Embedded systems | G28: Diplôme d'ingénieur | H28: JUNIA | I28: Université catholique de Lille | J28: Lille | L28: Private / EESPIG | M28: English | N28: Taught in English | O28: Bac +4 | P28: Eligible on level (4-yr BS ≈ Bac+4) | Q28: 1 | R28: 12 | S28: 9527 | U28: 2 | V28: =IF(S28="","",S28*U28) | W28: Catalogue fee €9,527/yr (entered by institution). | X28: High | Y28: 9527 | AC28: Open | AD28: 2026-10-01 | AE28: 2027-03-15 | AF28: Yes | AG28: https://www.junia.com/en/academics/master-of-science-and-engineering-in-electronics-and-embedded-systems/ | AH28: Minimum Bachelor degree in Physics, Electronics, IT engineering or equivalent. B2 level in English certified by an official test score (TOEFL, TOEIC, IELTS or equivalent) except for students from countries where English | AI28: Open in EEF
A29: 28 | B29: ★★★★★ | C29: 5 – Core fit (embedded/biomedical/health tech) | D29: Biomedical / Health tech | E29: Master of Science and Technology: Complex Systems Engineering track Biomedical Engineering | F29: Master of Science and Technology: Complex Systems Engineering track Biomedical Engineering | G29: Master indifférencié (recherche et professionnel) | H29: Ecole centrale de Marseille | J29: Ecole Centrale de Marseille | K29: 13013 MARSEILLE | L29: Public school / institute | M29: English | N29: Taught in English | O29: Bac +4 / Bac +5 | P29: Eligible on level (4-yr BS ≈ Bac+4) | Q29: 1/2 | R29: 24/12 | S29: 10270 | U29: 2 | V29: =IF(S29="","",S29*U29) | W29: Catalogue fee €10,270/yr (entered by institution). | X29: High | Y29: 10270 | Z29: you about our decision Deadline for applications: June 1st, 2026 Fees European Students: €6 750 / year* Non-European Students: €10 270 € / y … you about our decision Deadline for applications: June 1st, 2026 Fees Europ | AC29: Open | AD29: 2026-10-01 | AE29: 2027-03-15 | AF29: Yes | AG29: https://www.centrale-mediterranee.fr/fr/formation/masters/master-biomedical-engineering | AH29: The master’s course is fully taught in English - B2 level (independent user) is required. Entry level: Undergraduate / Bachelor's degree (180 ECTS) - with a strong background in sciences: physics, mechanics, applied math | AI29: Open in EEF
A30: 29 | B30: ★★★★★ | C30: 5 – Core fit (embedded/biomedical/health tech) | D30: Embedded systems / Electronics | E30: Mastère spécialisé© Embedded systems | F30: Specialised Master (MS)© Embedded systems | G30: Mastère spécialisé | H30: École nationale supérieure d'électrotechnique, d'électronique, d'informatique, d'hydraulique et des télécommunications | I30: Institut national polytechnique de Toulouse | J30: Site de Toulouse | K30: 31071 Toulouse Cedex | L30: Public school / institute | M30: English | N30: General | O30: Bac +5 | P30: Possible – MS rules allow Bac+4 + ≥3 yrs work experience (you have 3) | Q30: 1 | R30: 12 | S30: 13500 | U30: 1 | V30: =IF(S30="","",S30*U30) | W30: Catalogue fee €13,500/yr (entered by institution). | X30: High | Y30: 13500 | AC30: Open | AD30: 2026-10-01 | AE30: 2027-03-15 | AF30: Yes | AG30: http://www.enseeiht.fr | AH30: Niveau d’étude exigé : Bac+5 (Diplôme de Grande École d'ingénieur, DEA, master 2…) ou Bac+4 (maîtrise ou master1 avec expérience professionnelle d'au moins 3 années dans une fonction à responsabilités) | AI30: Open in EEF
A31: 30 | B31: ★★★★★ | C31: 5 – Core fit (embedded/biomedical/health tech) | D31: Embedded systems / Electronics | E31: Master recherche Master in Science and Technology, Electronic Embedded Systems | F31: Research Master Master in Science and Technology, Electronic Embedded Systems | G31: Master recherche | H31: Ecole supérieure d'ingénieurs en génie électrique | J31: Site de Saint-Etienne-du-Rouvray | L31: Private / EESPIG | M31: English | N31: Taught in English | O31: Bac +4 / Bac +5 | P31: Eligible on level (4-yr BS ≈ Bac+4) | Q31: 1/2 | R31: 24/18 | S31: 14000 | U31: 2 | V31: =IF(S31="","",S31*U31) | W31: Catalogue fee €14,000/yr (entered by institution). | X31: High | Y31: 17000/14000 | AC31: Open | AD31: 2026-10-01 | AE31: 2027-03-15 | AF31: Yes | AG31: https://esigelec.fr/fr | AH31: All courses are taught in English Admission Bachelor degree in engineering domains (Electronics, Computer Science,..) English proficiency Level equivalent to 6.0 at IELTS Interview in english with a representative of the | AI31: Open in EEF
A32: 31 | B32: ★★★★★ | C32: 5 – Core fit (embedded/biomedical/health tech) | D32: IoT / Telecom / Networks | E32: MSc&T Internet of Things: Innovation and Management Program | F32: MSc&T Internet of Things: Innovation and Management Program | G32: Master indifférencié (recherche et professionnel) | H32: Ecole polytechnique | J32: Site de Palaiseau | L32: Public school / institute | M32: English | N32: Taught in English | O32: Bac +4 | P32: Eligible on level (4-yr BS ≈ Bac+4) | Q32: 1 | S32: 15500 | U32: 2 | V32: =IF(S32="","",S32*U32) | W32: Not in catalogue. École polytechnique MSc&T programs cost €15,500–19,200/yr (official page); IoT fee not published – verify. | X32: Low | AC32: Open | AD32: 2026-10-01 | AE32: 2027-03-15 | AF32: Yes | AG32: https://bit.ly/3sYFUba | AH32: Les candidats doivent être diplômés d’un Bachelor ( licence ) en science, technologie, ingénierie, mathématiques . Des candidats issus d’autres formations peuvent être pris en considération, à condition qu’ils aient de s | AI32: Open in EEF
A33: 32 | B33: ★★★★★ | C33: 5 – Core fit (embedded/biomedical/health tech) | D33: Embedded systems / Electronics | E33: Master in Sciences & Technology, major "Embedded Electronic Systems" | F33: Master in Sciences & Technology, major "Embedded Electronic Systems" | G33: Master indifférencié (recherche et professionnel) | H33: Ecole supérieure d'ingénieurs en génie électrique | J33: Site de Saint-Etienne-du-Rouvray | L33: Private / EESPIG | M33: English | N33: Taught in English | O33: Bac +4 / Bac +5 | P33: Eligible on level (4-yr BS ≈ Bac+4) | Q33: 1/2 | R33: 24 | S33: 17000 | U33: 2 | V33: =IF(S33="","",S33*U33) | W33: Catalogue fee €17,000/yr (entered by institution). | X33: High | Y33: 17000 | AC33: Open | AD33: 2026-10-01 | AE33: 2027-03-15 | AF33: Yes | AG33: http://www.esigelec.fr | AH33: All courses are taught in English Admission Bachelor degree in engineering domains (Electronics, Computer Science,..) English proficiency Level equivalent to 6.0 at IELTS Interview in english with a representative of the | AI33: Open in EEF
A34: 33 | B34: ★★★★★ | C34: 5 – Core fit (embedded/biomedical/health tech) | D34: Embedded systems / Electronics | E34: Mastère Spécialisé® / Advanced Master EMS Embedded Systems | F34: Mastère Spécialisé® / Advanced Master EMS Embedded Systems | G34: Mastère spécialisé | H34: Institut supérieur de l'aéronautique et de l'espace | J34: Site de Toulouse | L34: Public school / institute | M34: English | N34: General | O34: Bac +6 | P34: Possible – MS rules allow Bac+4 + ≥3 yrs work experience (you have 3) | Q34: 1 | R34: 12 | S34: 17000 | U34: 1 | V34: =IF(S34="","",S34*U34) | W34: ISAE-SUPAERO Advanced Master: €17,000 (non-EU self-funded) / €23,000 company-funded – 2025-26 rates (official site). | X34: High | AC34: Open | AD34: 2026-10-01 | AE34: 2027-03-15 | AF34: Yes | AG34: https://www.tsaae.fr/ | AH34: Candidates can apply for our programme with the following backgrounds: Engineering degree Master 2 Master 1 with three years’ post-graduate professional experience A Master’s degree from a business school that is a membe | AI34: Open in EEF
A35: 34 | B35: ★★★★★ | C35: 5 – Core fit (embedded/biomedical/health tech) | D35: Embedded systems / Electronics | E35: Mastère Spécialisé® / Advanced Master EMS Embedded Systems | F35: Mastère Spécialisé® / Advanced Master EMS Embedded Systems | G35: Mastère spécialisé | H35: Institut supérieur de l'aéronautique et de l'espace | J35: Site de Toulouse | L35: Public school / institute | M35: English | N35: Taught in English | O35: Bac +6 | P35: Possible – MS rules allow Bac+4 + ≥3 yrs work experience (you have 3) | Q35: 1 | R35: 12 | S35: 17000 | U35: 1 | V35: =IF(S35="","",S35*U35) | W35: ISAE-SUPAERO Advanced Master: €17,000 (non-EU self-funded) / €23,000 company-funded – 2025-26 rates (official site). | X35: High | AC35: Open | AD35: 2026-10-01 | AE35: 2027-03-15 | AF35: Yes | AG35: https://www.tsaae.fr/ | AH35: Candidates can apply for our programme with the following backgrounds: Engineering degree Master 2 Master 1 with three years’ post-graduate professional experience A Master’s degree from a business school that is a membe | AI35: Open in EEF
A36: 35 | B36: ★★★★★ | C36: 5 – Core fit (embedded/biomedical/health tech) | D36: IoT / Telecom / Networks | E36: Master Sciences, technologies et santé mention Réseaux et Télécommunication parcours Internet des Objets | F36: Master Sciences, Technologies & Health – major: Networks & Telecommunication – track: Internet of Things | G36: Master indifférencié (recherche et professionnel) | H36: EURECOM | J36: EURECOM | K36: 06410 Biot - Sophia Antipolis | L36: Private / EESPIG | M36: English | N36: General | O36: Bac +4 | P36: Eligible on level (4-yr BS ≈ Bac+4) | Q36: 1 | R36: 24 | S36: 18000 | U36: 2 | V36: =IF(S36="","",S36*U36) | W36: Catalogue fee €18,000/yr (entered by institution). | X36: High | Y36: 18000 | Z36: dmission définitive dans le programme est conditionnée à la réception d’un acompte de 1000€ sur les frais de formation | AC36: Open | AD36: 2026-10-01 | AE36: 2027-03-15 | AF36: Yes | AG36: https://www.eurecom.fr/fr/les-formations/master-en-reseaux-et-telecommunication/master-en-reseaux-et-telecommunication-1 | AH36: Pour être éligibles, les candidats doivent être titulaires: un diplôme de grade de Licence/Bachelor ou diplôme équivalent à 3 années minimum d'études supérieures d'une université réputée dans le domaine des technologies | AI36: Open in EEF
A37: 36 | B37: ★★★★★ | C37: 5 – Core fit (embedded/biomedical/health tech) | D37: Biomedical / Health tech | E37: Master Sciences, Technologies & Health in Networks & Telecommunication - Internet of Things track | F37: Master Sciences, Technologies & Health in Networks & Telecommunication - Internet of Things track | G37: Master indifférencié (recherche et professionnel) | H37: EURECOM | J37: EURECOM | K37: 06410 Biot - Sophia Antipolis | L37: Private / EESPIG | M37: English | N37: Taught in English | O37: Bac +4 | P37: Eligible on level (4-yr BS ≈ Bac+4) | Q37: 1 | R37: 24 | S37: 18000 | U37: 2 | V37: =IF(S37="","",S37*U37) | W37: Catalogue fee €18,000/yr (entered by institution). | X37: High | Y37: 18000 | Z37: h or French Final admission to the program is contingent upon the receipt of a deposit of €1000 on tuition fees | AC37: Open | AD37: 2026-10-01 | AE37: 2027-03-15 | AF37: Yes | AG37: https://www.eurecom.fr/en/teaching/master-networks-and-telecommunication/msc-networks-and-telecommunication-internet-things | AH37: To be eligible, candidates must hold: a Bachelor's degree or diploma equivalent to at least 3 years of higher education from a reputable university in the field of information and communication technologies. (Computer sc | AI37: Open in EEF
A38: 37 | B38: ★★★★☆ | C38: 4 – Strong fit (electronics/signal/robotics/IoT/sensors) | D38: Robotics / Automation / Mechatronics | E38: Master indifférencié (recherche et professionnel) mention Automatique et Systèmes Électriques1 parcours Energie électrique et développement durable / electrical engineering for sustainable development. | F38: major: Automation & Systems Electrical1 – track: Energy Electrical & Development Sustainable / electrical engineering for sustainable development. | G38: Master indifférencié (recherche et professionnel) | H38: Faculté des sciences et technologies | I38: Université de Lille | J38: Département Electronique, électrotechnique et automatique | L38: Public university | M38: English | N38: Taught in English | O38: Bac +4 / Bac +5 | P38: Eligible on level (4-yr BS ≈ Bac+4) | Q38: 1/2 | R38: 12 | S38: 255 | U38: 2 | V38: =IF(S38="","",S38*U38) | W38: Catalogue lists €255 (EU/national rate). Confirm whether non-EU surcharge applies. | X38: Medium | Y38: 255/3950 | AA38: Lille opposed the decree; continues exemptions for part of non-EU students (master €254 if exempted). Apply for exemption early. | AB38: https://observalgerie.com/2026/06/13/misc/frais-dinscription-en-france-lille-maintient-un-avantage-pour-les-etudiants-etrangers/ | AC38: Open | AD38: 2026-10-01 | AE38: 2027-03-15 | AF38: No | AG38: https://formation.univ-lille.fr/fr/offre-de-formation/master-lmd-XB/master-automatique-et-systemes-electriques-MG001978/energie-electrique-et-developpement-durable-electrical-engineering-for-sustainable-development-m2-MX002024.html | AH38: Le candidat doit avoir un niveau M1 ou équivalent en EEA (Electronique, Electrotechique et Automatique). Niveau d'anglais C1 exigé. | AI38: Open in EEF
A39: 38 | B39: ★★★★☆ | C39: 4 – Strong fit (electronics/signal/robotics/IoT/sensors) | D39: Neuroscience / Neuro-engineering | E39: Euro-mediterranean Master in Neurosciences Online - | F39: Euro-mediterranean Master in Neuroscience Online | G39: Master indifférencié (recherche et professionnel) | H39: Faculté des sciences de la vie | I39: Université de Strasbourg | J39: Site de Strasbourg | K39: 67000 Strasbourg | L39: Public university | M39: English | N39: General | O39: Bac +4 | P39: Eligible on level (4-yr BS ≈ Bac+4) | Q39: 1 | S39: 3950 | T39: 255 | U39: 2 | V39: =IF(S39="","",S39*U39) | W39: Catalogue: €3,950. = national differentiated master fee (2026-27: €3,950). Exemption to ~€255 possible (university quota). | X39: High | Y39: 3950 | AA39: Unistra: master entrants who did not do their licence at Unistra pay the differentiated fee (€3,950). | AB39: https://www.unistra.fr/fr/node/8168 | AC39: Open | AD39: 2026-10-01 | AE39: 2027-03-15 | AF39: No | AG39: http://sciencesvie.unistra.fr/ | AH39: Le programme propose un cursus international en neuroscience, avec des cours et des évaluations identiques dispensés par chacune des 4 Universités Françaises ainsi que 14 partenaires issus d’Europe et de la zone méditerr | AI39: Open in EEF
